Workbook
Name IQ_CH: 110000
Name IQ_CQ: 5000
Name IQ_CY: 10000
Name IQ_DAILY: 500000
Name IQ_FH: 100000
Name IQ_FQ: 500
Name IQ_FY: 1000
Name IQ_LTM: 2000
Name IQ_MONTH: 15000
Name IQ_NTM: 6000
Name IQ_WEEK: 50000
Name IQ_YTD: 3000

Sheet Cover

Sheet Input Sheet
B3: Please provide the below inputs
B5: Name of the Company | C5: Epigral Ltd.
B8: Wacc Inputs
B9: Country | C9: India
B10: Local Currency 10Y Government Bond | C10: 0.067
B11: =C9&"'s"&" Moody's Soverign Rating " -> India's Moody's Soverign Rating | C11: =VLOOKUP(C9,'Damodaran Data'!B4:D161,3,) -> Baa3
B12: Credit default spread as per Dr Damodaran | C12: =VLOOKUP(C9,'Damodaran Data'!B4:E161,4,) -> 0.021609858
B13: Implied US Equity Risk Premium | C13: 0.0418
B14: Asset Beta | C14: 1.02
B15: Asset Beta Variation (+/-) | C15: 0.15
B16: Debt to Eauity Ratio | C16: ='Assumptions Working'!$H$885 -> 0.26207983
B17: Debt to Capital (Gearing) | C17: ='Assumptions Working'!$H$886 -> 0.2076571
B18: Marginal Tax Rate | C18: 0.2517
B19: Company Credit Rating Available | C19: No
B20: Company is Small or Large Firm ? | C20: L | G20: L | H20: Yes
B21: Provide Credit Rating | C21: A1/A+ | G21: S | H21: No
B22: Interest Coverage Ratio | C22: ='3 Statement Model'!H31/'3 Statement Model'!H35 -> 10.921509
B23: ICR Based Corporate Default Spread | C23: =IF(C20="L",VLOOKUP(C22,'Damodaran Data'!G6:J21,4,TRUE),VLOOKUP(C22,'Damodaran Data'!L6:O21,4,TRUE)) -> 0.004
B24: Small Size Premium | C24: 0.1222
B25: Assets Specific Risk Premium | C25: 0

Sheet Valuation Summary
B1: Valuation Summary
A4: # | B4: Valuation Methods | C4: Enterprise Value | D4: Equity Value Available for Equity Shareholders | E4: Value Per Share | F4: Market Price | G4: Discount/ Premium | H4: Discount/ Premium % | I4: Interpretaion
B6: Discounted Cash Flow - Perpetuity Growth | C6: 4587.7173 | D6: 4186.6783 | E6: 971.38708 | F6: 884 | G6: =E6-F6 -> 87.387081 | H6: =G6/F6 -> 0.098854164 | I6: Slight undervaluation
B7: Discounted Cash Flow - Exit Multiple | C7: 9089.6091 | D7: 8688.5701 | E7: 2015.9095 | F7: 884 | G7: =E7-F7 -> 1131.9095 | H7: =G7/F7 -> 1.2804407 | I7: Very undervalued
B8: Relative Valuation - EV/EBITDA | C8: 7064.0054 | D8: 6662.9664 | E8: 1545.9319 | F8: 884 | G8: =E8-F8 -> 661.93188 | H8: =G8/F8 -> 0.74879172 | I8: Undervalued
B9: Relative Valuation - EV/Sales | C9: 2307.7093 | D9: 1906.6703 | E9: 442.3829 | F9: 884 | G9: =E9-F9 -> -441.6171 | H9: =G9/F9 -> -0.49956685 | I9: Overvalued
B10: Relative Valuation - Price/Earnings | C10: 13122.327 | D10: 12721.288 | E10: 2951.575 | F10: 884 | G10: =E10-F10 -> 2067.575 | H10: =G10/F10 -> 2.3388858 | I10: Very undervalued

Sheet Beta Calculation
B2: Peers Calculations | C2: 2 Years Weekly Equity Beta | D2: 2 Years Avg D/E | E2: 2 Years avg D/(D+E) | F2: 2 Yearly Asset Beta | H2: 5 Years MonthLy Equity Beta | I2: 5 Years Avg D/E | J2: 5 Years avg D/(D+E) | K2: 5 Yearly Asset Beta
B3: Gujarat Alkalies & Chemicals Ltd (GAKL) | C3: =I209 -> 1.160871 | D3: =H90 -> 0.049479626 | E3: =H92 -> 0.045024077 | F3: =C3/(1+(1-$M$3)*D3) -> 1.1194237 | H3: =I79 -> 1.5204461 | I3: =H94 -> 0.077913959 | J3: =H95 -> 0.070993764 | K3: =H3/(1+(1-$M$3)*I3) -> 1.4366831 | M3: 0.2517
B4: Gujarat Narmada Valley Fertilizers & Chemicals Ltd (GNFC) | C4: =M209 -> 1.3114087 | D4: =N90 -> 0.0063605645 | E4: =N92 -> 0.0062850462 | F4: =C4/(1+(1-$M$3)*D4) -> 1.3051965 | H4: =M79 -> 1.2939189 | I4: =N94 -> 0.0027700594 | J4: =N95 -> 0.0027397431 | K4: =H4/(1+(1-$M$3)*I4) -> 1.2912424
B5: Grasim Industries Ltd | C5: =Q209 -> 1.2088705 | D5: =T90 -> 1.7289794 | E5: =T92 -> 0.6319277 | F5: =C5/(1+(1-$M$3)*D5) -> 0.52701761 | H5: =Q79 -> 1.1622769 | I5: =T94 -> 1.3922632 | J5: =T95 -> 0.57489838 | K5: =H5/(1+(1-$M$3)*I5) -> 0.56923278
B6: Chemplast Sanmar Ltd | C6: =U209 -> 1.202175 | D6: =Z90 -> 0.90038429 | E6: =Z92 -> 0.47377702 | F6: =C6/(1+(1-$M$3)*D6) -> 0.71824921 | H6: =U79 -> 1.0602292 | I6: =Z94 -> 0.57330196 | J6: =Z95 -> 0.56792781 | K6: =H6/(1+(1-$M$3)*I6) -> 0.74193691
B7: SRF | C7: =Y209 -> 0.80010021 | D7: =AF90 -> 0.40629279 | E7: =AF92 -> 0.28854247 | F7: =C7/(1+(1-$M$3)*D7) -> 0.61356018 | H7: =Y79 -> 0.95707112 | I7: =AF94 -> 0.43578461 | J7: =AF95 -> 0.30292616 | K7: =H7/(1+(1-$M$3)*I7) -> 0.72171996
B8: TGV SRACC LTD | C8: =AC209 -> 1.3395297 | D8: =AL90 -> 0.29796962 | E8: =AL92 -> 0.22955411 | F8: =C8/(1+(1-$M$3)*D8) -> 1.0953081 | H8: =AC79 -> 0.71612139 | I8: =AL94 -> 0.4516278 | J8: =AL95 -> 0.2949532 | K8: =H8/(1+(1-$M$3)*I8) -> 0.53523655
B9: Primo Chemicals | C9: =AG209 -> 0.71670229 | D9: =AR90 -> 0.44664083 | E9: =AR92 -> 0.30868491 | F9: =C9/(1+(1-$M$3)*D9) -> 0.53716896 | H9: =AG79 -> 0.34179507 | I9: =AR94 -> 0.29530943 | J9: =AR95 -> 0.21378119 | K9: =H9/(1+(1-$M$3)*I9) -> 0.27993502
B10: Deepak Nitrite | C10: =AK209 -> 1.0388116 | D10: =AX90 -> 0.14739261 | E10: =AX92 -> 0.12333011 | F10: =C10/(1+(1-$M$3)*D10) -> 0.93561856 | H10: =AK79 -> 1.5441467 | I10: =AX94 -> 0.13169868 | J10: =AX95 -> 0.11027597 | K10: =H10/(1+(1-$M$3)*I10) -> 1.4056224
B11: EPIGRAL | C11: =AO209 -> 1.6715682 | D11: =BD90 -> 0.53978853 | E11: =BD92 -> 0.33595745 | F11: =C11/(1+(1-$M$3)*D11) -> 1.1906403 | H11: =AO79 -> 1.5680078 | I11: =BD94 -> 0.97148972 | J11: =BD95 -> 0.46285376 | K11: =H11/(1+(1-$M$3)*I11) -> 0.90795533
D13: x | E13: Nifty
B14: Calculations 5 Yearly Monthly | D14: Y | E14: All
B16: Nifty 50 Index | C16: Nifty 50 Index | G16: Gujarat Alkalies & Chemicals Ltd (GAKL) | K16: Gujarat Narmada Valley Fertilizers & Chemicals Ltd (GNFC) | O16: Grasim Industries Ltd | S16: Chemplast
C17: Date | D17: Price | E17: Nifty 50 Returns | G17: Date | H17: Price | I17: GAKL | K17: Date | L17: Price | M17: GNFC | O17: Date | P17: Price | Q17: Grasim | S17: Date | T17: Price | U17: Chemplast | W17: Date | X17: Price | Y17: SRFL | AA17: Date | AB17: Price | AC17: TGVS | AE17: Date | AF17: Price | AG17: Primo | AI17: Date | AJ17: Price | AK17: DPNT | AM17: Date | AN17: Price | AO17: Epigral
C18: 46054 | D18: 24964.55 | G18: 46054 | H18: 439.5 | K18: 46054 | L18: 464.4 | O18: 46054 | P18: 2758.2 | S18: 46054 | T18: 249.35 | W18: 46054 | X18: 2771.5 | AA18: 46054 | AB18: 85.09 | AE18: 46054 | AF18: 19.8 | AI18: 46054 | AJ18: 1604.5 | AM18: 46054 | AN18: 922.8
C19: 46023 | D19: 25320.65 | E19: =D19/D18-1 -> 0.014264227 | G19: 46023 | H19: 455.95 | I19: =H19/H18-1 -> 0.037428896 | K19: 46023 | L19: 466.8 | M19: =L19/L18-1 -> 0.0051679587 | O19: 46023 | P19: 2819 | Q19: =P19/P18-1 -> 0.022043362 | S19: 46023 | T19: 260.25 | U19: =T19/T18-1 -> 0.043713656 | W19: 46023 | X19: 2816.3 | Y19: =X19/X18-1 -> 0.016164532 | AA19: 46023 | AB19: 87.2 | AC19: =AB19/AB18-1 -> 0.024797273 | AE19: 46023 | AF19: 20.14 | AG19: =AF19/AF18-1 -> 0.017171717 | AI19: 46023 | AJ19: 1642.5 | AK19: =AJ19/AJ18-1 -> 0.02368339 | AM19: 46023 | AN19: 1043.1 | AO19: =AN19/AN18-1 -> 0.13036411
C20: 45992 | D20: 26129.6 | E20: =D20/D19-1 -> 0.031948232 | G20: 45992 | H20: 504.25 | I20: =H20/H19-1 -> 0.10593267 | K20: 45992 | L20: 493.75 | M20: =L20/L19-1 -> 0.057733505 | O20: 45992 | P20: 2829 | Q20: =P20/P19-1 -> 0.0035473572 | S20: 45992 | T20: 261.2 | U20: =T20/T19-1 -> 0.0036503362 | W20: 45992 | X20: 3075 | Y20: =X20/X19-1 -> 0.091858112 | AA20: 45992 | AB20: 111.4 | AC20: =AB20/AB19-1 -> 0.27752294 | AE20: 45992 | AF20: 23.95 | AG20: =AF20/AF19-1 -> 0.18917577 | AI20: 45992 | AJ20: 1731.7 | AK20: =AJ20/AJ19-1 -> 0.054307458 | AM20: 45992 | AN20: 1220.1 | AO20: =AN20/AN19-1 -> 0.16968651
C21: 45962 | D21: 26202.95 | E21: =D21/D20-1 -> 0.0028071612 | G21: 45962 | H21: 530.5 | I21: =H21/H20-1 -> 0.052057511 | K21: 45962 | L21: 497.95 | M21: =L21/L20-1 -> 0.0085063291 | O21: 45962 | P21: 2739.4 | Q21: =P21/P20-1 -> -0.031671969 | S21: 45962 | T21: 284.2 | U21: =T21/T20-1 -> 0.08805513 | W21: 45962 | X21: 2927.3 | Y21: =X21/X20-1 -> -0.04803252 | AA21: 45962 | AB21: 114.15 | AC21: =AB21/AB20-1 -> 0.024685817 | AE21: 45962 | AF21: 25.52 | AG21: =AF21/AF20-1 -> 0.065553236 | AI21: 45962 | AJ21: 1558.6 | AK21: =AJ21/AJ20-1 -> -0.099959577 | AM21: 45962 | AN21: 1511.7 | AO21: =AN21/AN20-1 -> 0.2389968
C22: 45931 | D22: 25722.1 | E22: =D22/D21-1 -> -0.018350987 | G22: 45931 | H22: 572.05 | I22: =H22/H21-1 -> 0.078322337 | K22: 45931 | L22: 502.95 | M22: =L22/L21-1 -> 0.010041169 | O22: 45931 | P22: 2891.7 | Q22: =P22/P21-1 -> 0.055596116 | S22: 45931 | T22: 398.85 | U22: =T22/T21-1 -> 0.40341309 | W22: 45931 | X22: 2930.5 | Y22: =X22/X21-1 -> 0.0010931575 | AA22: 45931 | AB22: 120.55 | AC22: =AB22/AB21-1 -> 0.056066579 | AE22: 45931 | AF22: 23.55 | AG22: =AF22/AF21-1 -> -0.077194357 | AI22: 45931 | AJ22: 1728.4 | AK22: =AJ22/AJ21-1 -> 0.10894392 | AM22: 45931 | AN22: 1689.7 | AO22: =AN22/AN21-1 -> 0.11774823
C23: 45901 | D23: 24611.1 | E23: =D23/D22-1 -> -0.04319243 | G23: 45901 | H23: 546.55 | I23: =H23/H22-1 -> -0.044576523 | K23: 45901 | L23: 491 | M23: =L23/L22-1 -> -0.023759817 | O23: 45901 | P23: 2756.9 | Q23: =P23/P22-1 -> -0.046616177 | S23: 45901 | T23: 388.9 | U23: =T23/T22-1 -> -0.024946722 | W23: 45901 | X23: 2823.6 | Y23: =X23/X22-1 -> -0.036478417 | AA23: 45901 | AB23: 119.05 | AC23: =AB23/AB22-1 -> -0.01244297 | AE23: 45901 | AF23: 23.76 | AG23: =AF23/AF22-1 -> 0.0089171975 | AI23: 45901 | AJ23: 1835.1 | AK23: =AJ23/AJ22-1 -> 0.061733395 | AM23: 45901 | AN23: 1691.1 | AO23: =AN23/AN22-1 -> 0.00082854945
C24: 45870 | D24: 24426.85 | E24: =D24/D23-1 -> -0.0074864594 | G24: 45870 | H24: 564.3 | I24: =H24/H23-1 -> 0.032476443 | K24: 45870 | L24: 522.75 | M24: =L24/L23-1 -> 0.064663951 | O24: 45870 | P24: 2775.6 | Q24: =P24/P23-1 -> 0.0067829809 | S24: 45870 | T24: 427.3 | U24: =T24/T23-1 -> 0.098740036 | W24: 45870 | X24: 2836.4 | Y24: =X24/X23-1 -> 0.00453322 | AA24: 45870 | AB24: 125.6 | AC24: =AB24/AB23-1 -> 0.0550189 | AE24: 45870 | AF24: 25.67 | AG24: =AF24/AF23-1 -> 0.080387205 | AI24: 45870 | AJ24: 1787.9 | AK24: =AJ24/AJ23-1 -> -0.025720669 | AM24: 45870 | AN24: 1811.4 | AO24: =AN24/AN23-1 -> 0.07113713
C25: 45839 | D25: 24768.35 | E25: =D25/D24-1 -> 0.013980517 | G25: 45839 | H25: 581.6 | I25: =H25/H24-1 -> 0.030657452 | K25: 45839 | L25: 540.8 | M25: =L25/L24-1 -> 0.034528934 | O25: 45839 | P25: 2746.4 | Q25: =P25/P24-1 -> -0.010520248 | S25: 45839 | T25: 416.85 | U25: =T25/T24-1 -> -0.024455886 | W25: 45839 | X25: 3040.8 | Y25: =X25/X24-1 -> 0.072063179 | AA25: 45839 | AB25: 115.43 | AC25: =AB25/AB24-1 -> -0.080971338 | AE25: 45839 | AF25: 28.06 | AG25: =AF25/AF24-1 -> 0.093104792 | AI25: 45839 | AJ25: 1840.4 | AK25: =AJ25/AJ24-1 -> 0.029364058 | AM25: 45839 | AN25: 2019.2 | AO25: =AN25/AN24-1 -> 0.1147179
C26: 45809 | D26: 25517.05 | E26: =D26/D25-1 -> 0.030228094 | G26: 45809 | H26: 599.65 | I26: =H26/H25-1 -> 0.031035076 | K26: 45809 | L26: 553 | M26: =L26/L25-1 -> 0.022559172 | O26: 45809 | P26: 2844.5 | Q26: =P26/P25-1 -> 0.035719487 | S26: 45809 | T26: 439.05 | U26: =T26/T25-1 -> 0.053256567 | W26: 45809 | X26: 3242.1 | Y26: =X26/X25-1 -> 0.066199684 | AA26: 45809 | AB26: 98.25 | AC26: =AB26/AB25-1 -> -0.14883479 | AE26: 45809 | AF26: 25.81 | AG26: =AF26/AF25-1 -> -0.080185317 | AI26: 45809 | AJ26: 1987.1 | AK26: =AJ26/AJ25-1 -> 0.079710932 | AM26: 45809 | AN26: 1808.2 | AO26: =AN26/AN25-1 -> -0.10449683
C27: 45778 | D27: 24750.7 | E27: =D27/D26-1 -> -0.03003286 | G27: 45778 | H27: 574 | I27: =H27/H26-1 -> -0.042774952 | K27: 45778 | L27: 535.45 | M27: =L27/L26-1 -> -0.031735986 | O27: 45778 | P27: 2545.8 | Q27: =P27/P26-1 -> -0.10500967 | S27: 45778 | T27: 424.45 | U27: =T27/T26-1 -> -0.033253616 | W27: 45778 | X27: 2861 | Y27: =X27/X26-1 -> -0.11754727 | AA27: 45778 | AB27: 100.6 | AC27: =AB27/AB26-1 -> 0.023918575 | AE27: 45778 | AF27: 25.99 | AG27: =AF27/AF26-1 -> 0.0069740411 | AI27: 45778 | AJ27: 2027.3 | AK27: =AJ27/AJ26-1 -> 0.020230487 | AM27: 45778 | AN27: 1780.1 | AO27: =AN27/AN26-1 -> -0.015540316
C28: 45748 | D28: 24334.2 | E28: =D28/D27-1 -> -0.016827807 | G28: 45748 | H28: 605.7 | I28: =H28/H27-1 -> 0.055226481 | K28: 45748 | L28: 486.35 | M28: =L28/L27-1 -> -0.091698571 | O28: 45748 | P28: 2737.5 | Q28: =P28/P27-1 -> 0.075300495 | S28: 45748 | T28: 410.65 | U28: =T28/T27-1 -> -0.032512663 | W28: 45748 | X28: 3008.9 | Y28: =X28/X27-1 -> 0.051695211 | AA28: 45748 | AB28: 98.93 | AC28: =AB28/AB27-1 -> -0.016600398 | AE28: 45748 | AF28: 25.87 | AG28: =AF28/AF27-1 -> -0.0046171604 | AI28: 45748 | AJ28: 1935.6 | AK28: =AJ28/AJ27-1 -> -0.045232575 | AM28: 45748 | AN28: 1735.2 | AO28: =AN28/AN27-1 -> -0.025223302
C29: 45717 | D29: 23519.35 | E29: =D29/D28-1 -> -0.033485794 | G29: 45717 | H29: 579.2 | I29: =H29/H28-1 -> -0.043751032 | K29: 45717 | L29: 496.45 | M29: =L29/L28-1 -> 0.020766937 | O29: 45717 | P29: 2611.15 | Q29: =P29/P28-1 -> -0.046155251 | S29: 45717 | T29: 435.05 | U29: =T29/T28-1 -> 0.059417996 | W29: 45717 | X29: 2939.15 | Y29: =X29/X28-1 -> -0.023181229 | AA29: 45717 | AB29: 94.9 | AC29: =AB29/AB28-1 -> -0.040735874 | AE29: 45717 | AF29: 21.19 | AG29: =AF29/AF28-1 -> -0.18090452 | AI29: 45717 | AJ29: 1983.6 | AK29: =AJ29/AJ28-1 -> 0.024798512 | AM29: 45717 | AN29: 1904.1 | AO29: =AN29/AN28-1 -> 0.097337483
C30: 45689 | D30: 22124.7 | E30: =D30/D29-1 -> -0.059297982 | G30: 45689 | H30: 524.15 | I30: =H30/H29-1 -> -0.09504489 | K30: 45689 | L30: 468.85 | M30: =L30/L29-1 -> -0.055594723 | O30: 45689 | P30: 2306.65 | Q30: =P30/P29-1 -> -0.11661528 | S30: 45689 | T30: 404.6 | U30: =T30/T29-1 -> -0.069991955 | W30: 45689 | X30: 2795.4 | Y30: =X30/X29-1 -> -0.048908698 | AA30: 45689 | AB30: 91.82 | AC30: =AB30/AB29-1 -> -0.032455216 | AE30: 45689 | AF30: 26.14 | AG30: =AF30/AF29-1 -> 0.23360076 | AI30: 45689 | AJ30: 1851.3 | AK30: =AJ30/AJ29-1 -> -0.066696915 | AM30: 45689 | AN30: 1613.35 | AO30: =AN30/AN29-1 -> -0.15269681
... C71: 44440 | D71: 17618.15 | E71: =D71/D70-1 -> -0.0030274479 | G71: 44440 | H71: 672.75 | I71: =H71/H70-1 -> -0.1038961 | K71: 44440 | L71: 434.25 | M71: =L71/L70-1 -> -0.05720799 | O71: 44440 | P71: 1657.68 | Q71: =P71/P70-1 -> -0.030006554 | S71: 44440 | T71: 612.45 | U71: =T71/T70-1 -> -0.05863818 | W71: 44440 | X71: 2255.82 | Y71: =X71/X70-1 -> 0.065422944 | AA71: 44440 | AB71: 55.45 | AC71: =AB71/AB70-1 -> 0.0081818182 | AE71: 44440 | AF71: 26.02 | AG71: =AF71/AF70-1 -> -0.21814904 | AI71: 44440 | AJ71: 2406.55 | AK71: =AJ71/AJ70-1 -> 0.079001054 | AM71: 44440 | AN71: 778.2 | AO71: =AN71/AN70-1 -> -0.12236382
C72: 44409 | D72: 17132.2 | E72: =D72/D71-1 -> -0.027582351 | G72: 44409 | H72: 454.5 | I72: =H72/H71-1 -> -0.32441472 | K72: 44409 | L72: 332.6 | M72: =L72/L71-1 -> -0.23408175 | O72: 44409 | P72: 1489.82 | Q72: =P72/P71-1 -> -0.101262 | W72: 44409 | X72: 2027.95 | Y72: =X72/X71-1 -> -0.10101427 | AA72: 44409 | AB72: 34.6 | AC72: =AB72/AB71-1 -> -0.37601443 | AE72: 44409 | AF72: 22.72 | AG72: =AF72/AF71-1 -> -0.12682552 | AI72: 44409 | AJ72: 2283.6 | AK72: =AJ72/AJ71-1 -> -0.051089734
C73: 44378 | D73: 15763.05 | E73: =D73/D72-1 -> -0.079916765 | G73: 44378 | H73: 478.6 | I73: =H73/H72-1 -> 0.053025303 | K73: 44378 | L73: 384.7 | M73: =L73/L72-1 -> 0.15664462 | O73: 44378 | P73: 1536.31 | Q73: =P73/P72-1 -> 0.031205112 | W73: 44378 | X73: 1731.74 | Y73: =X73/X72-1 -> -0.14606376 | AA73: 44378 | AB73: 39.85 | AC73: =AB73/AB72-1 -> 0.1517341 | AE73: 44378 | AF73: 24.85 | AG73: =AF73/AF72-1 -> 0.09375 | AI73: 44378 | AJ73: 2039.2 | AK73: =AJ73/AJ72-1 -> -0.107024
C74: 44348 | D74: 15721.5 | E74: =D74/D73-1 -> -0.0026359112 | G74: 44348 | H74: 402.3 | I74: =H74/H73-1 -> -0.15942332 | K74: 44348 | L74: 377.2 | M74: =L74/L73-1 -> -0.019495711 | O74: 44348 | P74: 1484.22 | Q74: =P74/P73-1 -> -0.033905917 | W74: 44348 | X74: 1455.14 | Y74: =X74/X73-1 -> -0.15972375 | AA74: 44348 | AB74: 30.15 | AC74: =AB74/AB73-1 -> -0.2434128 | AE74: 44348 | AF74: 16.43 | AG74: =AF74/AF73-1 -> -0.338833 | AI74: 44348 | AJ74: 1807.63 | AK74: =AJ74/AJ73-1 -> -0.11355924
C75: 44317 | D75: 15582.8 | E75: =D75/D74-1 -> -0.0088223134 | G75: 44317 | H75: 402.45 | I75: =H75/H74-1 -> 0.00037285608 | K75: 44317 | L75: 375.85 | M75: =L75/L74-1 -> -0.0035790032 | O75: 44317 | P75: 1456.94 | Q75: =P75/P74-1 -> -0.018380025 | W75: 44317 | X75: 1302.63 | Y75: =X75/X74-1 -> -0.10480778 | AA75: 44317 | AB75: 34.7 | AC75: =AB75/AB74-1 -> 0.15091211 | AE75: 44317 | AF75: 17.57 | AG75: =AF75/AF74-1 -> 0.069385271 | AI75: 44317 | AJ75: 1784.49 | AK75: =AJ75/AJ74-1 -> -0.012801292
C76: 44287 | D76: 14631.1 | E76: =D76/D75-1 -> -0.061073748 | G76: 44287 | H76: 412.15 | I76: =H76/H75-1 -> 0.024102373 | K76: 44287 | L76: 361.85 | M76: =L76/L75-1 -> -0.037248902 | O76: 44287 | P76: 1388.16 | Q76: =P76/P75-1 -> -0.047208533 | W76: 44287 | X76: 1286.22 | Y76: =X76/X75-1 -> -0.012597591 | AA76: 44287 | AB76: 32.95 | AC76: =AB76/AB75-1 -> -0.050432277 | AE76: 44287 | AF76: 17.43 | AG76: =AF76/AF75-1 -> -0.0079681275 | AI76: 44287 | AJ76: 1864.65 | AK76: =AJ76/AJ75-1 -> 0.044920397
C77: 44256 | D77: 14690.7 | E77: =D77/D76-1 -> 0.0040735146 | G77: 44256 | H77: 344.8 | I77: =H77/H76-1 -> -0.16341138 | K77: 44256 | L77: 300.2 | M77: =L77/L76-1 -> -0.17037446 | O77: 44256 | P77: 1436.49 | Q77: =P77/P76-1 -> 0.034815871 | W77: 44256 | X77: 1082.16 | Y77: =X77/X76-1 -> -0.15865093 | AA77: 44256 | AB77: 24.25 | AC77: =AB77/AB76-1 -> -0.26403642 | AE77: 44256 | AF77: 17.85 | AG77: =AF77/AF76-1 -> 0.024096386 | AI77: 44256 | AJ77: 1655.65 | AK77: =AJ77/AJ76-1 -> -0.11208538
H79: Beta | I79: =SLOPE(I19:I77,$E$19:$E$77) -> 1.5204461 | M79: =SLOPE(M19:M77,$E$19:$E$77) -> 1.2939189 | Q79: =SLOPE(Q19:Q77,$E$19:$E$77) -> 1.1622769 | U79: =SLOPE(U19:U71,$E$19:$E$71) -> 1.0602292 | Y79: =SLOPE(Y19:Y77,$E$19:$E$77) -> 0.95707112 | AC79: =SLOPE(AC19:AC77,$E$19:$E$77) -> 0.71612139 | AG79: =SLOPE(AG19:AG77,$E$19:$E$77) -> 0.34179507 | AK79: =SLOPE(AK19:AK77,$E$19:$E$77) -> 1.5441467 | AO79: =SLOPE(AO19:AO71,$E$19:$E$71) -> 1.5680078
D83: GUCL | J83: GNFC | P83: Grasim | V83: Chemplast | AB83: SRF | AH83: TGV | AN83: Primo | AT83: Deepak Nitrite Ltd | AZ83: Epigral
D84: 2021 | E84: =D84+1 -> 2022 | F84: =E84+1 -> 2023 | G84: =F84+1 -> 2024 | H84: =G84+1 -> 2025 | J84: 2021 | K84: =J84+1 -> 2022 | L84: =K84+1 -> 2023 | M84: 2024 | N84: 2025 | P84: 2021 | Q84: =P84+1 -> 2022 | R84: =Q84+1 -> 2023 | S84: 2024 | T84: 2025 | V84: 2021 | W84: =V84+1 -> 2022 | X84: =W84+1 -> 2023 | Y84: 2024 | Z84: 2025 | AB84: 2021 | AC84: =AB84+1 -> 2022 | AD84: =AC84+1 -> 2023 | AE84: 2024 | AF84: 2025 | AH84: 2021 | AI84: =AH84+1 -> 2022 | AJ84: =AI84+1 -> 2023 | AK84: 2024 | AL84: 2025 | AN84: 2021 | AO84: =AN84+1 -> 2022 | AP84: =AO84+1 -> 2023 | AQ84: 2024 | AR84: 2025 | AT84: 2021 | AU84: =AT84+1 -> 2022 | AV84: =AU84+1 -> 2023 | AW84: 2024 | AX84: 2025 | AZ84: 2021 | BA84: =AZ84+1 -> 2022 | BB84: =BA84+1 -> 2023 | BC84: 2024 | BD84: 2025
B85: Debt | D85: 498 | E85: 594 | F85: 597 | H85: 561 | J85: 4 | K85: 2 | L85: 2 | M85: 3 | N85: 106 | P85: 79078 | Q85: 74744 | R85: 103039 | S85: 137155 | T85: 186326 | V85: 2127 | W85: 882 | X85: 1019 | Y85: 1548 | Z85: 1842 | AB85: 3469 | AC85: 3655 | AD85: 4478 | AE85: 5031 | AF85: 4726 | AH85: 499 | AI85: 461 | AJ85: 234 | AK85: 321 | AL85: 357 | AN85: 1 | AO85: 61 | AP85: 145 | AQ85: 178 | AR85: 169 | AT85: 590 | AU85: 315 | AV85: 73 | AW85: 286 | AX85: 1267 | AZ85: 753 | BA85: 993 | BB85: 879 | BC85: 964 | BD85: 593
B86: Total Equity | D86: =SUM(D87:D88) -> 5374 | E86: =SUM(E87:E88) -> 5899 | F86: =SUM(F87:F88) -> 6139 | G86: =SUM(G87:G88) -> 6075 | H86: =SUM(H87:H88) -> 5669 | J86: =SUM(J87:J88) -> 6068 | K86: =SUM(K87:K88) -> 7990 | L86: =SUM(L87:L88) -> 9105 | M86: =SUM(M87:M88) -> 8309 | N86: =SUM(N87:N88) -> 8576 | P86: =SUM(P87:P88) -> 65494 | Q86: =SUM(Q87:Q88) -> 75699 | R86: =SUM(R87:R88) -> 78742 | S86: =SUM(S87:S88) -> 88653 | T86: =SUM(T87:T88) -> 97509 | V86: =SUM(V87:V88) -> -350 | W86: =SUM(W87:W88) -> 1705 | X86: =SUM(X87:X88) -> 1858 | Y86: =SUM(Y87:Y88) -> 1701 | Z86: =SUM(Z87:Z88) -> 2068 | AB86: =SUM(AB87:AB88) -> 6856 | AC86: =SUM(AC87:AC88) -> 8565 | AD86: =SUM(AD87:AD88) -> 10327 | AE86: =SUM(AE87:AE88) -> 11479 | AF86: =SUM(AF87:AF88) -> 12626 | AH86: =SUM(AH87:AH88) -> 610 | AI86: =SUM(AI87:AI88) -> 743 | AJ86: =SUM(AJ87:AJ88) -> 1046 | AK86: =SUM(AK87:AK88) -> 1096 | AL86: =SUM(AL87:AL88) -> 1178 | AN86: =SUM(AN87:AN88) -> 97 | AO86: =SUM(AO87:AO88) -> 276 | AP86: =SUM(AP87:AP88) -> 412 | AQ86: =SUM(AQ87:AQ88) -> 387 | AR86: =SUM(AR87:AR88) -> 390 | AT86: =SUM(AT87:AT88) -> 2346 | AU86: =SUM(AU87:AU88) -> 3338 | AV86: =SUM(AV87:AV88) -> 4090 | AW86: =SUM(AW87:AW88) -> 4796 | AX86: =SUM(AX87:AX88) -> 5388 | AZ86: =SUM(AZ87:AZ88) -> 474 | BA86: =SUM(BA87:BA88) -> 726 | BB86: =SUM(BB87:BB88) -> 1070 | BC86: =SUM(BC87:BC88) -> 1255 | BD86: =SUM(BD87:BD88) -> 1904
B87: Equity | D87: 73 | E87: 73 | F87: 73 | G87: 73 | H87: 73 | J87: 155 | K87: 155 | L87: 155 | M87: 147 | N87: 147 | P87: 132 | Q87: 132 | R87: 132 | S87: 133 | T87: 136 | V87: 67 | W87: 79 | X87: 79 | Y87: 79 | Z87: 79 | AB87: 60 | AC87: 297 | AD87: 297 | AE87: 297 | AF87: 297 | AH87: 107 | AI87: 107 | AJ87: 107 | AK87: 107 | AL87: 107 | AN87: 31 | AO87: 48 | AP87: 48 | AQ87: 48 | AR87: 48 | AT87: 27 | AU87: 27 | AV87: 27 | AW87: 27 | AX87: 27 | AZ87: 42 | BA87: 42 | BB87: 42 | BC87: 42 | BD87: 43
B88: Reserve | D88: 5301 | E88: 5826 | F88: 6066 | G88: 6002 | H88: 5596 | J88: 5913 | K88: 7835 | L88: 8950 | M88: 8162 | N88: 8429 | P88: 65362 | Q88: 75567 | R88: 78610 | S88: 88520 | T88: 97373 | V88: -417 | W88: 1626 | X88: 1779 | Y88: 1622 | Z88: 1989 | AB88: 6796 | AC88: 8268 | AD88: 10030 | AE88: 11182 | AF88: 12329 | AH88: 503 | AI88: 636 | AJ88: 939 | AK88: 989 | AL88: 1071 | AN88: 66 | AO88: 228 | AP88: 364 | AQ88: 339 | AR88: 342 | AT88: 2319 | AU88: 3311 | AV88: 4063 | AW88: 4769 | AX88: 5361 | AZ88: 432 | BA88: 684 | BB88: 1028 | BC88: 1213 | BD88: 1861
B89: Debt To Equity | D89: =D85/D86 -> 0.092668403 | E89: =E85/E86 -> 0.10069503 | F89: =F85/F86 -> 0.097247109 | G89: =G85/G86 -> 0 | H89: =H85/H86 -> 0.098959252 | J89: =J85/J86 -> 0.00065919578 | K89: =K85/K86 -> 0.00025031289 | L89: =L85/L86 -> 0.00021965953 | M89: =M85/M86 -> 0.00036105428 | N89: =N85/N86 -> 0.012360075 | P89: =P85/P86 -> 1.2074083 | Q89: =Q85/Q86 -> 0.98738425 | R89: =R85/R86 -> 1.3085647 | S89: =S85/S86 -> 1.5470994 | T89: =T85/T86 -> 1.9108595 | V89: =IF(V85/V86<0,0,V85/V86) -> 0 | W89: =IF(W85/W86<0,0,W85/W86) -> 0.51730205 | X89: =X85/X86 -> 0.54843918 | Y89: =Y85/Y86 -> 0.91005291 | Z89: =Z85/Z86 -> 0.89071567 | AB89: =(AB85/AB86) -> 0.50598016 | AC89: =AC85/AC86 -> 0.42673672 | AD89: =AD85/AD86 -> 0.43362061 | AE89: =AE85/AE86 -> 0.4382786 | AF89: =AF85/AF86 -> 0.37430699 | AH89: =(AH85/AH86) -> 0.81803279 | AI89: =AI85/AI86 -> 0.6204576 | AJ89: =AJ85/AJ86 -> 0.22370937 | AK89: =AK85/AK86 -> 0.29288321 | AL89: =AL85/AL86 -> 0.30305603 | AN89: =(AN85/AN86) -> 0.010309278 | AO89: =AO85/AO86 -> 0.22101449 | AP89: =AP85/AP86 -> 0.35194175 | AQ89: =AQ85/AQ86 -> 0.45994832 | AR89: =AR85/AR86 -> 0.43333333 | AT89: =(AT85/AT86) -> 0.2514919 | AU89: =AU85/AU86 -> 0.094367885 | AV89: =AV85/AV86 -> 0.017848411 | AW89: =AW85/AW86 -> 0.059633028 | AX89: =AX85/AX86 -> 0.23515219 | AZ89: =(AZ85/AZ86) -> 1.5886076 | BA89: =BA85/BA86 -> 1.3677686 | BB89: =BB85/BB86 -> 0.82149533 | BC89: =BC85/BC86 -> 0.76812749 | BD89: =BD85/BD86 -> 0.31144958
B90: 2 Years Avg D/E | H90: =AVERAGE(G89:H89) -> 0.049479626 | N90: =AVERAGE(M89:N89) -> 0.0063605645 | T90: =AVERAGE(S89:T89) -> 1.7289794 | Z90: =AVERAGE(Y89:Z89) -> 0.90038429 | AF90: =AVERAGE(AE89:AF89) -> 0.40629279 | AL90: =AVERAGE(AK89:AL89) -> 0.29796962 | AR90: =AVERAGE(AQ89:AR89) -> 0.44664083 | AX90: =AVERAGE(AW89:AX89) -> 0.14739261 | BD90: =AVERAGE(BC89:BD89) -> 0.53978853
B91: Debt /(D+E) | D91: =D85/SUM(D85:D86) -> 0.084809264 | E91: =E85/SUM(E85:E86) -> 0.091483136 | F91: =F85/SUM(F85:F86) -> 0.088628266 | G91: =G85/SUM(G85:G86) -> 0 | H91: =H85/SUM(H85:H86) -> 0.090048154 | J91: =J85/SUM(J85:J86) -> 0.00065876153 | K91: =K85/SUM(K85:K86) -> 0.00025025025 | L91: =L85/SUM(L85:L86) -> 0.00021961129 | M91: =M85/SUM(M85:M86) -> 0.00036092397 | N91: =N85/SUM(N85:N86) -> 0.012209168 | P91: =P85/SUM(P85:P86) -> 0.54698005 | Q91: =Q85/SUM(Q85:Q86) -> 0.49682604 | R91: =R85/SUM(R85:R86) -> 0.56683042 | S91: =S85/SUM(S85:S86) -> 0.60739655 | T91: =T85/SUM(T85:T86) -> 0.65645886 | V91: =V85/SUM(V85:V86) -> 1.1969612 | W91: =W85/SUM(W85:W86) -> 0.34093545 | X91: =X85/SUM(X85:X86) -> 0.35418839 | Y91: =Y85/SUM(Y85:Y86) -> 0.47645429 | Z91: =Z85/SUM(Z85:Z86) -> 0.47109974 | AB91: =AB85/SUM(AB85:AB86) -> 0.33598063 | AC91: =AC85/SUM(AC85:AC86) -> 0.29909984 | AD91: =AD85/SUM(AD85:AD86) -> 0.30246538 | AE91: =AE85/SUM(AE85:AE86) -> 0.30472441 | AF91: =AF85/SUM(AF85:AF86) -> 0.27236053 | AH91: =AH85/SUM(AH85:AH86) -> 0.44995491 | AI91: =AI85/SUM(AI85:AI86) -> 0.38289037 | AJ91: =AJ85/SUM(AJ85:AJ86) -> 0.1828125 | AK91: =AK85/SUM(AK85:AK86) -> 0.22653493 | AL91: =AL85/SUM(AL85:AL86) -> 0.23257329 | AN91: =AN85/SUM(AN85:AN86) -> 0.010204082 | AO91: =AO85/SUM(AO85:AO86) -> 0.1810089 | AP91: =AP85/SUM(AP85:AP86) -> 0.26032316 | AQ91: =AQ85/SUM(AQ85:AQ86) -> 0.31504425 | AR91: =AR85/SUM(AR85:AR86) -> 0.30232558 | AT91: =AT85/SUM(AT85:AT86) -> 0.20095368 | AU91: =AU85/SUM(AU85:AU86) -> 0.086230495 | AV91: =AV85/SUM(AV85:AV86) -> 0.017535431 | AW91: =AW85/SUM(AW85:AW86) -> 0.056277056 | AX91: =AX85/SUM(AX85:AX86) -> 0.19038317 | AZ91: =AZ85/SUM(AZ85:AZ86) -> 0.61369193 | BA91: =BA85/SUM(BA85:BA86) -> 0.57766143 | BB91: =BB85/SUM(BB85:BB86) -> 0.45100051 | BC91: =BC85/SUM(BC85:BC86) -> 0.43442992 | BD91: =BD85/SUM(BD85:BD86) -> 0.23748498
B92: 2 Years avg D/(D+E) | H92: =AVERAGE(G91:H91) -> 0.045024077 | N92: =AVERAGE(M91:N91) -> 0.0062850462 | T92: =AVERAGE(S91:T91) -> 0.6319277 | Z92: =AVERAGE(Y91:Z91) -> 0.47377702 | AF92: =AVERAGE(AE91:AF91) -> 0.28854247 | AL92: =AVERAGE(AK91:AL91) -> 0.22955411 | AR92: =AVERAGE(AQ91:AR91) -> 0.30868491 | AX92: =AVERAGE(AW91:AX91) -> 0.12333011 | BD92: =AVERAGE(BC91:BD91) -> 0.33595745
B94: 5 Years Avg D/E | H94: =AVERAGE(D89:H89) -> 0.077913959 | N94: =AVERAGE(J89:N89) -> 0.0027700594 | T94: =AVERAGE(P89:T89) -> 1.3922632 | Z94: =AVERAGE(V89:Z89) -> 0.57330196 | AF94: =AVERAGE(AB89:AF89) -> 0.43578461 | AL94: =AVERAGE(AH89:AL89) -> 0.4516278 | AR94: =AVERAGE(AN89:AR89) -> 0.29530943 | AX94: =AVERAGE(AT89:AX89) -> 0.13169868 | BD94: =AVERAGE(AZ89:BD89) -> 0.97148972
B95: 5 Years avg D/(D+E) | H95: =AVERAGE(D91:H91) -> 0.070993764 | N95: =AVERAGE(J91:N91) -> 0.0027397431 | T95: =AVERAGE(P91:T91) -> 0.57489838 | Z95: =AVERAGE(V91:Z91) -> 0.56792781 | AF95: =AVERAGE(AB91:AF91) -> 0.30292616 | AL95: =AVERAGE(AH91:AL91) -> 0.2949532 | AR95: =AVERAGE(AN91:AR91) -> 0.21378119 | AX95: =AVERAGE(AT91:AX91) -> 0.11027597 | BD95: =AVERAGE(AZ91:BD91) -> 0.46285376
B99: Calculations 2 Yearly Weekly
C101: Nifty 50 Index | G101: Gujarat Alkalies & Chemicals Ltd (GAKL) | K101: Gujarat Narmada Valley Fertilizers & Chemicals Ltd (GNFC) | O101: Grasim Industries Ltd | S101: Chemplast | W101: SRFl | AA101: TGVS | AE101: Primo | AI101: DPNT | AM101: Epigral
C102: Date | D102: Price | E102: Nifty 50 Returns | G102: Date | H102: Price | I102: GAKL | K102: Date | L102: Price | M102: GNFC | O102: Date | P102: Price | Q102: Grasim | S102: Date | T102: Price | U102: Chemplast | W102: Date | X102: Price | Y102: SRFL | AA102: Date | AB102: Price | AC102: TGVS | AE102: Date | AF102: Price | AG102: Primo | AI102: Date | AJ102: Price | AK102: DPNT | AM102: Date | AN102: Price | AO102: EPI
C103: 46054 | D103: 24915.25 | G103: 46054 | H103: 439.5 | K103: 46054 | L103: 464.4 | O103: 46054 | P103: 2757.2 | S103: 46054 | T103: 249.2 | W103: 46054 | X103: 2770.6 | AA103: 46054 | AB103: 84.91 | AE103: 46054 | AF103: 19.8 | AI103: 46054 | AJ103: 1603.6 | AM103: 46054 | AN103: 922.8
C104: 46047 | D104: 25320.65 | E104: =D104/D103-1 -> 0.016271159 | G104: 46047 | H104: 455.95 | I104: =H104/H103-1 -> 0.037428896 | K104: 46047 | L104: 466.8 | M104: =L104/L103-1 -> 0.0051679587 | O104: 46047 | P104: 2819 | Q104: =P104/P103-1 -> 0.022414043 | S104: 46047 | T104: 260.25 | U104: =T104/T103-1 -> 0.044341894 | W104: 46047 | X104: 2816.3 | Y104: =X104/X103-1 -> 0.016494622 | AA104: 46047 | AB104: 87.2 | AC104: =AB104/AB103-1 -> 0.026969733 | AE104: 46047 | AF104: 20.14 | AG104: =AF104/AF103-1 -> 0.017171717 | AI104: 46047 | AJ104: 1642.5 | AK104: =AJ104/AJ103-1 -> 0.02425792 | AM104: 46047 | AN104: 1043.1 | AO104: =AN104/AN103-1 -> 0.13036411
C105: 46040 | D105: 25048.65 | E105: =D105/D104-1 -> -0.01074222 | G105: 46040 | H105: 453.8 | I105: =H105/H104-1 -> -0.0047154293 | K105: 46040 | L105: 464.2 | M105: =L105/L104-1 -> -0.0055698372 | O105: 46040 | P105: 2759 | Q105: =P105/P104-1 -> -0.021284143 | S105: 46040 | T105: 245.2 | U105: =T105/T104-1 -> -0.057829011 | W105: 46040 | X105: 2713.7 | Y105: =X105/X104-1 -> -0.036430778 | AA105: 46040 | AB105: 91 | AC105: =AB105/AB104-1 -> 0.043577982 | AE105: 46040 | AF105: 21.12 | AG105: =AF105/AF104-1 -> 0.048659384 | AI105: 46040 | AJ105: 1563.6 | AK105: =AJ105/AJ104-1 -> -0.04803653 | AM105: 46040 | AN105: 1065.6 | AO105: =AN105/AN104-1 -> 0.021570319
C106: 46033 | D106: 25694.35 | E106: =D106/D105-1 -> 0.025777836 | G106: 46033 | H106: 475.8 | I106: =H106/H105-1 -> 0.048479506 | K106: 46033 | L106: 477.4 | M106: =L106/L105-1 -> 0.028436019 | O106: 46033 | P106: 2809.6 | Q106: =P106/P105-1 -> 0.018339978 | S106: 46033 | T106: 274.8 | U106: =T106/T105-1 -> 0.12071778 | W106: 46033 | X106: 3027.4 | Y106: =X106/X105-1 -> 0.11559863 | AA106: 46033 | AB106: 99.55 | AC106: =AB106/AB105-1 -> 0.093956044 | AE106: 46033 | AF106: 22.04 | AG106: =AF106/AF105-1 -> 0.043560606 | AI106: 46033 | AJ106: 1546.4 | AK106: =AJ106/AJ105-1 -> -0.011000256 | AM106: 46033 | AN106: 1158.3 | AO106: =AN106/AN105-1 -> 0.086993243
C107: 46026 | D107: 25683.3 | E107: =D107/D106-1 -> -0.00043005563 | G107: 46026 | H107: 478.4 | I107: =H107/H106-1 -> 0.0054644809 | K107: 46026 | L107: 478.85 | M107: =L107/L106-1 -> 0.0030372853 | O107: 46026 | P107: 2776.9 | Q107: =P107/P106-1 -> -0.011638667 | S107: 46026 | T107: 242.1 | U107: =T107/T106-1 -> -0.11899563 | W107: 46026 | X107: 3023.2 | Y107: =X107/X106-1 -> -0.0013873291 | AA107: 46026 | AB107: 101.45 | AC107: =AB107/AB106-1 -> 0.019085886 | AE107: 46026 | AF107: 22.41 | AG107: =AF107/AF106-1 -> 0.016787659 | AI107: 46026 | AJ107: 1595.4 | AK107: =AJ107/AJ106-1 -> 0.031686498 | AM107: 46026 | AN107: 1118.4 | AO107: =AN107/AN106-1 -> -0.034447034
C108: 46019 | D108: 26328.55 | E108: =D108/D107-1 -> 0.025123329 | G108: 46019 | H108: 504.65 | I108: =H108/H107-1 -> 0.054870401 | K108: 46019 | L108: 493.55 | M108: =L108/L107-1 -> 0.030698549 | O108: 46019 | P108: 2856.4 | Q108: =P108/P107-1 -> 0.028629047 | S108: 46019 | T108: 265.8 | U108: =T108/T107-1 -> 0.097893432 | W108: 46019 | X108: 3059.5 | Y108: =X108/X107-1 -> 0.012007145 | AA108: 46019 | AB108: 110.2 | AC108: =AB108/AB107-1 -> 0.086249384 | AE108: 46019 | AF108: 24 | AG108: =AF108/AF107-1 -> 0.070950469 | AI108: 46019 | AJ108: 1711.1 | AK108: =AJ108/AJ107-1 -> 0.072520998 | AM108: 46019 | AN108: 1245.8 | AO108: =AN108/AN107-1 -> 0.11391273
C109: 46012 | D109: 26042.3 | E109: =D109/D108-1 -> -0.010872228 | G109: 46012 | H109: 501.9 | I109: =H109/H108-1 -> -0.0054493213 | K109: 46012 | L109: 487.85 | M109: =L109/L108-1 -> -0.011548982 | O109: 46012 | P109: 2817.7 | Q109: =P109/P108-1 -> -0.013548523 | S109: 46012 | T109: 260.8 | U109: =T109/T108-1 -> -0.018811136 | W109: 46012 | X109: 3101.6 | Y109: =X109/X108-1 -> 0.013760418 | AA109: 46012 | AB109: 110.3 | AC109: =AB109/AB108-1 -> 0.00090744102 | AE109: 46012 | AF109: 24.18 | AG109: =AF109/AF108-1 -> 0.0075 | AI109: 46012 | AJ109: 1765.2 | AK109: =AJ109/AJ108-1 -> 0.031617088 | AM109: 46012 | AN109: 1277.7 | AO109: =AN109/AN108-1 -> 0.025606036
C110: 46005 | D110: 25966.4 | E110: =D110/D109-1 -> -0.0029144891 | G110: 46005 | H110: 503.85 | I110: =H110/H109-1 -> 0.0038852361 | K110: 46005 | L110: 485.85 | M110: =L110/L109-1 -> -0.0040996208 | O110: 46005 | P110: 2812.5 | Q110: =P110/P109-1 -> -0.0018454768 | S110: 46005 | T110: 248.05 | U110: =T110/T109-1 -> -0.048888037 | W110: 46005 | X110: 3090.3 | Y110: =X110/X109-1 -> -0.0036432809 | AA110: 46005 | AB110: 114.2 | AC110: =AB110/AB109-1 -> 0.035358114 | AE110: 46005 | AF110: 22.92 | AG110: =AF110/AF109-1 -> -0.052109181 | AI110: 46005 | AJ110: 1667 | AK110: =AJ110/AJ109-1 -> -0.05563109 | AM110: 46005 | AN110: 1389.1 | AO110: =AN110/AN109-1 -> 0.087187916
C111: 45998 | D111: 26046.95 | E111: =D111/D110-1 -> 0.0031020858 | G111: 45998 | H111: 507.2 | I111: =H111/H110-1 -> 0.0066488042 | K111: 45998 | L111: 490.85 | M111: =L111/L110-1 -> 0.010291242 | O111: 45998 | P111: 2836.7 | Q111: =P111/P110-1 -> 0.0086044444 | S111: 45998 | T111: 261.4 | U111: =T111/T110-1 -> 0.053819794 | W111: 45998 | X111: 3023.6 | Y111: =X111/X110-1 -> -0.021583665 | AA111: 45998 | AB111: 116.9 | AC111: =AB111/AB110-1 -> 0.023642732 | AE111: 45998 | AF111: 22.35 | AG111: =AF111/AF110-1 -> -0.02486911 | AI111: 45998 | AJ111: 1528.6 | AK111: =AJ111/AJ110-1 -> -0.083023395 | AM111: 45998 | AN111: 1412.5 | AO111: =AN111/AN110-1 -> 0.016845439
C112: 45991 | D112: 26186.45 | E112: =D112/D111-1 -> 0.0053557134 | G112: 45991 | H112: 516.8 | I112: =H112/H111-1 -> 0.018927445 | K112: 45991 | L112: 502.7 | M112: =L112/L111-1 -> 0.024141795 | O112: 45991 | P112: 2747 | Q112: =P112/P111-1 -> -0.03162125 | S112: 45991 | T112: 262.1 | U112: =T112/T111-1 -> 0.0026778883 | W112: 45991 | X112: 2885.4 | Y112: =X112/X111-1 -> -0.045707104 | AA112: 45991 | AB112: 114.85 | AC112: =AB112/AB111-1 -> -0.017536356 | AE112: 45991 | AF112: 23.92 | AG112: =AF112/AF111-1 -> 0.070246085 | AI112: 45991 | AJ112: 1569 | AK112: =AJ112/AJ111-1 -> 0.026429413 | AM112: 45991 | AN112: 1471.8 | AO112: =AN112/AN111-1 -> 0.041982301
C113: 45984 | D113: 26202.95 | E113: =D113/D112-1 -> 0.00063009686 | G113: 45984 | H113: 530.5 | I113: =H113/H112-1 -> 0.026509288 | K113: 45984 | L113: 497.95 | M113: =L113/L112-1 -> -0.0094489755 | O113: 45984 | P113: 2739.4 | Q113: =P113/P112-1 -> -0.0027666545 | S113: 45984 | T113: 284.2 | U113: =T113/T112-1 -> 0.084318962 | W113: 45984 | X113: 2927.3 | Y113: =X113/X112-1 -> 0.014521384 | AA113: 45984 | AB113: 114.15 | AC113: =AB113/AB112-1 -> -0.0060949064 | AE113: 45984 | AF113: 25.52 | AG113: =AF113/AF112-1 -> 0.066889632 | AI113: 45984 | AJ113: 1558.6 | AK113: =AJ113/AJ112-1 -> -0.0066284257 | AM113: 45984 | AN113: 1511.7 | AO113: =AN113/AN112-1 -> 0.027109662
C114: 45977 | D114: 26068.15 | E114: =D114/D113-1 -> -0.0051444589 | G114: 45977 | H114: 545.75 | I114: =H114/H113-1 -> 0.028746466 | K114: 45977 | L114: 492.3 | M114: =L114/L113-1 -> -0.011346521 | O114: 45977 | P114: 2734.8 | Q114: =P114/P113-1 -> -0.0016791998 | S114: 45977 | T114: 308.45 | U114: =T114/T113-1 -> 0.085327234 | W114: 45977 | X114: 2838.4 | Y114: =X114/X113-1 -> -0.030369282 | AA114: 45977 | AB114: 118.4 | AC114: =AB114/AB113-1 -> 0.037231713 | AE114: 45977 | AF114: 22.26 | AG114: =AF114/AF113-1 -> -0.12774295 | AI114: 45977 | AJ114: 1691.8 | AK114: =AJ114/AJ113-1 -> 0.085461311 | AM114: 45977 | AN114: 1451.8 | AO114: =AN114/AN113-1 -> -0.039624264
C115: 45970 | D115: 25910.05 | E115: =D115/D114-1 -> -0.0060648723 | G115: 45970 | H115: 553.5 | I115: =H115/H114-1 -> 0.014200641 | K115: 45970 | L115: 504.5 | M115: =L115/L114-1 -> 0.024781637 | O115: 45970 | P115: 2783.4 | Q115: =P115/P114-1 -> 0.017770952 | S115: 45970 | T115: 345.1 | U115: =T115/T114-1 -> 0.11881991 | W115: 45970 | X115: 2839.1 | Y115: =X115/X114-1 -> 0.00024661781 | AA115: 45970 | AB115: 110.95 | AC115: =AB115/AB114-1 -> -0.062922297 | AE115: 45970 | AF115: 24.1 | AG115: =AF115/AF114-1 -> 0.082659479 | AI115: 45970 | AJ115: 1741 | AK115: =AJ115/AJ114-1 -> 0.029081452 | AM115: 45970 | AN115: 1507.7 | AO115: =AN115/AN114-1 -> 0.038503926
... C207: 45326 | D207: 21782.5 | E207: =D207/D206-1 -> -0.011714691 | G207: 45326 | H207: 788.34 | I207: =H207/H206-1 -> -0.012995793 | K207: 45326 | L207: 671.7 | M207: =L207/L206-1 -> 0.018730568 | O207: 45326 | P207: 2168.5 | Q207: =P207/P206-1 -> 0.029848265 | S207: 45326 | T207: 469.4 | U207: =T207/T206-1 -> 0.041375485 | W207: 45326 | X207: 2298.55 | Y207: =X207/X206-1 -> -0.034263266 | AA207: 45326 | AB207: 98.65 | AC207: =AB207/AB206-1 -> 0.017534812 | AE207: 45326 | AF207: 43.6 | AG207: =AF207/AF206-1 -> 0.11708942 | AI207: 45326 | AJ207: 2215.15 | AK207: =AJ207/AJ206-1 -> -0.041973013 | AM207: 45326 | AN207: 1019 | AO207: =AN207/AN206-1 -> -0.031460888
E209: Beta | H209: Beta | I209: =SLOPE(I104:I207,$E$104:$E$207) -> 1.160871 | M209: =SLOPE(M104:M207,$E$104:$E$207) -> 1.3114087 | Q209: =SLOPE(Q104:Q207,$E$104:$E$207) -> 1.2088705 | U209: =SLOPE(U104:U207,$E$104:$E$207) -> 1.202175 | Y209: =SLOPE(Y104:Y207,$E$104:$E$207) -> 0.80010021 | AC209: =SLOPE(AC104:AC207,$E$104:$E$207) -> 1.3395297 | AG209: =SLOPE(AG104:AG207,$E$104:$E$207) -> 0.71670229 | AK209: =SLOPE(AK104:AK207,$E$104:$E$207) -> 1.0388116 | AO209: =SLOPE(AO104:AO207,$E$104:$E$207) -> 1.6715682

Sheet Damodaran Data
B3: Country Data | G3: Company Data
B4: Country | C4: Africa | D4: Moody's rating | E4: Rating-based Default Spread | G4: For large non-financial service firms | L4: For smaller and riskier firms
B5: India | C5: Asia | D5: Baa3 | E5: 0.021609858 | G5: If interest coverage ratio is | L5: If interest coverage ratio is
B6: United Kingdom | C6: Western Europe | D6: Aa3 | E6: 0.0058935977 | G6: > | H6: ≤ to | I6: Rating is | J6: Spread is | L6: greater than | M6: ≤ to | N6: Rating is | O6: Spread is
B7: United States | C7: North America | D7: Aa1 | E7: 0.0027 | G7: -100000 | H7: 0.199999 | I7: D2/D | J7: 0.19 | L7: -100000 | M7: 0.499999 | N7: D2/D | O7: 0.19
B8: Abu Dhabi | C8: Middle East | D8: Aa2 | E8: 0.004853551 | G8: 0.2 | H8: 0.649999 | I8: C2/C | J8: 0.16 | L8: 0.5 | M8: 0.799999 | N8: C2/C | O8: 0.16
B9: Albania | C9: Eastern Europe & Russia | D9: Ba3 | E9: 0.035361586 | G9: 0.65 | H9: 0.799999 | I9: Ca2/CC | J9: 0.1261 | L9: 0.8 | M9: 1.249999 | N9: Ca2/CC | O9: 0.1261
B10: Andorra (Principality of) | C10: Western Europe | D10: Baa1 | E10: 0.015716261 | G10: 0.8 | H10: 1.249999 | I10: Caa/CCC | J10: 0.0885 | L10: 1.25 | M10: 1.499999 | N10: Caa/CCC | O10: 0.0885
B11: Angola | C11: Africa | D11: B3 | E11: 0.063905089 | G11: 1.25 | H11: 1.499999 | I11: B3/B- | J11: 0.0509 | L11: 1.5 | M11: 1.999999 | N11: B3/B- | O11: 0.0509
B12: Argentina | C12: Central and South America | D12: Caa3 | E12: 0.098342189 | G12: 1.5 | H12: 1.749999 | I12: B2/B | J12: 0.0321 | L12: 2 | M12: 2.499999 | N12: B2/B | O12: 0.0321
B13: Armenia | C13: Eastern Europe & Russia | D13: Ba3 | E13: 0.035361586 | G13: 1.75 | H13: 1.999999 | I13: B1/B+ | J13: 0.0275 | L13: 2.5 | M13: 2.999999 | N13: B1/B+ | O13: 0.0275
B14: Aruba | C14: Caribbean | D14: Baa3 | E14: 0.021609858 | G14: 2 | H14: 2.2499999 | I14: Ba2/BB | J14: 0.0184 | L14: 3 | M14: 3.499999 | N14: Ba2/BB | O14: 0.0184
B15: Australia | C15: Australia & New Zealand | D15: Aaa | E15: 0 | G15: 2.25 | H15: 2.49999 | I15: Ba1/BB+ | J15: 0.0138 | L15: 3.5 | M15: 3.9999999 | N15: Ba1/BB+ | O15: 0.0138
B16: Austria | C16: Western Europe | D16: Aa1 | E16: 0.0027 | G16: 2.5 | H16: 2.999999 | I16: Baa2/BBB | J16: 0.0111 | L16: 4 | M16: 4.499999 | N16: Baa2/BBB | O16: 0.0111
B17: Azerbaijan | C17: Eastern Europe & Russia | D17: Baa3 | E17: 0.021609858 | G17: 3 | H17: 4.249999 | I17: A3/A- | J17: 0.0089 | L17: 4.5 | M17: 5.999999 | N17: A3/A- | O17: 0.0089
B18: Bahamas | C18: Caribbean | D18: B1 | E18: 0.044259763 | G18: 4.25 | H18: 5.499999 | I18: A2/A | J18: 0.0078 | L18: 6 | M18: 7.499999 | N18: A2/A | O18: 0.0078
... B21: Barbados | C21: Caribbean | D21: B2 | E21: 0.054082426 | G21: 8.5 | H21: 100000 | I21: Aaa/AAA | J21: 0.004 | L21: 12.5 | M21: 100000 | N21: Aaa/AAA | O21: 0.004
B22: Belarus | C22: Eastern Europe & Russia | D22: C | E22: 0.175
B23: Belgium | C23: Western Europe | D23: Aa3 | E23: 0.0058935977
B24: Belize | C24: Central and South America | D24: Caa1 | E24: 0.073727752
B25: Benin | C25: Africa | D25: B1 | E25: 0.044259763
B26: Bermuda | C26: Caribbean | D26: A2 | E26: 0.0083203732
B27: Bolivia | C27: Central and South America | D27: Ca | E27: 0.11798751
B28: Bosnia and Herzegovina | C28: Eastern Europe & Russia | D28: B3 | E28: 0.063905089
B29: Botswana | C29: Africa | D29: A3 | E29: 0.011787195
B30: Brazil | C30: Central and South America | D30: Ba1 | E30: 0.024614437
B31: Bulgaria | C31: Eastern Europe & Russia | D31: Baa1 | E31: 0.015716261
B32: Burkina Faso | C32: Africa | D32: Caa1 | E32: 0.073727752
B33: Cambodia | C33: Asia | D33: B2 | E33: 0.054082426
... B161: Zambia | C161: Africa | D161: Caa2 | E161: 0.088519526

Sheet Control Sheet
B2: ='Input Sheet'!C5 -> Epigral Ltd. | C2: 46041 | M2: Management case
B3: Control Sheet | H3: Current Case | I3: 1 | M3: Base Case
M4: Down Case
D7: Actual | I7: Explicit Forecast Period | Q7: Terminal Value
B8: In INR Crores Other wise Stated | D8: =' Income Statement'!D6 -> 2021 | E8: =' Income Statement'!E6 -> 2022 | F8: =' Income Statement'!F6 -> 2023 | G8: =' Income Statement'!G6 -> 2024 | H8: =' Income Statement'!H6 -> 2025 | I8: =H8+1 -> 2026 | J8: =I8+1 -> 2027 | K8: =J8+1 -> 2028 | L8: =K8+1 -> 2029 | M8: =L8+1 -> 2030 | N8: =M8+1 -> 2031 | O8: =N8+1 -> 2032 | P8: =O8+1 -> 2033 | ... V8: =U8+1 -> 2039
B10: Assumption
A12: # | B12: Revenue
B14: Revenue - yoy % Growth
B15: Management Case | D15: =' Income Statement'!D12 -> 0 | E15: =' Income Statement'!E12 -> 0.77927928 | F15: =' Income Statement'!F12 -> 0.35822785 | G15: =' Income Statement'!G12 -> -0.19105312 | H15: =' Income Statement'!H12 -> 0.37903226 | I15: 0.16 | J15: 0.22 | K15: 0.25 | L15: 0.25 | M15: =L$15-(($L$15-$P$15)/($P$8-$L$8)) -> 0.2325 | N15: =M$15-(($L$15-$P$15)/($P$8-$L$8)) -> 0.215 | O15: =N$15-(($L$15-$P$15)/($P$8-$L$8)) -> 0.1975 | P15: 0.18 | Q15: 0.15 | R15: 0.14 | S15: 0.12 | T15: 0.1 | U15: 0.08 | V15: 0.05
B16: Best Case | D16: =D15 -> 0 | E16: =E15 -> 0.77927928 | F16: =F15 -> 0.35822785 | G16: =G15 -> -0.19105312 | H16: =H15 -> 0.37903226 | I16: 0.15 | J16: 0.2 | K16: 0.18 | L16: =K$16-(($K$16-$P$16)/($P$8-$K$8)) -> 0.174 | M16: =L$16-(($K$16-$P$16)/($P$8-$K$8)) -> 0.168 | N16: =M$16-(($K$16-$P$16)/($P$8-$K$8)) -> 0.162 | O16: =N$16-(($K$16-$P$16)/($P$8-$K$8)) -> 0.156 | P16: 0.15 | Q16: 0.15 | R16: 0.15 | S16: 0.15 | T16: 0.15 | U16: 0.15 | V16: 0.15
B17: Down Case | D17: =D16 -> 0 | E17: =E16 -> 0.77927928 | F17: =F16 -> 0.35822785 | G17: =G16 -> -0.19105312 | H17: =H16 -> 0.37903226 | I17: 0.13 | J17: 0.2 | K17: =J$17-(($I$17-$P$17)/($P$8-$I$8)) -> 0.19857143 | L17: =K$17-(($I$17-$P$17)/($P$8-$I$8)) -> 0.19714286 | M17: =L$17-(($I$17-$P$17)/($P$8-$I$8)) -> 0.19571429 | N17: =M$17-(($I$17-$P$17)/($P$8-$I$8)) -> 0.19428571 | O17: =N$17-(($I$17-$P$17)/($P$8-$I$8)) -> 0.19285714 | P17: 0.12 | Q17: 0.12 | R17: 0.12 | S17: 0.12 | T17: 0.12 | U17: 0.12 | V17: 0.12
B18: ="Current Case - "&CHOOSE($I$3,B15,B16,B17) -> Current Case - Management Case | I18: =CHOOSE($I$3,I15,I16,I17,) -> 0.16 | J18: =CHOOSE($I$3,J15,J16,J17,) -> 0.22 | K18: =CHOOSE($I$3,K15,K16,K17,) -> 0.25 | L18: =CHOOSE($I$3,L15,L16,L17,) -> 0.25 | M18: =CHOOSE($I$3,M15,M16,M17,) -> 0.2325 | N18: =CHOOSE($I$3,N15,N16,N17,) -> 0.215 | O18: =CHOOSE($I$3,O15,O16,O17,) -> 0.1975 | P18: =CHOOSE($I$3,P15,P16,P17,) -> 0.18 | ... V18: =CHOOSE($I$3,V15,V16,V17,) -> 0.05
A20: # | B20: COGS
B22: Gross Margins%
B23: Management Case | D23: =' Income Statement'!D14 -> 0.53558504 | E23: =' Income Statement'!E14 -> 0.50934881 | F23: =' Income Statement'!F14 -> 0.49040219 | G23: =' Income Statement'!G14 -> 0.44997408 | H23: =' Income Statement'!H14 -> 0.46941176 | I23: 0.45 | J23: 0.456 | K23: 0.456 | L23: =K$23-(($K$23-$P$23)/($P$8-$K$8)) -> 0.4608 | M23: =L$23-(($K$23-$P$23)/($P$8-$K$8)) -> 0.4656 | N23: =M$23-(($K$23-$P$23)/($P$8-$K$8)) -> 0.4704 | O23: =N$23-(($K$23-$P$23)/($P$8-$K$8)) -> 0.4752 | P23: 0.48 | Q23: 0.51 | R23: 0.51 | S23: 0.51 | T23: 0.52 | U23: 0.52 | V23: 0.52
B24: Best Case | D24: =D23 -> 0.53558504 | E24: =E23 -> 0.50934881 | F24: =F23 -> 0.49040219 | G24: =G23 -> 0.44997408 | H24: =H23 -> 0.46941176 | I24: 0.47 | J24: 0.47 | K24: 0.49 | L24: =K$24-(($K$24-$P$24)/($P$8-$K$8)) -> 0.482 | M24: =L$24-(($K$24-$P$24)/($P$8-$K$8)) -> 0.474 | N24: =M$24-(($K$24-$P$24)/($P$8-$K$8)) -> 0.466 | O24: =N$24-(($K$24-$P$24)/($P$8-$K$8)) -> 0.458 | P24: 0.45 | Q24: 0.45 | R24: 0.45 | S24: 0.45 | T24: 0.45 | U24: 0.45 | V24: 0.45
B25: Down Case | D25: =D24 -> 0.53558504 | E25: =E24 -> 0.50934881 | F25: =F24 -> 0.49040219 | G25: =G24 -> 0.44997408 | H25: =H24 -> 0.46941176 | I25: 0.45 | J25: =I$25-(($I$25-$P$25)/($P$8-$I$8)) -> 0.43 | K25: =J$25-(($I$25-$P$25)/($P$8-$I$8)) -> 0.41 | L25: =K$25-(($I$25-$P$25)/($P$8-$I$8)) -> 0.39 | M25: =L$25-(($I$25-$P$25)/($P$8-$I$8)) -> 0.37 | N25: =M$25-(($I$25-$P$25)/($P$8-$I$8)) -> 0.35 | O25: =N$25-(($I$25-$P$25)/($P$8-$I$8)) -> 0.33 | P25: 0.31 | Q25: 0.31 | R25: 0.31 | S25: 0.31 | T25: 0.31 | U25: 0.31 | V25: 0.31
B26: ="Current Case - "&CHOOSE($I$3,B23,B24,B25) -> Current Case - Management Case | I26: =CHOOSE($I$3,I23,I24,I25,) -> 0.45 | J26: =CHOOSE($I$3,J23,J24,J25,) -> 0.456 | K26: =CHOOSE($I$3,K23,K24,K25,) -> 0.456 | L26: =CHOOSE($I$3,L23,L24,L25,) -> 0.4608 | M26: =CHOOSE($I$3,M23,M24,M25,) -> 0.4656 | N26: =CHOOSE($I$3,N23,N24,N25,) -> 0.4704 | O26: =CHOOSE($I$3,O23,O24,O25,) -> 0.4752 | P26: =CHOOSE($I$3,P23,P24,P25,) -> 0.48 | ... V26: =CHOOSE($I$3,V23,V24,V25,) -> 0.52
B28: Current Case COGS | I28: =1-I26 -> 0.55 | J28: =1-J26 -> 0.544 | K28: =1-K26 -> 0.544 | L28: =1-L26 -> 0.5392 | M28: =1-M26 -> 0.5344 | N28: =1-N26 -> 0.5296 | O28: =1-O26 -> 0.5248 | P28: =1-P26 -> 0.52 | ... V28: =1-V26 -> 0.48
A30: # | B30: Selling, General & Administration (SG&A)
B32: Salaries, Wages & Bonus % Revenue
B33: Management Case | D33: ='Assumptions Working'!D409 -> 0.049457177 | E33: ='Assumptions Working'!E409 -> 0.033526757 | F33: ='Assumptions Working'!F409 -> 0.031535649 | G33: ='Assumptions Working'!G409 -> 0.041990669 | H33: ='Assumptions Working'!H409 -> 0.038431373 | I33: 0.038 | J33: 0.038 | K33: 0.038 | L33: 0.038 | M33: 0.038 | N33: 0.038 | O33: 0.038 | P33: 0.038 | Q33: 0.038 | R33: 0.038 | S33: 0.038 | T33: 0.038 | U33: 0.038 | V33: 0.038
B34: Best Case | D34: =D33 -> 0.049457177 | E34: =E33 -> 0.033526757 | F34: =F33 -> 0.031535649 | G34: =G33 -> 0.041990669 | H34: =H33 -> 0.038431373 | I34: 0.038 | J34: 0.038 | K34: 0.038 | L34: 0.038 | M34: 0.038 | N34: 0.038 | O34: 0.038 | P34: 0.038 | Q34: 0.038 | R34: 0.038 | S34: 0.038 | T34: 0.038 | U34: 0.038 | V34: 0.038
B35: Down Case | D35: =D34 -> 0.049457177 | E35: =E34 -> 0.033526757 | F35: =F34 -> 0.031535649 | G35: =G34 -> 0.041990669 | H35: =H34 -> 0.038431373 | I35: 0.038 | J35: 0.038 | K35: 0.038 | L35: 0.038 | M35: 0.038 | N35: 0.038 | O35: 0.038 | P35: 0.038 | Q35: 0.038 | R35: 0.038 | S35: 0.038 | T35: 0.038 | U35: 0.038 | V35: 0.038
B36: ="Current Case - "&CHOOSE($I$3,B33,B34,B35) -> Current Case - Management Case | I36: =CHOOSE($I$3,I33,I34,I35,) -> 0.038 | J36: =CHOOSE($I$3,J33,J34,J35,) -> 0.038 | K36: =CHOOSE($I$3,K33,K34,K35,) -> 0.038 | L36: =CHOOSE($I$3,L33,L34,L35,) -> 0.038 | M36: =CHOOSE($I$3,M33,M34,M35,) -> 0.038 | N36: =CHOOSE($I$3,N33,N34,N35,) -> 0.038 | O36: =CHOOSE($I$3,O33,O34,O35,) -> 0.038 | P36: =CHOOSE($I$3,P33,P34,P35,) -> 0.038 | ... V36: =CHOOSE($I$3,V33,V34,V35,) -> 0.038
B38: Power & Fuel Cost % Revenue
B39: Management Case | D39: ='Assumptions Working'!D412 -> 0.031363088 | E39: ='Assumptions Working'!E412 -> 0.064474533 | F39: ='Assumptions Working'!F412 -> 0.070383912 | G39: ='Assumptions Working'!G412 -> 0.073094868 | H39: ='Assumptions Working'!H412 -> 0.070588235 | I39: 0.07 | J39: 0.07 | K39: 0.07 | L39: 0.07 | M39: 0.07 | N39: 0.07 | O39: 0.07 | P39: 0.07 | Q39: 0.07 | R39: 0.07 | S39: 0.07 | T39: 0.07 | U39: 0.07 | V39: 0.07
B40: Best Case | D40: =D39 -> 0.031363088 | E40: =E39 -> 0.064474533 | F40: =F39 -> 0.070383912 | G40: =G39 -> 0.073094868 | H40: =H39 -> 0.070588235 | I40: 0.07 | J40: 0.07 | K40: 0.07 | L40: 0.07 | M40: 0.07 | N40: 0.07 | O40: 0.07 | P40: 0.07 | Q40: 0.07 | R40: 0.07 | S40: 0.07 | T40: 0.07 | U40: 0.07 | V40: 0.07
B41: Down Case | D41: =D40 -> 0.031363088 | E41: =E40 -> 0.064474533 | F41: =F40 -> 0.070383912 | G41: =G40 -> 0.073094868 | H41: =H40 -> 0.070588235 | I41: 0.07 | J41: 0.07 | K41: 0.07 | L41: 0.07 | M41: 0.07 | N41: 0.07 | O41: 0.07 | P41: 0.07 | Q41: 0.07 | R41: 0.07 | S41: 0.07 | T41: 0.07 | U41: 0.07 | V41: 0.07
B42: ="Current Case - "&CHOOSE($I$3,B39,B40,B41) -> Current Case - Management Case | I42: =CHOOSE($I$3,I39,I40,I41,) -> 0.07 | J42: =CHOOSE($I$3,J39,J40,J41,) -> 0.07 | K42: =CHOOSE($I$3,K39,K40,K41,) -> 0.07 | L42: =CHOOSE($I$3,L39,L40,L41,) -> 0.07 | M42: =CHOOSE($I$3,M39,M40,M41,) -> 0.07 | N42: =CHOOSE($I$3,N39,N40,N41,) -> 0.07 | O42: =CHOOSE($I$3,O39,O40,O41,) -> 0.07 | P42: =CHOOSE($I$3,P39,P40,P41,) -> 0.07 | ... V42: =CHOOSE($I$3,V39,V40,V41,) -> 0.07
B44: Other Operating Expenses % Revenue
B45: Management Case | D45: ='Assumptions Working'!D415 -> 0.053075995 | E45: ='Assumptions Working'!E415 -> 0.040618956 | F45: ='Assumptions Working'!F415 -> 0.036563071 | G45: ='Assumptions Working'!G415 -> 0.044582685 | H45: ='Assumptions Working'!H415 -> 0.036862745 | I45: 0.041 | J45: 0.041 | K45: 0.041 | L45: 0.041 | M45: 0.041 | N45: 0.041 | O45: 0.041 | P45: 0.041 | Q45: 0.041 | R45: 0.041 | S45: 0.041 | T45: 0.041 | U45: 0.041 | V45: 0.041
B46: Best Case | D46: =D45 -> 0.053075995 | E46: =E45 -> 0.040618956 | F46: =F45 -> 0.036563071 | G46: =G45 -> 0.044582685 | H46: =H45 -> 0.036862745 | I46: 0.041 | J46: 0.041 | K46: 0.041 | L46: 0.041 | M46: 0.041 | N46: 0.041 | O46: 0.041 | P46: 0.041 | Q46: 0.041 | R46: 0.041 | S46: 0.041 | T46: 0.041 | U46: 0.041 | V46: 0.041
B47: Down Case | D47: =D46 -> 0.053075995 | E47: =E46 -> 0.040618956 | F47: =F46 -> 0.036563071 | G47: =G46 -> 0.044582685 | H47: =H46 -> 0.036862745 | I47: 0.041 | J47: 0.041 | K47: 0.041 | L47: 0.041 | M47: 0.041 | N47: 0.041 | O47: 0.041 | P47: 0.041 | Q47: 0.041 | R47: 0.041 | S47: 0.041 | T47: 0.041 | U47: 0.041 | V47: 0.041
B48: ="Current Case - "&CHOOSE($I$3,B45,B46,B47) -> Current Case - Management Case | I48: =CHOOSE($I$3,I45,I46,I47,) -> 0.041 | J48: =CHOOSE($I$3,J45,J46,J47,) -> 0.041 | K48: =CHOOSE($I$3,K45,K46,K47,) -> 0.041 | L48: =CHOOSE($I$3,L45,L46,L47,) -> 0.041 | M48: =CHOOSE($I$3,M45,M46,M47,) -> 0.041 | N48: =CHOOSE($I$3,N45,N46,N47,) -> 0.041 | O48: =CHOOSE($I$3,O45,O46,O47,) -> 0.041 | P48: =CHOOSE($I$3,P45,P46,P47,) -> 0.041 | ... V48: =CHOOSE($I$3,V45,V46,V47,) -> 0.041
B50: Other SG&A Expenses % Revenue
B51: Management Case | D51: ='Assumptions Working'!D418 -> 0.08588661 | E51: ='Assumptions Working'!E418 -> 0.041779497 | F51: ='Assumptions Working'!F418 -> 0.036837294 | G51: ='Assumptions Working'!G418 -> 0.041109383 | H51: ='Assumptions Working'!H418 -> 0.04454902 | I51: 0.042 | J51: 0.042 | K51: 0.042 | L51: 0.042 | M51: 0.042 | N51: 0.042 | O51: 0.042 | P51: 0.042 | Q51: 0.042 | R51: 0.042 | S51: 0.042 | T51: 0.042 | U51: 0.042 | V51: 0.042
B52: Best Case | D52: =D51 -> 0.08588661 | E52: =E51 -> 0.041779497 | F52: =F51 -> 0.036837294 | G52: =G51 -> 0.041109383 | H52: =H51 -> 0.04454902 | I52: 0.042 | J52: 0.042 | K52: 0.042 | L52: 0.042 | M52: 0.042 | N52: 0.042 | O52: 0.042 | P52: 0.042 | Q52: 0.042 | R52: 0.042 | S52: 0.042 | T52: 0.042 | U52: 0.042 | V52: 0.042
B53: Down Case | D53: =D52 -> 0.08588661 | E53: =E52 -> 0.041779497 | F53: =F52 -> 0.036837294 | G53: =G52 -> 0.041109383 | H53: =H52 -> 0.04454902 | I53: 0.042 | J53: 0.042 | K53: 0.042 | L53: 0.042 | M53: 0.042 | N53: 0.042 | O53: 0.042 | P53: 0.042 | Q53: 0.042 | R53: 0.042 | S53: 0.042 | T53: 0.042 | U53: 0.042 | V53: 0.042
B54: ="Current Case - "&CHOOSE($I$3,B51,B52,B53) -> Current Case - Management Case | I54: =CHOOSE($I$3,I51,I52,I53,) -> 0.042 | J54: =CHOOSE($I$3,J51,J52,J53,) -> 0.042 | K54: =CHOOSE($I$3,K51,K52,K53,) -> 0.042 | L54: =CHOOSE($I$3,L51,L52,L53,) -> 0.042 | M54: =CHOOSE($I$3,M51,M52,M53,) -> 0.042 | N54: =CHOOSE($I$3,N51,N52,N53,) -> 0.042 | O54: =CHOOSE($I$3,O51,O52,O53,) -> 0.042 | P54: =CHOOSE($I$3,P51,P52,P53,) -> 0.042 | ... V54: =CHOOSE($I$3,V51,V52,V53,) -> 0.042
B56: Total SG&A Expense | D56: =D51+D45+D39+D33 -> 0.21978287 | E56: =E51+E45+E39+E33 -> 0.18039974 | F56: =F51+F45+F39+F33 -> 0.17531993 | G56: =G51+G45+G39+G33 -> 0.2007776 | H56: =H51+H45+H39+H33 -> 0.19043137 | I56: =I51+I45+I39+I33 -> 0.191 | J56: =J51+J45+J39+J33 -> 0.191 | K56: =K51+K45+K39+K33 -> 0.191 | ... V56: =V51+V45+V39+V33 -> 0.191
A58: # | B58: Non Current Asset
B61: Other Non-current Assets % Revenue
B62: Management Case | I62: 0 | J62: 0 | K62: 0 | L62: 0 | M62: 0 | N62: 0 | O62: 0 | P62: 0 | Q62: 0 | R62: 0 | S62: 0 | T62: 0 | U62: 0 | V62: 0
B63: Best Case | I63: 0 | J63: 0 | K63: 0 | L63: 0 | M63: 0 | N63: 0 | O63: 0 | P63: 0 | Q63: 0 | R63: 0 | S63: 0 | T63: 0 | U63: 0 | V63: 0
B64: Down Case | I64: 0 | J64: 0 | K64: 0 | L64: 0 | M64: 0 | N64: 0 | O64: 0 | P64: 0 | Q64: 0 | R64: 0 | S64: 0 | T64: 0 | U64: 0 | V64: 0
B65: ="Current Case - "&CHOOSE($I$3,B62,B63,B64) -> Current Case - Management Case | I65: =CHOOSE($I$3,I62,I63,I64,) -> 0 | J65: =CHOOSE($I$3,J62,J63,J64,) -> 0 | K65: =CHOOSE($I$3,K62,K63,K64,) -> 0 | L65: =CHOOSE($I$3,L62,L63,L64,) -> 0 | M65: =CHOOSE($I$3,M62,M63,M64,) -> 0 | N65: =CHOOSE($I$3,N62,N63,N64,) -> 0 | O65: =CHOOSE($I$3,O62,O63,O64,) -> 0 | P65: =CHOOSE($I$3,P62,P63,P64,) -> 0 | ... V65: =CHOOSE($I$3,V62,V63,V64,) -> 0
B67: CWIP % Fixed Assets
B68: Management Case | I68: 0 | J68: 0 | K68: 0 | L68: 0 | M68: 0 | N68: 0 | O68: 0 | P68: 0 | Q68: 0 | R68: 0 | S68: 0 | T68: 0 | U68: 0 | V68: 0
B69: Best Case | I69: 0 | J69: 0 | K69: 0 | L69: 0 | M69: 0 | N69: 0 | O69: 0 | P69: 0 | Q69: 0 | R69: 0 | S69: 0 | T69: 0 | U69: 0 | V69: 0
B70: Down Case | I70: 0 | J70: 0 | K70: 0 | L70: 0 | M70: 0 | N70: 0 | O70: 0 | P70: 0 | Q70: 0 | R70: 0 | S70: 0 | T70: 0 | U70: 0 | V70: 0
B71: ="Current Case - "&CHOOSE($I$3,B68,B69,B70) -> Current Case - Management Case | I71: =CHOOSE($I$3,I68,I69,I70,) -> 0 | J71: =CHOOSE($I$3,J68,J69,J70,) -> 0 | K71: =CHOOSE($I$3,K68,K69,K70,) -> 0 | L71: =CHOOSE($I$3,L68,L69,L70,) -> 0 | M71: =CHOOSE($I$3,M68,M69,M70,) -> 0 | N71: =CHOOSE($I$3,N68,N69,N70,) -> 0 | O71: =CHOOSE($I$3,O68,O69,O70,) -> 0 | P71: =CHOOSE($I$3,P68,P69,P70,) -> 0 | ... V71: =CHOOSE($I$3,V68,V69,V70,) -> 0
B73: Intangible Non Current Assets
B75: Other Intangible Assets Growth %
B76: Management Case | I76: -0.15789474 | J76: -0.1875 | K76: -0.23076923 | L76: -0.3 | M76: -0.42857143 | N76: -1 | O76: 0 | P76: 0 | Q76: 0 | R76: 0 | S76: 0 | T76: 0 | U76: 0 | V76: 0
B77: Best Case | I77: -0.15789474 | J77: -0.1875 | K77: -0.23076923 | L77: -0.3 | M77: -0.42857143 | N77: -1 | O77: 0 | P77: 0 | Q77: 0 | R77: 0 | S77: 0 | T77: 0 | U77: 0 | V77: 0
B78: Down Case | I78: -0.15789474 | J78: -0.1875 | K78: -0.23076923 | L78: -0.3 | M78: -0.42857143 | N78: -1 | O78: 0 | P78: 0 | Q78: 0 | R78: 0 | S78: 0 | T78: 0 | U78: 0 | V78: 0
B79: Current Case - Management Case | I79: =CHOOSE($I$3,I76,I77,I78,) -> -0.15789474 | J79: =CHOOSE($I$3,J76,J77,J78,) -> -0.1875 | K79: =CHOOSE($I$3,K76,K77,K78,) -> -0.23076923 | L79: =CHOOSE($I$3,L76,L77,L78,) -> -0.3 | M79: =CHOOSE($I$3,M76,M77,M78,) -> -0.42857143 | N79: =CHOOSE($I$3,N76,N77,N78,) -> -1 | O79: =CHOOSE($I$3,O76,O77,O78,) -> 0 | P79: =CHOOSE($I$3,P76,P77,P78,) -> 0 | ... V79: =CHOOSE($I$3,V76,V77,V78,) -> 0
A81: # | B81: Tax Rate
B83: Marginal Tax Rate
B84: Management Case | I84: 0.2517 | J84: 0.2517 | K84: 0.2517 | L84: 0.2517 | M84: 0.2517 | N84: 0.2517 | O84: 0.2517 | P84: 0.2517 | Q84: 0.2517 | R84: 0.2517 | S84: 0.2517 | T84: 0.2517 | U84: 0.2517 | V84: 0.2517
B85: Best Case | I85: 0.2517 | J85: 0.2517 | K85: 0.2517 | L85: 0.2517 | M85: 0.2517 | N85: 0.2517 | O85: 0.2517 | P85: 0.2517 | Q85: 0.2517 | R85: 0.2517 | S85: 0.2517 | T85: 0.2517 | U85: 0.2517 | V85: 0.2517
B86: Down Case | I86: 0.2517 | J86: 0.2517 | K86: 0.2517 | L86: 0.2517 | M86: 0.2517 | N86: 0.2517 | O86: 0.2517 | P86: 0.2517 | Q86: 0.2517 | R86: 0.2517 | S86: 0.2517 | T86: 0.2517 | U86: 0.2517 | V86: 0.2517
B87: ="Current Case - "&CHOOSE($I$3,B84,B85,B86) -> Current Case - Management Case | I87: =CHOOSE($I$3,I84,I85,I86,) -> 0.2517 | J87: =CHOOSE($I$3,J84,J85,J86,) -> 0.2517 | K87: =CHOOSE($I$3,K84,K85,K86,) -> 0.2517 | L87: =CHOOSE($I$3,L84,L85,L86,) -> 0.2517 | M87: =CHOOSE($I$3,M84,M85,M86,) -> 0.2517 | N87: =CHOOSE($I$3,N84,N85,N86,) -> 0.2517 | O87: =CHOOSE($I$3,O84,O85,O86,) -> 0.2517 | P87: =CHOOSE($I$3,P84,P85,P86,) -> 0.2517 | ... V87: =CHOOSE($I$3,V84,V85,V86,) -> 0.2517
A89: # | B89: Long Term Borrowing
B91: Growth YoY%
B92: Management Case | I92: 0.03 | J92: 0.04 | K92: 0.04 | L92: 0.04 | M92: 0.04 | N92: 0.02 | O92: 0.01 | P92: 0.01 | Q92: 0 | R92: 0 | S92: 0 | T92: 0 | U92: 0 | V92: 0
B93: Best Case | I93: 0.03 | J93: 0.04 | K93: 0.04 | L93: 0.04 | M93: 0.04 | N93: 0.02 | O93: 0.01 | P93: 0.01 | Q93: 0 | R93: 0 | S93: 0 | T93: 0 | U93: 0 | V93: 0
B94: Down Case | I94: 0.03 | J94: 0.04 | K94: 0.04 | L94: 0.04 | M94: 0.04 | N94: 0.02 | O94: 0.01 | P94: 0.01 | Q94: 0 | R94: 0 | S94: 0 | T94: 0 | U94: 0 | V94: 0
B95: ="Current Case - "&CHOOSE($I$3,B92,B93,B94) -> Current Case - Management Case | I95: =CHOOSE($I$3,I92,I93,I94,) -> 0.03 | J95: =CHOOSE($I$3,J92,J93,J94,) -> 0.04 | K95: =CHOOSE($I$3,K92,K93,K94,) -> 0.04 | L95: =CHOOSE($I$3,L92,L93,L94,) -> 0.04 | M95: =CHOOSE($I$3,M92,M93,M94,) -> 0.04 | N95: =CHOOSE($I$3,N92,N93,N94,) -> 0.02 | O95: =CHOOSE($I$3,O92,O93,O94,) -> 0.01 | P95: =CHOOSE($I$3,P92,P93,P94,) -> 0.01 | ... V95: =CHOOSE($I$3,V92,V93,V94,) -> 0
B97: Short Term Borrowing
B99: Revenue %
B100: Management Case | I100: 0.03 | J100: 0.03 | K100: 0.03 | L100: 0.03 | M100: 0.025 | N100: 0.015 | O100: 0.01 | P100: 0.01 | Q100: 0 | R100: 0 | S100: 0 | T100: 0 | U100: 0 | V100: 0
B101: Best Case | I101: 0.03 | J101: 0.03 | K101: 0.03 | L101: 0.03 | M101: 0.025 | N101: 0.015 | O101: 0.01 | P101: 0.01 | Q101: 0 | R101: 0 | S101: 0 | T101: 0 | U101: 0 | V101: 0
B102: Down Case | I102: 0.03 | J102: 0.03 | K102: 0.03 | L102: 0.03 | M102: 0.025 | N102: 0.015 | O102: 0.01 | P102: 0.01 | Q102: 0 | R102: 0 | S102: 0 | T102: 0 | U102: 0 | V102: 0
B103: ="Current Case - "&CHOOSE($I$3,B100,B101,B102) -> Current Case - Management Case | I103: =CHOOSE($I$3,I100,I101,I102,) -> 0.03 | J103: =CHOOSE($I$3,J100,J101,J102,) -> 0.03 | K103: =CHOOSE($I$3,K100,K101,K102,) -> 0.03 | L103: =CHOOSE($I$3,L100,L101,L102,) -> 0.03 | M103: =CHOOSE($I$3,M100,M101,M102,) -> 0.025 | N103: =CHOOSE($I$3,N100,N101,N102,) -> 0.015 | O103: =CHOOSE($I$3,O100,O101,O102,) -> 0.01 | P103: =CHOOSE($I$3,P100,P101,P102,) -> 0.01 | ... V103: =CHOOSE($I$3,V100,V101,V102,) -> 0
A105: # | B105: Interest Rate
B107: Interest Rate
B108: Management Case | I108: 0.077 | J108: 0.077 | K108: 0.077 | L108: 0.077 | M108: 0.077 | N108: 0.077 | O108: 0.077 | P108: 0.077 | Q108: 0.077 | R108: 0.077 | S108: 0.077 | T108: 0.077 | U108: 0.077 | V108: 0.077
B109: Best Case | I109: 0.077 | J109: 0.077 | K109: 0.077 | L109: 0.077 | M109: 0.077 | N109: 0.077 | O109: 0.077 | P109: 0.077 | Q109: 0.077 | R109: 0.077 | S109: 0.077 | T109: 0.077 | U109: 0.077 | V109: 0.077
B110: Down Case | I110: 0.077 | J110: 0.077 | K110: 0.077 | L110: 0.077 | M110: 0.077 | N110: 0.077 | O110: 0.077 | P110: 0.077 | Q110: 0.077 | R110: 0.077 | S110: 0.077 | T110: 0.077 | U110: 0.077 | V110: 0.077
B111: ="Current Case - "&CHOOSE($I$3,B108,B109,B110) -> Current Case - Management Case | I111: =CHOOSE($I$3,I108,I109,I110,) -> 0.077 | J111: =CHOOSE($I$3,J108,J109,J110,) -> 0.077 | K111: =CHOOSE($I$3,K108,K109,K110,) -> 0.077 | L111: =CHOOSE($I$3,L108,L109,L110,) -> 0.077 | M111: =CHOOSE($I$3,M108,M109,M110,) -> 0.077 | N111: =CHOOSE($I$3,N108,N109,N110,) -> 0.077 | O111: =CHOOSE($I$3,O108,O109,O110,) -> 0.077 | P111: =CHOOSE($I$3,P108,P109,P110,) -> 0.077 | ... V111: =CHOOSE($I$3,V108,V109,V110,) -> 0.077
A113: # | B113: Dividend Payout
B115: Dividend Payout %
B116: Management Case | I116: 0.07 | J116: 0.08 | K116: 0.1 | L116: 0.12 | M116: 0.18 | N116: 0.22 | O116: 0.3 | P116: 0.4 | Q116: 0.5 | R116: 0.6 | S116: 0.65 | T116: 0.7 | U116: 0.75 | V116: 0.75
B117: Best Case | I117: 0.07 | J117: 0.08 | K117: 0.1 | L117: 0.12 | M117: 0.18 | N117: 0.22 | O117: 0.3 | P117: 0.4 | Q117: 0.5 | R117: 0.6 | S117: 0.65 | T117: 0.7 | U117: 0.75 | V117: 0.75
B118: Down Case | I118: 0.07 | J118: 0.08 | K118: 0.1 | L118: 0.12 | M118: 0.18 | N118: 0.22 | O118: 0.3 | P118: 0.4 | Q118: 0.5 | R118: 0.6 | S118: 0.65 | T118: 0.7 | U118: 0.75 | V118: 0.75
B119: ="Current Case - "&CHOOSE($I$3,B116,B117,B118) -> Current Case - Management Case | I119: =CHOOSE($I$3,I116,I117,I118,) -> 0.07 | J119: =CHOOSE($I$3,J116,J117,J118,) -> 0.08 | K119: =CHOOSE($I$3,K116,K117,K118,) -> 0.1 | L119: =CHOOSE($I$3,L116,L117,L118,) -> 0.12 | M119: =CHOOSE($I$3,M116,M117,M118,) -> 0.18 | N119: =CHOOSE($I$3,N116,N117,N118,) -> 0.22 | O119: =CHOOSE($I$3,O116,O117,O118,) -> 0.3 | P119: =CHOOSE($I$3,P116,P117,P118,) -> 0.4 | ... V119: =CHOOSE($I$3,V116,V117,V118,) -> 0.75
A121: # | B121: Other Income
B123: % Revenue
B124: Management Case | I124: 0.005 | J124: 0.005 | K124: 0.005 | L124: 0.005 | M124: 0.005 | N124: 0.005 | O124: 0.005 | P124: 0.005 | Q124: 0.005 | R124: 0.005 | S124: 0.005 | T124: 0.005 | U124: 0.005 | V124: 0.005
B125: Best Case | I125: 0.005 | J125: 0.005 | K125: 0.005 | L125: 0.005 | M125: 0.005 | N125: 0.005 | O125: 0.005 | P125: 0.005 | Q125: 0.005 | R125: 0.005 | S125: 0.005 | T125: 0.005 | U125: 0.005 | V125: 0.005
B126: Down Case | I126: 0.005 | J126: 0.005 | K126: 0.005 | L126: 0.005 | M126: 0.005 | N126: 0.005 | O126: 0.005 | P126: 0.005 | Q126: 0.005 | R126: 0.005 | S126: 0.005 | T126: 0.005 | U126: 0.005 | V126: 0.005
B127: ="Current Case - "&CHOOSE($I$3,B124,B125,B126) -> Current Case - Management Case | I127: =CHOOSE($I$3,I124,I125,I126,) -> 0.005 | J127: =CHOOSE($I$3,J124,J125,J126,) -> 0.005 | K127: =CHOOSE($I$3,K124,K125,K126,) -> 0.005 | L127: =CHOOSE($I$3,L124,L125,L126,) -> 0.005 | M127: =CHOOSE($I$3,M124,M125,M126,) -> 0.005 | N127: =CHOOSE($I$3,N124,N125,N126,) -> 0.005 | O127: =CHOOSE($I$3,O124,O125,O126,) -> 0.005 | P127: =CHOOSE($I$3,P124,P125,P126,) -> 0.005 | ... V127: =CHOOSE($I$3,V124,V125,V126,) -> 0.005

Sheet Assumptions Working
A2: # | B2: Revenue Growth
B4: Company Historical Growth
J5: CAGR
B6: =' Income Statement'!B6 -> Particulars | D6: =' Income Statement'!D6 -> 2021 | E6: =' Income Statement'!E6 -> 2022 | F6: =' Income Statement'!F6 -> 2023 | G6: =' Income Statement'!G6 -> 2024 | H6: =' Income Statement'!H6 -> 2025 | J6: 3 Years | K6: 5 Years
B7: Revenue from Operations (Net) | D7: =' Income Statement'!D8 -> 829 | E7: =' Income Statement'!E8 -> 1551 | F7: =' Income Statement'!F8 -> 2188 | G7: =' Income Statement'!G8 -> 1929 | H7: =' Income Statement'!H8 -> 2550 | J7: =_xlfn.RRI(3,F7,H7) -> 0.052359892 | K7: =_xlfn.RRI(5,D7,H7) -> 0.25197925
B8: Sales Growth | E8: =E7/D7-1 -> 0.87092883 | F8: =F7/E7-1 -> 0.41070277 | G8: =G7/F7-1 -> -0.11837294 | H8: =H7/G7-1 -> 0.32192846
B11: Global Speciality Chemical
B13: GVR | D13: https://www.grandviewresearch.com/industry-analysis/specialty-chemicals-market
B14: The global specialty chemicals market was valued at approximately USD 978.97 billion in 2024 and is projected to reach USD 1,312.78 billion over the forecast period.
B15: growing at a CAGR of 5% from 2025 to 2030
B17: Fortune Business Insight | D17: https://www.fortunebusinessinsights.com/specialty-chemicals-market-105517
B18: The global specialty chemicals market size was USD 757.98 billion in 2025 and is projected to grow from USD 796.84 billion in 2026 to USD 1,167.22 billion in 2034 at a CAGR of 4.90% during the forecast period 2026-2034. Asia Pacific dominated the specialty chemicals market with a market share of 49.60% in 2025. Moreover, the specialty chemical market size in the U.S. is projected to grow significantly, reaching an estimated value of USD 152.36 billion by 2032, driven by expanding demand for construction chemicals on account of an increase in investments in infrastructure projects.
B21: Precedence research | D21: https://www.precedenceresearch.com/specialty-chemicals-market
B43: Indian Chlor alkali market Growth
B45: IMARC | D45: http://imarcgroup.com/india-chlor-alkali-market
B47: CAGR Growth 2025-2033 | D47: 0.0418
B66: Mobility Foresight | D66: https://mobilityforesights.com/product/india-chlor-alkali-market#:~:text=India%20Chlor%2DAlkali%20Market%20Size%20and%20Forecast,expansion%20across%20the%20forecast%20horizon.
B68: 25 Revenue | D68: USD 84.6 billion in 2025
B69: CAGR Growth 2025-2032 | D69: 0.0419
B72: Global Research Consulting | D72: https://www.omrglobal.com/industry-reports/india-chlor-alkali-market-size#:~:text=Indian%20chlor%20alkali%20market%20is,friendly%20ones%20like%20membrane%20cells.
B74: 0.065
D76: https://www.fortunebusinessinsights.com/industry-reports/chlor-alkali-market-101720#:~:text=The%20global%20chlor%20alkali%20market,the%20share%20in%20production%20technologies.
B77: The global chlor alkali market size was USD 52.23 billion in 2023 and is projected to grow from USD 53.22 billion in 2024 to USD 62.24 billion by 2032 at a CAGR of 1.94% during the forecast period.
B81: Mordor Intelligence
B83: CAGR over 2026-2031 | D83: 0.0299
B84: Asia-Pacific retained 62.15% of the chlor-alkali market size in 2025 and is projected to compound at a 3.12% CAGR through 2031
B85: Source: https://www.mordorintelligence.com/industry-reports/chlor-alkali-market
V86: Category | W86: Specific Product(s) | X86: Status / Capacity (approx.) | Y86: Key End-Use Industries
V87: Primary Chlor-Alkali | W87: Caustic Soda (Lye & Flakes) | X87: 400,000 TPA (4th largest in India) | Y87: Alumina, Textiles, Soaps
W88: Caustic Potash (Lye & Flakes) | X88: 21,000 TPA (3rd largest in India) | Y88: Soaps, Fertilizers, Pharma
W89: Chlorine & Hydrogen | X89: Captive Feedstock | Y89: Baseline for all derivatives
V90: Industrial By-products | W90: Hydrochloric Acid (HCl) | X90: Related product | Y90: Steel pickling, Water treatment
W91: Sodium Hypochlorite | X91: Related product | Y91: Disinfectant, Bleaching
W92: Diluted Sulphuric Acid | X92: Process byproduct | Y92: Industrial chemical processes
V93: Chloromethanes (CMS) | W93: Methyl Chloride, MDC, Chloroform, CTC | X93: 50,000 TPA (5th largest in India) | Y93: Pharma solvents, Refrigerants
V94: CPVC Value Chain | W94: CPVC Resin | X94: 75,000 TPA (Expanding to 150,000) | Y94: Heat-resistant plumbing (PVC)
W95: CPVC Compound | X95: 35,000 TPA (Commissioned 2024) | Y95: Ready-to-use pipe material
V96: Specialty Derivatives | W96: Epichlorohydrin (ECH) | X96: 50,000 TPA (Expanding to 100,000) | Y96: Epoxy Resins (Windmills, Auto)
W97: Hydrogen Peroxide (H2​O2​) | X97: 60,000 TPA (3rd largest in India) | Y97: Paper, Pulp, Textile bleaching
V98: Chlorotoluenes | W98: OCT, PCT, DCT (8-9 total products) | X98: Commissioned Q4 FY25 | Y98: Agrochemicals, Pharma (APIs)
B113: Indian Special chemical market Growth
B115: CN Market Insight | D115: https://www.custommarketinsights.com/report/india-specialty-chemicals-market/
B118: CARG | D118: 0.048
B121: Finnovate | D121: https://www.finnovate.in/learn/blog/specialty-chemicals-india-global-opportunity
B124: CARG | D124: 12%-16% | E124: 0.12 | F124: 0.16
B127: Invest iNdia | D127: https://www.investindia.gov.in/team-india-blogs/chemical-industry-growth-drivers-and-investment-opportunities-india
B129: CAGR upto 30 | D129: 0.11
B131: Grand view research | D131: https://www.grandviewresearch.com/industry-analysis/india-specialty-fine-chemicals-market-report
B133: Carg 30 | D133: 0.093
B136: Spherical Insight | D136: https://www.sphericalinsights.com/reports/india-specialty-fine-chemicals-market-size
B138: 22 revenue | D138: usa 48.05 billion
B139: Cagr 32 | D139: 0.087 | L139: 48.5 | M139: =L139*(1+$D$139) -> 52.7195 | N139: =M139*(1+$D$139) -> 57.306096 | O139: =N139*(1+$D$139) -> 62.291727 | P139: =O139*(1+$D$139) -> 67.711107 | Q139: =P139*(1+$D$139) -> 73.601973 | R139: =Q139*(1+$D$139) -> 80.005345 | S139: =R139*(1+$D$139) -> 86.96581 | T139: =S139*(1+$D$139) -> 94.531836 | ... V139: =U139*(1+$D$139) -> 111.69589
M140: 8.7 | O140: 0.038 | P140: =O139*(1+$O$140) -> 64.658813 | Q140: =P139*(1+$O$140) -> 70.284129 | R140: =Q139*(1+$O$140) -> 76.398848 | S140: =R139*(1+$O$140) -> 83.045548 | T140: =S139*(1+$O$140) -> 90.270511 | U140: =T139*(1+$O$140) -> 98.124045 | V140: =U139*(1+$O$140) -> 106.66084
D141: https://swarajyamag.com/economy/bottled-ambitions-can-indias-specialty-chemicals-live-up-to-hype
B158: IMARC | D158: https://www.imarcgroup.com/india-specialty-chemicals-market
B160: 24 Revenue | D160: USD 64.5 b
B161: Cagr 33 | D161: 0.038
B181: Global Market in SC
B182: Grand View Research | D182: https://www.grandviewresearch.com/industry-analysis/specialty-chemicals-market
B185: 24 Revenue | D185: USD 978.97 bi
B186: 30 Cagr | D186: 0.05
B188: Markets & Markets | D188: https://www.marketsandmarkets.com/Market-Reports/global-specialty-chemicals-165.html
B190: CAGR | D190: 0.05
B192: Technavio | D192: https://www.technavio.com/report/specialty-chemicals-market-industry-analysishttps:/www.technavio.com/report/specialty-chemicals-market-industry-analysis
B194: CAGR | D194: 0.067
B197: Yahoo Finance | D197: https://finance.yahoo.com/news/specialty-chemicals-market-size-worth-141100310.html?guccounter=1&guce_referrer=aHR0cHM6Ly93d3cuZ29vZ2xlLmNvbS8&guce_referrer_sig=AQAAABTKsS5upkv_yVJRWc-whpYBkaK8tPzSFLvJRgyYNQsq8OmK1o6YRDCTAHJrKhztbv-bdpKvhoa03gc70WWc9MqFzNkGfCrOkwSnvakYwF4P1LdyWYIlFZkvyjLA-qX8MK9p2c38taj7w_Les_YAlceXEJhbq1GukzETpZbNlktz
B199: According to Towards Chemical and Materials, the global specialty chemicals market size was reached at USD 671.19 billion in 2024 and is expected to be worth around USD 1,118.55 billion by 2034, growing at a compound annual growth rate (CAGR) of 5.24% over the forecast period 2025 to 2034.
B219: IMARC | D219: https://www.imarcgroup.com/specialty-chemicals-market
B221: CAGR) of 3.23%
B224: Company Concalls
B226: 45778
L227: 45870
M246: 45962
M260: Grow upto 2035 -40 in Double digit
F262: =E264*(1+$F$266) -> 30601.2 | G262: =F264*(1+$F$266) -> 38400.8 | H262: =G264*(1+$F$266) -> 46200.4
D263: 2024 | E263: =D263+1 -> 2025 | F263: =E263+1 -> 2026 | G263: =F263+1 -> 2027 | H263: =G263+1 -> 2028
B264: Only 33 Is comes from Derivatives | D264: 19292 | E264: 25501 | F264: =E264-(($E$264-$H$264)/($H$263-$E$263)) -> 32000.667 | G264: =F264-(($E$264-$H$264)/($H$263-$E$263)) -> 38500.333 | H264: 45000
E265: =E264/D264-1 -> 0.32184325 | F265: =F264/E264-1 -> 0.25487889 | G265: =G264/F264-1 -> 0.20311035 | H265: =H264/G264-1 -> 0.16882105
F266: 0.2
B267: Street Estimates
D268: Emkay
B269: Epigral maintains volume growth guidance of 15-20% for coming couple of years
D271: 2024 | E271: =D271+1 -> 2025 | F271: =E271+1 -> 2026 | G271: =F271+1 -> 2027 | H271: =G271+1 -> 2028
B272: Emkay | D272: 19292 | E272: 25501 | F272: 31030 | G272: 37993 | H272: 46717
E273: =E272/D272-1 -> 0.32184325 | F273: =F272/E272-1 -> 0.21681503 | G273: =G272/F272-1 -> 0.22439575 | H273: =H272/G272-1 -> 0.22962125
B275: Market Scrneer | D275: 2024 | E275: =D275+1 -> 2025 | F275: =E275+1 -> 2026 | G275: =F275+1 -> 2027 | H275: =G275+1 -> 2028 | J275: https://in.marketscreener.com/quote/stock/EPIGRAL-LIMITED-126415281/finances/
D276: 19292 | E276: 25501 | F276: 24749 | G276: 30283 | H276: 37949
E277: =E276/D276-1 -> 0.32184325 | F277: =F276/E276-1 -> -0.02948904 | G277: =G276/F276-1 -> 0.22360499 | H277: =H276/G276-1 -> 0.25314533
T291: The Indian specialty chemicals market is expected to grow at around 9%–12% CAGR over the next 5–6 years. This growth is supported by India’s overall GDP growth across end-user sectors such as FMCG, textiles, electronics, automobiles, agrochemicals, and paints & coatings, along with structural drivers like urbanization, low per-capita consumption, and Make in India.
A301: # | B301: Gross Margin
B303: Company Historical Margin
D305: =' Income Statement'!D6 -> 2021 | E305: =' Income Statement'!E6 -> 2022 | F305: =' Income Statement'!F6 -> 2023 | G305: =' Income Statement'!G6 -> 2024 | H305: =' Income Statement'!H6 -> 2025 | J305: Median | K305: Average
B306: Gross Margin | D306: =' Income Statement'!D14 -> 0.53558504 | E306: =' Income Statement'!E14 -> 0.50934881 | F306: =' Income Statement'!F14 -> 0.49040219 | G306: =' Income Statement'!G14 -> 0.44997408 | H306: =' Income Statement'!H14 -> 0.46941176 | J306: =MEDIAN(D306:H306) -> 0.49040219 | K306: =AVERAGE(D306:H306) -> 0.49094438 | M306: When ever this Median and Average are close means that consistency has been maintained
B308: Sector Data - Damodaran
B310: Just India
B311: Chemical (Specialty) | D311: 0.3442
B313: Emerging Market
B314: Chemical (Specialty) | D314: 0.2305
B316: Global
B317: Chemical (Specialty) | D317: 0.3024
...

Sheet Schedules
B2: ='Input Sheet'!C5 -> Epigral Ltd.
B3: Schedules | E3: Current Case | F3: 2
D7: Actual | I7: Explicit Forecast Period | Q7: Terminal Value
B8: In INR Crores Other wise Stated | D8: =' Income Statement'!D6 -> 2021 | E8: =' Income Statement'!E6 -> 2022 | F8: =' Income Statement'!F6 -> 2023 | G8: =' Income Statement'!G6 -> 2024 | H8: =' Income Statement'!H6 -> 2025 | I8: =H8+1 -> 2026 | J8: =I8+1 -> 2027 | K8: =J8+1 -> 2028 | L8: =K8+1 -> 2029 | M8: =L8+1 -> 2030 | N8: =M8+1 -> 2031 | O8: =N8+1 -> 2032 | P8: =O8+1 -> 2033 | ... V8: =U8+1 -> 2039
A10: # | B10: Revenue Schedule
B12: Revenue | D12: =' Income Statement'!D8 -> 829 | E12: =' Income Statement'!E8 -> 1551 | F12: =' Income Statement'!F8 -> 2188 | G12: =' Income Statement'!G8 -> 1929 | H12: =' Income Statement'!H8 -> 2550 | I12: =H12*(1+I14) -> 2958 | J12: =I12*(1+J14) -> 3608.76 | K12: =J12*(1+K14) -> 4510.95 | L12: =K12*(1+L14) -> 5638.6875 | M12: =L12*(1+M14) -> 6949.6823 | N12: =M12*(1+N14) -> 8443.864 | O12: =N12*(1+O14) -> 10111.527 | P12: =O12*(1+P14) -> 11931.602 | ... V12: =U12*(1+V14) -> 21853.712
B14: Growth YoY | E14: =E12/D12-1 -> 0.87092883 | F14: =F12/E12-1 -> 0.41070277 | G14: =G12/F12-1 -> -0.11837294 | H14: =H12/G12-1 -> 0.32192846 | I14: ='Control Sheet'!I18 -> 0.16 | J14: ='Control Sheet'!J18 -> 0.22 | K14: ='Control Sheet'!K18 -> 0.25 | L14: ='Control Sheet'!L18 -> 0.25 | M14: ='Control Sheet'!M18 -> 0.2325 | N14: ='Control Sheet'!N18 -> 0.215 | O14: ='Control Sheet'!O18 -> 0.1975 | P14: ='Control Sheet'!P18 -> 0.18 | ... V14: ='Control Sheet'!V18 -> 0.05
A16: # | B16: COGS Schedule
B18: Cogs | D18: =' Income Statement'!D9*-1 -> 385 | E18: =' Income Statement'!E9*-1 -> 761 | F18: =' Income Statement'!F9*-1 -> 1115 | G18: =' Income Statement'!G9*-1 -> 1061 | H18: =' Income Statement'!H9*-1 -> 1353 | I18: =I12*I20 -> 1626.9 | J18: =J12*J20 -> 1963.1654 | K18: =K12*K20 -> 2453.9568 | L18: =L12*L20 -> 3040.3803 | M18: =M12*M20 -> 3713.9102 | N18: =N12*N20 -> 4471.8704 | O18: =O12*O20 -> 5306.5295 | P18: =P12*P20 -> 6204.4331 | ... V18: =V12*V20 -> 10489.782
B20: Cogs % Revenue | I20: ='Control Sheet'!I28 -> 0.55 | J20: ='Control Sheet'!J28 -> 0.544 | K20: ='Control Sheet'!K28 -> 0.544 | L20: ='Control Sheet'!L28 -> 0.5392 | M20: ='Control Sheet'!M28 -> 0.5344 | N20: ='Control Sheet'!N28 -> 0.5296 | O20: ='Control Sheet'!O28 -> 0.5248 | P20: ='Control Sheet'!P28 -> 0.52 | ... V20: ='Control Sheet'!V28 -> 0.48
A22: # | B22: SG&A (Excluding Depreciation & Interest Expenses) Schedule
B24: Salaries, Wages & Bonus
B26: Salaries, Wages & Bonus | D26: ='Assumptions Working'!D381 -> 41 | E26: ='Assumptions Working'!E381 -> 52 | F26: ='Assumptions Working'!F381 -> 69 | G26: ='Assumptions Working'!G381 -> 81 | H26: ='Assumptions Working'!H381 -> 98 | I26: =I$12*I27 -> 112.404 | J26: =J$12*J27 -> 137.13288 | K26: =K$12*K27 -> 171.4161 | L26: =L$12*L27 -> 214.27013 | M26: =M$12*M27 -> 264.08793 | N26: =N$12*N27 -> 320.86683 | O26: =O$12*O27 -> 384.23803 | P26: =P$12*P27 -> 453.40088 | ... V26: =V$12*V27 -> 830.44106
B27: Salaries, Wages & Bonus % Revenue | D27: ='Assumptions Working'!D409 -> 0.049457177 | E27: ='Assumptions Working'!E409 -> 0.033526757 | F27: ='Assumptions Working'!F409 -> 0.031535649 | G27: ='Assumptions Working'!G409 -> 0.041990669 | H27: ='Assumptions Working'!H409 -> 0.038431373 | I27: ='Control Sheet'!I36 -> 0.038 | J27: ='Control Sheet'!J36 -> 0.038 | K27: ='Control Sheet'!K36 -> 0.038 | L27: ='Control Sheet'!L36 -> 0.038 | M27: ='Control Sheet'!M36 -> 0.038 | N27: ='Control Sheet'!N36 -> 0.038 | O27: ='Control Sheet'!O36 -> 0.038 | P27: ='Control Sheet'!P36 -> 0.038 | ... V27: ='Control Sheet'!V36 -> 0.038
B29: Power & Fuel Cost
B31: Power & Fuel Cost | D31: ='Assumptions Working'!D382 -> 26 | E31: ='Assumptions Working'!E382 -> 100 | F31: ='Assumptions Working'!F382 -> 154 | G31: ='Assumptions Working'!G382 -> 141 | H31: ='Assumptions Working'!H382 -> 180 | I31: =I$12*I32 -> 207.06 | J31: =J$12*J32 -> 252.6132 | K31: =K$12*K32 -> 315.7665 | L31: =L$12*L32 -> 394.70813 | M31: =M$12*M32 -> 486.47776 | N31: =N$12*N32 -> 591.07048 | O31: =O$12*O32 -> 707.8069 | P31: =P$12*P32 -> 835.21215 | ... V31: =V$12*V32 -> 1529.7598
B32: Power & Fuel Cost % Revenue | D32: ='Assumptions Working'!D412 -> 0.031363088 | E32: ='Assumptions Working'!E412 -> 0.064474533 | F32: ='Assumptions Working'!F412 -> 0.070383912 | G32: ='Assumptions Working'!G412 -> 0.073094868 | H32: ='Assumptions Working'!H412 -> 0.070588235 | I32: ='Control Sheet'!I42 -> 0.07 | J32: ='Control Sheet'!J42 -> 0.07 | K32: ='Control Sheet'!K42 -> 0.07 | L32: ='Control Sheet'!L42 -> 0.07 | M32: ='Control Sheet'!M42 -> 0.07 | N32: ='Control Sheet'!N42 -> 0.07 | O32: ='Control Sheet'!O42 -> 0.07 | P32: ='Control Sheet'!P42 -> 0.07 | ... V32: ='Control Sheet'!V42 -> 0.07
B34: Other Operating Expenses
B36: Other Operating Expenses | D36: ='Assumptions Working'!D387 -> 44 | E36: ='Assumptions Working'!E387 -> 63 | F36: ='Assumptions Working'!F387 -> 80 | G36: ='Assumptions Working'!G387 -> 86 | H36: ='Assumptions Working'!H387 -> 94 | I36: =I$12*I37 -> 121.278 | J36: =J$12*J37 -> 147.95916 | K36: =K$12*K37 -> 184.94895 | L36: =L$12*L37 -> 231.18619 | M36: =M$12*M37 -> 284.93698 | N36: =N$12*N37 -> 346.19843 | O36: =O$12*O37 -> 414.57262 | P36: =P$12*P37 -> 489.19569 | ... V36: =V$12*V37 -> 896.00219
B37: Other Expenses % Revenue | D37: ='Assumptions Working'!D415 -> 0.053075995 | E37: ='Assumptions Working'!E415 -> 0.040618956 | F37: ='Assumptions Working'!F415 -> 0.036563071 | G37: ='Assumptions Working'!G415 -> 0.044582685 | H37: ='Assumptions Working'!H415 -> 0.036862745 | I37: ='Control Sheet'!I48 -> 0.041 | J37: ='Control Sheet'!J48 -> 0.041 | K37: ='Control Sheet'!K48 -> 0.041 | L37: ='Control Sheet'!L48 -> 0.041 | M37: ='Control Sheet'!M48 -> 0.041 | N37: ='Control Sheet'!N48 -> 0.041 | O37: ='Control Sheet'!O48 -> 0.041 | P37: ='Control Sheet'!P48 -> 0.041 | ... V37: ='Control Sheet'!V48 -> 0.041
B39: Other SG&A Expenses
B41: Other SG&A Expenses | D41: ='Assumptions Working'!D417 -> 71.2 | E41: ='Assumptions Working'!E417 -> 64.8 | F41: ='Assumptions Working'!F417 -> 80.6 | G41: ='Assumptions Working'!G417 -> 79.3 | H41: ='Assumptions Working'!H417 -> 113.6 | I41: =I$12*I37 -> 121.278 | J41: =J$12*J37 -> 147.95916 | K41: =K$12*K37 -> 184.94895 | L41: =L$12*L37 -> 231.18619 | M41: =M$12*M37 -> 284.93698 | N41: =N$12*N37 -> 346.19843 | O41: =O$12*O37 -> 414.57262 | P41: =P$12*P37 -> 489.19569 | ... V41: =V$12*V37 -> 896.00219
B42: Other SG&A Expenses % Revenue | D42: ='Assumptions Working'!D418 -> 0.08588661 | E42: ='Assumptions Working'!E418 -> 0.041779497 | F42: ='Assumptions Working'!F418 -> 0.036837294 | G42: ='Assumptions Working'!G418 -> 0.041109383 | H42: ='Assumptions Working'!H418 -> 0.04454902 | I42: ='Control Sheet'!I54 -> 0.042 | J42: ='Control Sheet'!J54 -> 0.042 | K42: ='Control Sheet'!K54 -> 0.042 | L42: ='Control Sheet'!L54 -> 0.042 | M42: ='Control Sheet'!M54 -> 0.042 | N42: ='Control Sheet'!N54 -> 0.042 | O42: ='Control Sheet'!O54 -> 0.042 | P42: ='Control Sheet'!P54 -> 0.042 | ... V42: ='Control Sheet'!V54 -> 0.042
B44: Total SG&A (Excluding Depriciation & Interest Expense) | D44: =D41+D36+D31+D26 -> 182.2 | E44: =E41+E36+E31+E26 -> 279.8 | F44: =F41+F36+F31+F26 -> 383.6 | G44: =G41+G36+G31+G26 -> 387.3 | H44: =H41+H36+H31+H26 -> 485.6 | I44: =I41+I36+I31+I26 -> 562.02 | J44: =J41+J36+J31+J26 -> 685.6644 | K44: =K41+K36+K31+K26 -> 857.0805 | ... V44: =V41+V36+V31+V26 -> 4152.2053
B45: Total SG&A % Sales | D45: =D44/D12 -> 0.21978287 | E45: =E44/E12 -> 0.18039974 | F45: =F44/F12 -> 0.17531993 | G45: =G44/G12 -> 0.2007776 | H45: =H44/H12 -> 0.19043137 | I45: =I44/I12 -> 0.19 | J45: =J44/J12 -> 0.19 | K45: =K44/K12 -> 0.19 | ... V45: =V44/V12 -> 0.19
A47: # | B47: Non Current Asset Schedule
B49: Property, Plant and Equipment
B50: Opening PP& E | D50: =D70 -> 0 | E50: =E70 -> 0 | F50: =F70 -> 0 | G50: =G70 -> 0 | I50: 2219 | J50: =I53 -> 2507.5271 | K50: =J53 -> 2903.1971 | L50: =K53 -> 3395.2957 | M50: =L53 -> 3973.1086 | N50: =M53 -> 4625.9214 | O50: =N53 -> 5343.02 | P50: =O53 -> 6113.69 | Q50: =P53 -> 6927.2171 | ... V50: =U53 -> 10181.027
B51: Add: Capex During the Year | I51: ='Assumptions Working'!E731 -> 450 | J51: ='Assumptions Working'!F731 -> 600 | K51: ='Assumptions Working'!G731 -> 750 | L51: ='Assumptions Working'!H731 -> 900 | M51: ='Assumptions Working'!I731 -> 1050 | N51: ='Assumptions Working'!J731 -> 1200 | O51: ='Assumptions Working'!K731 -> 1350 | P51: ='Assumptions Working'!L731 -> 1500 | ... V51: ='Assumptions Working'!R731 -> 1897.9785
B52: Less: Depreciation during the year | D52: =' Income Statement'!D26*-1 -> 70.77 | E52: =' Income Statement'!E26*-1 -> 82.67 | F52: =' Income Statement'!F26*-1 -> 105.72 | G52: =' Income Statement'!G26*-1 -> 120.33 | H52: =' Income Statement'!H26*-1 -> 129.33 | I52: =H52+I51/$C$71 -> 161.47286 | J52: =I52+J51/$C$71 -> 204.33 | K52: =J52+K51/$C$71 -> 257.90143 | L52: =K52+L51/$C$71 -> 322.18714 | M52: =L52+M51/$C$71 -> 397.18714 | N52: =M52+N51/$C$71 -> 482.90143 | O52: =N52+O51/$C$71 -> 579.33 | P52: =O52+P51/$C$71 -> 686.47286 | ... V52: =U52+V51/$C$71 -> 1425.5758
B53: Closing PP&E | D53: =D73 -> 1070.65 | E53: =E73 -> 1039.4 | F53: =F73 -> 1778.85 | G53: =G73 -> 1744.68 | H53: =H73 -> 2219.39 | I53: =I50+I51+-I52 -> 2507.5271 | J53: =J50+J51+-J52 -> 2903.1971 | K53: =K50+K51+-K52 -> 3395.2957 | L53: =L50+L51+-L52 -> 3973.1086 | M53: =M50+M51+-M52 -> 4625.9214 | N53: =N50+N51+-N52 -> 5343.02 | O53: =O50+O51+-O52 -> 6113.69 | P53: =P50+P51+-P52 -> 6927.2171 | ... V53: =V50+V51+-V52 -> 10653.43
B54: YoY Growth% | J54: =J53/I53-1 -> 0.15779291 | K54: =K53/J53-1 -> 0.16950229 | L54: =L53/K53-1 -> 0.17018042 | M54: =M53/L53-1 -> 0.16430783 | N54: =N53/M53-1 -> 0.15501746 | O54: =O53/N53-1 -> 0.14423865 | P54: =P53/O53-1 -> 0.13306647 | Q54: =Q53/P53-1 -> 0.11001511 | ... V54: =V53/U53-1 -> 0.046400297
B56: Other Non-current Assets
B57: Other Non-current Assets | D57: =' Balance Sheet'!D20 -> 39.2 | E57: =' Balance Sheet'!E20 -> 19.8 | F57: =' Balance Sheet'!F20 -> 51 | G57: =' Balance Sheet'!G20 -> 43.2 | H57: =' Balance Sheet'!H20 -> 76 | I57: =H57*(1+I58) -> 76 | J57: =I57*(1+J58) -> 76 | K57: =J57*(1+K58) -> 76 | L57: =K57*(1+L58) -> 76 | M57: =L57*(1+M58) -> 76 | N57: =M57*(1+N58) -> 76 | O57: =N57*(1+O58) -> 76 | P57: =O57*(1+P58) -> 76 | ... V57: =U57*(1+V58) -> 76
B58: % Revenue | D58: =D57/D12 -> 0.047285887 | E58: =E57/E12 -> 0.012765957 | F58: =F57/F12 -> 0.023308958 | G58: =G57/G12 -> 0.022395023 | H58: =H57/H12 -> 0.029803922 | I58: ='Control Sheet'!I65 -> 0 | J58: ='Control Sheet'!J65 -> 0 | K58: ='Control Sheet'!K65 -> 0 | L58: ='Control Sheet'!L65 -> 0 | M58: ='Control Sheet'!M65 -> 0 | N58: ='Control Sheet'!N65 -> 0 | O58: ='Control Sheet'!O65 -> 0 | P58: ='Control Sheet'!P65 -> 0 | ... V58: ='Control Sheet'!V65 -> 0
B60: CWIP
B61: CWIP | D61: =' Balance Sheet'!D19 -> 126 | E61: =' Balance Sheet'!E19 -> 589 | F61: =' Balance Sheet'!F19 -> 158 | G61: =' Balance Sheet'!G19 -> 483 | H61: =' Balance Sheet'!H19 -> 64 | I61: =H61 -> 64 | J61: =I61 -> 64 | K61: =J61 -> 64 | L61: =K61 -> 64 | M61: =L61 -> 64 | N61: =M61 -> 64 | O61: =N61 -> 64 | P61: =O61 -> 64 | ... V61: =U61 -> 64
I62: ='Control Sheet'!I71 -> 0 | J62: ='Control Sheet'!J71 -> 0 | K62: ='Control Sheet'!K71 -> 0 | L62: ='Control Sheet'!L71 -> 0 | M62: ='Control Sheet'!M71 -> 0 | N62: ='Control Sheet'!N71 -> 0 | O62: ='Control Sheet'!O71 -> 0 | P62: ='Control Sheet'!P71 -> 0 | ... V62: ='Control Sheet'!V71 -> 0
B64: Intangible Non Current Assets
B65: Intangible Non current Assets | D65: =' Balance Sheet'!D18 -> 31.35 | E65: =' Balance Sheet'!E18 -> 28.6 | F65: =' Balance Sheet'!F18 -> 25.15 | G65: =' Balance Sheet'!G18 -> 22.32 | H65: =' Balance Sheet'!H18 -> 19 | I65: =H65*(1+I66) -> 16 | J65: =I65*(1+J66) -> 13 | K65: =J65*(1+K66) -> 10 | L65: =K65*(1+L66) -> 7 | M65: 4 | N65: =M65*(1+N66) -> 0 | O65: =N65*(1+O66) -> 0 | P65: =O65*(1+P66) -> 0 | Q65: =P65*(1+Q66) -> 0 | R65: =Q65*(1+R66) -> 0 | S65: =R65*(1+S66) -> 0 | T65: =S65*(1+T66) -> 0 | U65: =T65*(1+U66) -> 0 | V65: =U65*(1+V66) -> 0
B66: YoY Growth % | E66: =E65/D65-1 -> -0.087719298 | F66: =F65/E65-1 -> -0.12062937 | G66: =G65/F65-1 -> -0.11252485 | H66: =H65/G65-1 -> -0.14874552 | I66: ='Control Sheet'!I76 -> -0.15789474 | J66: ='Control Sheet'!J76 -> -0.1875 | K66: ='Control Sheet'!K76 -> -0.23076923 | L66: ='Control Sheet'!L76 -> -0.3 | M66: ='Control Sheet'!M76 -> -0.42857143 | N66: ='Control Sheet'!N76 -> -1
A68: # | B68: Depreciation Schedule
B70: PP&E - Beginning of the Year | I70: =I50 -> 2219 | J70: =J50 -> 2507.5271 | K70: =K50 -> 2903.1971 | L70: =L50 -> 3395.2957 | M70: =M50 -> 3973.1086 | N70: =N50 -> 4625.9214 | O70: =O50 -> 5343.02 | P70: =P50 -> 6113.69 | ... V70: =V50 -> 10181.027
B71: Add : Capex | C71: 14 | H71: =H51 -> 0 | I71: =I51 -> 450 | J71: =J51 -> 600 | K71: =K51 -> 750 | L71: =L51 -> 900 | M71: =M51 -> 1050 | N71: =N51 -> 1200 | O71: =O51 -> 1350 | ... V71: =V51 -> 1897.9785
B72: Less : Depreciation | D72: =' Income Statement'!D26*-1 -> 70.77 | E72: =' Income Statement'!E26*-1 -> 82.67 | F72: =' Income Statement'!F26*-1 -> 105.72 | G72: =' Income Statement'!G26*-1 -> 120.33 | H72: =' Income Statement'!H26*-1 -> 129.33 | I72: =H72+(I71/$C$71) -> 161.47286 | J72: =I72+(J71/$C$71) -> 204.33 | K72: =J72+(K71/$C$71) -> 257.90143 | L72: =K72+(L71/$C$71) -> 322.18714 | M72: =L72+(M71/$C$71) -> 397.18714 | N72: =M72+(N71/$C$71) -> 482.90143 | O72: =N72+(O71/$C$71) -> 579.33 | P72: =O72+(P71/$C$71) -> 686.47286 | ... V72: =U72+(V71/$C$71) -> 1425.5758
B73: PP&E - Ending of the Year | D73: =' Balance Sheet'!D17 -> 1070.65 | E73: =' Balance Sheet'!E17 -> 1039.4 | F73: =' Balance Sheet'!F17 -> 1778.85 | G73: =' Balance Sheet'!G17 -> 1744.68 | H73: =' Balance Sheet'!H17 -> 2219.39 | I73: =I70+I71-I72 -> 2507.5271 | J73: =J70+J71-J72 -> 2903.1971 | K73: =K70+K71-K72 -> 3395.2957 | L73: =L70+L71-L72 -> 3973.1086 | M73: =M70+M71-M72 -> 4625.9214 | N73: =N70+N71-N72 -> 5343.02 | O73: =O70+O71-O72 -> 6113.69 | P73: =P70+P71-P72 -> 6927.2171 | ... V73: =V70+V71-V72 -> 10653.43
B75: Intangible Non Current Assets - Beginning of the Year | C75: 10 | E75: ='3 Statement Model'!E59 -> 28.6 | F75: ='3 Statement Model'!F59 -> 25.15 | G75: ='3 Statement Model'!G59 -> 22.32 | H75: ='3 Statement Model'!H59 -> 19 | I75: =I65 -> 16 | J75: =J65 -> 13 | K75: =K65 -> 10 | L75: =L65 -> 7 | M75: =M65 -> 4 | N75: =M78 -> 0.77 | O75: =N78 -> -2.46 | P75: =O78 -> 0 | Q75: =P78 -> 0 | R75: =Q78 -> 0 | S75: =R78 -> 0 | T75: =S78 -> 0 | U75: =T78 -> 0 | V75: =U78 -> 0
B76: Add : Tangible Assets Spend | E76: 0 | F76: 0 | G76: 0 | H76: 0 | I76: 0 | J76: 0 | K76: 0 | L76: 0 | M76: 0 | N76: 0 | O76: 0 | P76: 0 | Q76: 0 | R76: 0 | S76: 0 | T76: 0 | U76: 0 | V76: 0
B77: Less : Amortization | D77: 3.23 | E77: 3.23 | F77: 3.23 | G77: 3.23 | H77: 3.23 | I77: =H77 -> 3.23 | J77: =I77 -> 3.23 | K77: =J77 -> 3.23 | L77: =K77 -> 3.23 | M77: =L77 -> 3.23 | N77: =M77 -> 3.23
B78: Intangible Non Current Assets - Ending of the Year | E78: =E75+E76-E77 -> 25.37 | F78: =F75+F76-F77 -> 21.92 | G78: =G75+G76-G77 -> 19.09 | H78: =H75+H76-H77 -> 15.77 | I78: =I75+I76-I77 -> 12.77 | J78: =J75+J76-J77 -> 9.77 | K78: =K75+K76-K77 -> 6.77 | L78: =L75+L76-L77 -> 3.77 | ... N78: =N75+N76-N77 -> -2.46
B80: Dep% Revenue | D80: =D72/D12 -> 0.085367913 | E80: =E72/E12 -> 0.053301096 | F80: =F72/F12 -> 0.048318099 | G80: =G72/G12 -> 0.062379471 | H80: =H72/H12 -> 0.050717647 | I80: =I72/I12 -> 0.054588525 | J80: =J72/J12 -> 0.056620557 | K80: =K72/K12 -> 0.057172309 | ... V80: =V72/V12 -> 0.065232663
B82: Depreciation WaterFall Schedule
B83: 2025 | H83: =H72 -> 129.33 | I83: =H83 -> 129.33 | J83: =I83 -> 129.33 | K83: =J83 -> 129.33 | L83: =K83 -> 129.33 | M83: =L83 -> 129.33 | N83: =M83 -> 129.33 | O83: =N83 -> 129.33 | P83: =O83 -> 129.33 | ... V83: =U83 -> 129.33
B84: =B83+1 -> 2026 | I84: =I71/$C$71 -> 32.142857 | J84: =I84 -> 32.142857 | K84: =J84 -> 32.142857 | L84: =K84 -> 32.142857 | M84: =L84 -> 32.142857 | N84: =M84 -> 32.142857 | O84: =N84 -> 32.142857 | P84: =O84 -> 32.142857 | Q84: =P84 -> 32.142857 | ... V84: =U84 -> 32.142857
B85: =B84+1 -> 2027 | J85: =J71/$C$71 -> 42.857143 | K85: =J85 -> 42.857143 | L85: =K85 -> 42.857143 | M85: =L85 -> 42.857143 | N85: =M85 -> 42.857143 | O85: =N85 -> 42.857143 | P85: =O85 -> 42.857143 | Q85: =P85 -> 42.857143 | R85: =Q85 -> 42.857143 | ... V85: =U85 -> 42.857143
B86: =B85+1 -> 2028 | K86: =K71/$C$71 -> 53.571429 | L86: =K86 -> 53.571429 | M86: =L86 -> 53.571429 | N86: =M86 -> 53.571429 | O86: =N86 -> 53.571429 | P86: =O86 -> 53.571429 | Q86: =P86 -> 53.571429 | R86: =Q86 -> 53.571429 | S86: =R86 -> 53.571429 | ... V86: =U86 -> 53.571429
B87: =B86+1 -> 2029 | L87: =L71/$C$71 -> 64.285714 | M87: =L87 -> 64.285714 | N87: =M87 -> 64.285714 | O87: =N87 -> 64.285714 | P87: =O87 -> 64.285714 | Q87: =P87 -> 64.285714 | R87: =Q87 -> 64.285714 | S87: =R87 -> 64.285714 | T87: =S87 -> 64.285714 | ... V87: =U87 -> 64.285714
B88: =B87+1 -> 2030 | M88: =M71/$C$71 -> 75 | N88: =M88 -> 75 | O88: =N88 -> 75 | P88: =O88 -> 75 | Q88: =P88 -> 75 | R88: =Q88 -> 75 | S88: =R88 -> 75 | T88: =S88 -> 75 | U88: =T88 -> 75 | V88: =U88 -> 75
B89: =B88+1 -> 2031 | N89: =N71/$C$71 -> 85.714286 | O89: =N89 -> 85.714286 | P89: =O89 -> 85.714286 | Q89: =P89 -> 85.714286 | R89: =Q89 -> 85.714286 | S89: =R89 -> 85.714286 | T89: =S89 -> 85.714286 | U89: =T89 -> 85.714286 | V89: =U89 -> 85.714286
B90: =B89+1 -> 2032 | O90: =O71/$C$71 -> 96.428571 | P90: =O90 -> 96.428571 | Q90: =P90 -> 96.428571 | R90: =Q90 -> 96.428571 | S90: =R90 -> 96.428571 | T90: =S90 -> 96.428571 | U90: =T90 -> 96.428571 | V90: =U90 -> 96.428571
B91: =B90+1 -> 2033 | P91: =P71/C71 -> 107.14286 | Q91: =P91 -> 107.14286 | R91: =Q91 -> 107.14286 | S91: =R91 -> 107.14286 | T91: =S91 -> 107.14286 | U91: =T91 -> 107.14286 | V91: =U91 -> 107.14286
B92: =B91+1 -> 2034 | Q92: =Q71/C71 -> 111.42857 | R92: =Q92 -> 111.42857 | S92: =R92 -> 111.42857 | T92: =S92 -> 111.42857 | U92: =T92 -> 111.42857 | V92: =U92 -> 111.42857
B93: =B92+1 -> 2035 | R93: =R71/C71 -> 115.88571 | S93: =R93 -> 115.88571 | T93: =S93 -> 115.88571 | U93: =T93 -> 115.88571 | V93: =U93 -> 115.88571
B94: =B93+1 -> 2036 | S94: =S71/C71 -> 120.52114 | T94: =S94 -> 120.52114 | U94: =T94 -> 120.52114 | V94: =U94 -> 120.52114
B95: =B94+1 -> 2037 | T95: =T71/C71 -> 125.34199 | U95: =T95 -> 125.34199 | V95: =U95 -> 125.34199
B96: =B95+1 -> 2038 | U96: =U71/C71 -> 130.35567 | V96: =U96 -> 130.35567
B97: =B96+1 -> 2039 | V97: =V71/C71 -> 135.56989
B98: Total Deprecition | H98: =SUM(H83:H90) -> 129.33 | I98: =SUM(I83:I90) -> 161.47286 | J98: =SUM(J83:J90) -> 204.33 | K98: =SUM(K83:K90) -> 257.90143 | L98: =SUM(L83:L90) -> 322.18714 | M98: =SUM(M83:M90) -> 397.18714 | N98: =SUM(N83:N90) -> 482.90143 | O98: =SUM(O83:O90) -> 579.33 | P98: =SUM(P83:P91) -> 686.47286 | Q98: =SUM(Q83:Q92) -> 797.90143 | R98: =SUM(R83:R93) -> 913.78714 | S98: =SUM(S83:S94) -> 1034.3083 | T98: =SUM(T83:T95) -> 1159.6503 | U98: =SUM(U83:U96) -> 1290.0059 | V98: =SUM(V83:V97) -> 1425.5758
B100: Amortization Used to be fall in the Straight Line method
A102: # | B102: Tax Expenses Schedule
B104: Revenue | D104: =D12 -> 829 | E104: =E12 -> 1551 | F104: =F12 -> 2188 | G104: =G12 -> 1929 | H104: =H12 -> 2550 | I104: =I12 -> 2958 | J104: =J12 -> 3608.76 | K104: =K12 -> 4510.95 | ... V104: =V12 -> 21853.712
B105: Less : Cost of Good Sold | D105: =Schedules!D18*-1 -> -385 | E105: =Schedules!E18*-1 -> -761 | F105: =Schedules!F18*-1 -> -1115 | G105: =Schedules!G18*-1 -> -1061 | H105: =Schedules!H18*-1 -> -1353 | I105: =Schedules!I18*-1 -> -1626.9 | J105: =Schedules!J18*-1 -> -1963.1654 | K105: =Schedules!K18*-1 -> -2453.9568 | ... V105: =Schedules!V18*-1 -> -10489.782
B106: Less : SG&A Expenses | D106: =D44*-1 -> -182.2 | E106: =E44*-1 -> -279.8 | F106: =F44*-1 -> -383.6 | G106: =G44*-1 -> -387.3 | H106: =H44*-1 -> -485.6 | I106: =I44*-1 -> -562.02 | J106: =J44*-1 -> -685.6644 | K106: =K44*-1 -> -857.0805 | ... V106: =V44*-1 -> -4152.2053
B107: Less : Depreciation & Amortization | D107: =SUM(D72,D77)*-1 -> -74 | E107: =SUM(E72,E77)*-1 -> -85.9 | F107: =SUM(F72,F77)*-1 -> -108.95 | G107: =SUM(G72,G77)*-1 -> -123.56 | H107: =SUM(H72,H77)*-1 -> -132.56 | I107: =SUM(I72,I77)*-1 -> -164.70286 | J107: =SUM(J72,J77)*-1 -> -207.56 | K107: =SUM(K72,K77)*-1 -> -261.13143 | ... V107: =SUM(V72,V77)*-1 -> -1425.5758
B108: Add : Other Income | D108: ='3 Statement Model'!D36 -> 7.5 | E108: ='3 Statement Model'!E36 -> 8.3 | F108: ='3 Statement Model'!F36 -> 9.3 | G108: ='3 Statement Model'!G36 -> 6.6 | H108: ='3 Statement Model'!H36 -> 15 | I108: ='3 Statement Model'!I36 -> 14.79 | J108: ='3 Statement Model'!J36 -> 18.0438 | K108: ='3 Statement Model'!K36 -> 22.55475 | ... V108: ='3 Statement Model'!V36 -> 109.26856
B109: Less : Interest Expenses | D109: ='3 Statement Model'!D35*-1 -> -34 | E109: ='3 Statement Model'!E35*-1 -> -48 | F109: ='3 Statement Model'!F35*-1 -> -67 | G109: ='3 Statement Model'!G35*-1 -> -73 | H109: ='3 Statement Model'!H35*-1 -> -53 | I109: ='3 Statement Model'!I35*-1 -> -40.433085 | J109: ='3 Statement Model'!J35*-1 -> -43.907002 | K109: ='3 Statement Model'!K35*-1 -> -47.153555 | ... V109: ='3 Statement Model'!V35*-1 -> -51.13203
B110: Earning Before Tax | D110: =SUM(D104:D109) -> 161.3 | E110: =SUM(E104:E109) -> 384.6 | F110: =SUM(F104:F109) -> 522.75 | G110: =SUM(G104:G109) -> 290.74 | H110: =SUM(H104:H109) -> 540.84 | I110: =SUM(I104:I109) -> 578.73406 | J110: =SUM(J104:J109) -> 726.50696 | K110: =SUM(K104:K109) -> 914.18247 | ... V110: =SUM(V104:V109) -> 5844.2857
B111: Less: Tax | D111: =' Income Statement'!D32 -> -60 | E111: =' Income Statement'!E32 -> -131 | F111: =' Income Statement'!F32 -> -169 | G111: =' Income Statement'!G32 -> -95 | H111: =' Income Statement'!H32 -> -183 | I111: =-I110*I114 -> -145.66736 | J111: =-J110*J114 -> -182.8618 | K111: =-K110*K114 -> -230.09973 | L111: =-L110*L114 -> -296.68476 | M111: =-M110*M114 -> -376.44358 | N111: =-N110*N114 -> -470.7058 | O111: =-O110*O114 -> -579.8064 | P111: =-P110*P114 -> -700.33821 | ... V111: =-V110*V114 -> -1471.0067
B112: Net Income | D112: =SUM(D110:D111) -> 101.3 | E112: =SUM(E110:E111) -> 253.6 | F112: =SUM(F110:F111) -> 353.75 | G112: =SUM(G110:G111) -> 195.74 | H112: =SUM(H110:H111) -> 357.84 | I112: =SUM(I110:I111) -> 433.0667 | J112: =SUM(J110:J111) -> 543.64516 | K112: =SUM(K110:K111) -> 684.08274 | ... V112: =SUM(V110:V111) -> 4373.279
B114: Marginal Tax Rate | I114: ='Control Sheet'!I87 -> 0.2517 | J114: ='Control Sheet'!J87 -> 0.2517 | K114: ='Control Sheet'!K87 -> 0.2517 | L114: ='Control Sheet'!L87 -> 0.2517 | M114: ='Control Sheet'!M87 -> 0.2517 | N114: ='Control Sheet'!N87 -> 0.2517 | O114: ='Control Sheet'!O87 -> 0.2517 | P114: ='Control Sheet'!P87 -> 0.2517 | ... V114: ='Control Sheet'!V87 -> 0.2517
A116: # | B116: Retained Earnings Schedule
B118: Retained Earnings - Beginning of Year | I118: ='3 Statement Model'!H80 -> 1861 | J118: =I121 -> 2263.752 | K118: =J121 -> 2763.9056 | L118: =K121 -> 3379.58 | M118: =L121 -> 4155.7743 | N118: =M121 -> 5073.4861 | O118: =N121 -> 6165.0186 | P118: =O121 -> 7371.6471 | Q118: =P121 -> 8620.9035 | ... V118: =U121 -> 14642.482
B119: Add : Net Profit | I119: ='3 Statement Model'!I39 -> 433.0667 | J119: =J$112 -> 543.64516 | K119: =K$112 -> 684.08274 | L119: =L$112 -> 882.03897 | M119: =M$112 -> 1119.1606 | N119: =N$112 -> 1399.4007 | O119: =O$112 -> 1723.755 | P119: =P$112 -> 2082.0941 | Q119: =Q$112 -> 2701.6644 | ... V119: =V$112 -> 4373.279
B120: Less : Dividend Paid | I120: =I119*I123 -> 30.314669 | J120: =J119*J123 -> 43.491613 | K120: =K119*K123 -> 68.408274 | L120: =L119*L123 -> 105.84468 | M120: =M119*M123 -> 201.44891 | N120: =N119*N123 -> 307.86815 | O120: =O119*O123 -> 517.1265 | P120: =P119*P123 -> 832.83764 | ... V120: =V119*V123 -> 3279.9592
B121: Retained Earning - Ending of Year | I121: =I118+I119-I120 -> 2263.752 | J121: =J118+J119-J120 -> 2763.9056 | K121: =K118+K119-K120 -> 3379.58 | L121: =L118+L119-L120 -> 4155.7743 | M121: =M118+M119-M120 -> 5073.4861 | N121: =N118+N119-N120 -> 6165.0186 | O121: =O118+O119-O120 -> 7371.6471 | P121: =P118+P119-P120 -> 8620.9035 | ... V121: =V118+V119-V120 -> 15735.801
B123: Dividend Pay out Rate % | I123: ='Control Sheet'!I119 -> 0.07 | J123: ='Control Sheet'!J119 -> 0.08 | K123: ='Control Sheet'!K119 -> 0.1 | L123: ='Control Sheet'!L119 -> 0.12 | M123: ='Control Sheet'!M119 -> 0.18 | N123: ='Control Sheet'!N119 -> 0.22 | O123: ='Control Sheet'!O119 -> 0.3 | P123: ='Control Sheet'!P119 -> 0.4 | ... V123: ='Control Sheet'!V119 -> 0.75
A125: # | B125: Working Capital Schedule
V126: 365
B127: Trade Receivables
B128: Revenue | D128: =D12 -> 829 | E128: =E12 -> 1551 | F128: =F12 -> 2188 | G128: =G12 -> 1929 | H128: =H12 -> 2550 | I128: =I12 -> 2958 | J128: =J12 -> 3608.76 | K128: =K12 -> 4510.95 | ... V128: =V12 -> 21853.712
B129: Trade receivable | D129: =' Balance Sheet'!D10 -> 119 | E129: =' Balance Sheet'!E10 -> 256 | F129: =' Balance Sheet'!F10 -> 166 | G129: =' Balance Sheet'!G10 -> 179 | H129: =' Balance Sheet'!H10 -> 232 | I129: =I128/$V$126*I130 -> 283.64384 | J129: =J128/$V$126*J130 -> 346.04548 | K129: =K128/$V$126*K130 -> 432.55685 | L129: =L128/$V$126*L130 -> 540.69606 | M129: =M128/$V$126*M130 -> 666.4079 | N129: =N128/$V$126*N130 -> 809.68559 | O129: =O128/$V$126*O130 -> 969.5985 | P129: =P128/$V$126*P130 -> 1144.1262 | ... V129: =V128/$V$126*V130 -> 2095.5614
B130: Debtor Days | E130: =AVERAGE(E129,D129)/E128*$V$126 -> 44.124758 | F130: =AVERAGE(F129,E129)/F128*$V$126 -> 35.198812 | G130: =AVERAGE(G129,F129)/G128*$V$126 -> 32.639969 | H130: =AVERAGE(H129,G129)/H128*$V$126 -> 29.414706 | I130: 35 | J130: 35 | K130: 35 | L130: 35 | M130: 35 | N130: 35 | O130: 35 | P130: 35 | Q130: 35 | R130: 35 | S130: 35 | T130: 35 | U130: 35 | V130: 35
B132: Inventory
B133: Revenue | D133: 829 | E133: 1551 | F133: 2188 | G133: 1929 | H133: 2550 | I133: =I128 -> 2958 | J133: =J128 -> 3608.76 | K133: =K128 -> 4510.95 | L133: =L128 -> 5638.6875 | M133: =M128 -> 6949.6823 | N133: =N128 -> 8443.864 | O133: =O128 -> 10111.527 | P133: =P128 -> 11931.602 | ... V133: =V128 -> 21853.712
B134: Inventory | D134: =' Balance Sheet'!D9 -> 54 | E134: =' Balance Sheet'!E9 -> 154 | F134: =' Balance Sheet'!F9 -> 212 | G134: =' Balance Sheet'!G9 -> 263 | H134: =' Balance Sheet'!H9 -> 388 | I134: =I133/$V$126*I135 -> 397.10137 | J134: =J133/$V$126*J135 -> 484.46367 | K134: =K133/$V$126*K135 -> 630.29712 | L134: =L133/$V$126*L135 -> 818.76832 | M134: =M133/$V$126*M135 -> 990.09173 | N134: =N133/$V$126*N135 -> 1179.8276 | O134: =O133/$V$126*O135 -> 1357.4379 | P134: =P133/$V$126*P135 -> 1601.7767 | ... V134: =V133/$V$126*V135 -> 2933.786
B135: Inventory Days | E135: =AVERAGE(E134,D134)/E133*$V$126 -> 24.474533 | F135: =AVERAGE(F134,E134)/F133*$V$126 -> 30.527879 | G135: =AVERAGE(G134,F134)/G133*$V$126 -> 44.939088 | H135: =AVERAGE(H134,G134)/H133*$V$126 -> 46.591176 | I135: 49 | J135: 49 | K135: 51 | L135: 53 | M135: 52 | N135: 51 | O135: 49 | P135: 49 | Q135: 49 | R135: 49 | S135: 49 | T135: 49 | U135: 49 | V135: 49
B136: Inventory % Revenue | D136: =D134/D133 -> 0.065138721 | E136: =E134/E133 -> 0.09929078 | F136: =F134/F133 -> 0.096892139 | G136: =G134/G133 -> 0.13634007 | H136: =H134/H133 -> 0.15215686 | I136: =I134/I133 -> 0.13424658 | J136: =J134/J133 -> 0.13424658 | K136: =K134/K133 -> 0.13972603 | ... V136: =V134/V133 -> 0.13424658
B138: Other Current Assets
B139: Revenue | D139: =D128 -> 829 | E139: =E128 -> 1551 | F139: =F128 -> 2188 | G139: =G128 -> 1929 | H139: =H128 -> 2550 | I139: =I128 -> 2958 | J139: =J128 -> 3608.76 | K139: =K128 -> 4510.95 | ... V139: =V128 -> 21853.712
B140: Other Current Assets | D140: =' Balance Sheet'!D14 -> 8.1 | E140: =' Balance Sheet'!E14 -> 12.2 | F140: =' Balance Sheet'!F14 -> 26 | G140: =' Balance Sheet'!G14 -> 52 | H140: =' Balance Sheet'!H14 -> 131.61 | I140: =I139*I141 -> 147.9 | J140: =J139*J141 -> 180.438 | K140: =K139*K141 -> 225.5475 | L140: =L139*L141 -> 281.93437 | M140: =M139*M141 -> 347.48412 | N140: =N139*N141 -> 422.1932 | O140: =O139*O141 -> 505.57636 | P140: =P139*P141 -> 596.5801 | ... V140: =V139*V141 -> 1092.6856
...

Sheet 3 Statement Model
S1: +
B2: ='Input Sheet'!C5 -> Epigral Ltd.
B3: Three Statement Model | H3: Current Case | I3: 2
X6: CAGR
D7: Actual | I7: Explicit Forecast Period | Q7: Terminal Value | X7: 8 Years | Y7: 5 Years | Z7: 3 Years
B8: In INR Crores Other wise Stated | D8: =Schedules!D8 -> 2021 | E8: =Schedules!E8 -> 2022 | F8: =Schedules!F8 -> 2023 | G8: =Schedules!G8 -> 2024 | H8: =Schedules!H8 -> 2025 | I8: =H8+1 -> 2026 | J8: =I8+1 -> 2027 | K8: =J8+1 -> 2028 | L8: =K8+1 -> 2029 | M8: =L8+1 -> 2030 | N8: =M8+1 -> 2031 | O8: =N8+1 -> 2032 | P8: =O8+1 -> 2033 | ... V8: =U8+1 -> 2039
A10: # | B10: Income Statement | X10: =V8-N8 -> 8 | Y10: =V8-Q8 -> 5 | Z10: =V8-S8 -> 3
B12: Revenue | D12: =Schedules!D12 -> 829 | E12: =Schedules!E12 -> 1551 | F12: =Schedules!F12 -> 2188 | G12: =Schedules!G12 -> 1929 | H12: =Schedules!H12 -> 2550 | I12: =Schedules!I12 -> 2958 | J12: =Schedules!J12 -> 3608.76 | K12: =Schedules!K12 -> 4510.95 | ... V12: =Schedules!V12 -> 21853.712 | X12: =_xlfn.RRI($V$8-$N$8,N12,V12) -> 0.12621938 | Y12: =_xlfn.RRI($V$8-$Q$8,Q12,V12) -> 0.09755356 | Z12: =_xlfn.RRI($V$8-$S$8,S12,V12) -> 0.076469956
B13: Less: Cost of Goods Sold | D13: =Schedules!D18 -> 385 | E13: =Schedules!E18 -> 761 | F13: =Schedules!F18 -> 1115 | G13: =Schedules!G18 -> 1061 | H13: =Schedules!H18 -> 1353 | I13: =Schedules!I18 -> 1626.9 | J13: =Schedules!J18 -> 1963.1654 | K13: =Schedules!K18 -> 2453.9568 | ... V13: =Schedules!V18 -> 10489.782 | X13: =_xlfn.RRI($V$8-$N$8,N13,V13) -> 0.11246064 | Y13: =_xlfn.RRI($V$8-$Q$8,Q13,V13) -> 0.093036725 | Z13: =_xlfn.RRI($V$8-$S$8,S13,V13) -> 0.069096643
B14: Gross Profit | D14: =D12-D13 -> 444 | E14: =E12-E13 -> 790 | F14: =F12-F13 -> 1073 | G14: =G12-G13 -> 868 | H14: =H12-H13 -> 1197 | I14: =I12-I13 -> 1331.1 | J14: =J12-J13 -> 1645.5946 | K14: =K12-K13 -> 2056.9932 | ... V14: =V12-V13 -> 11363.93 | X14: =_xlfn.RRI($V$8-$N$8,N14,V14) -> 0.14042046 | Y14: =_xlfn.RRI($V$8-$Q$8,Q14,V14) -> 0.10182433 | Z14: =_xlfn.RRI($V$8-$S$8,S14,V14) -> 0.083460216
B16: Gross Margins | D16: =D14/D12 -> 0.53558504 | E16: =E14/E12 -> 0.50934881 | F16: =F14/F12 -> 0.49040219 | G16: =G14/G12 -> 0.44997408 | H16: =H14/H12 -> 0.46941176 | I16: =I14/I12 -> 0.45 | J16: =J14/J12 -> 0.456 | K16: =K14/K12 -> 0.456 | ... V16: =V14/V12 -> 0.52
B18: Less: SG&A Expense (Excluding Depreciation & Interest)
B19: =Schedules!B24 -> Salaries, Wages & Bonus | D19: =Schedules!D26 -> 41 | E19: =Schedules!E26 -> 52 | F19: =Schedules!F26 -> 69 | G19: =Schedules!G26 -> 81 | H19: =Schedules!H26 -> 98 | I19: =Schedules!I26 -> 112.404 | J19: =Schedules!J26 -> 137.13288 | K19: =Schedules!K26 -> 171.4161 | ... V19: =Schedules!V26 -> 830.44106 | X19: =_xlfn.RRI($V$8-$N$8,N19,V19) -> 0.12621938 | Y19: =_xlfn.RRI($V$8-$Q$8,Q19,V19) -> 0.09755356 | Z19: =_xlfn.RRI($V$8-$S$8,S19,V19) -> 0.076469956
B20: =Schedules!B29 -> Power & Fuel Cost | D20: =Schedules!D31 -> 26 | E20: =Schedules!E31 -> 100 | F20: =Schedules!F31 -> 154 | G20: =Schedules!G31 -> 141 | H20: =Schedules!H31 -> 180 | I20: =Schedules!I31 -> 207.06 | J20: =Schedules!J31 -> 252.6132 | K20: =Schedules!K31 -> 315.7665 | ... V20: =Schedules!V31 -> 1529.7598 | X20: =_xlfn.RRI($V$8-$N$8,N20,V20) -> 0.12621938 | Y20: =_xlfn.RRI($V$8-$Q$8,Q20,V20) -> 0.09755356 | Z20: =_xlfn.RRI($V$8-$S$8,S20,V20) -> 0.076469956
B21: =Schedules!B34 -> Other Operating Expenses | D21: =Schedules!D36 -> 44 | E21: =Schedules!E36 -> 63 | F21: =Schedules!F36 -> 80 | G21: =Schedules!G36 -> 86 | H21: =Schedules!H36 -> 94 | I21: =Schedules!I36 -> 121.278 | J21: =Schedules!J36 -> 147.95916 | K21: =Schedules!K36 -> 184.94895 | ... V21: =Schedules!V36 -> 896.00219 | X21: =_xlfn.RRI($V$8-$N$8,N21,V21) -> 0.12621938 | Y21: =_xlfn.RRI($V$8-$Q$8,Q21,V21) -> 0.09755356 | Z21: =_xlfn.RRI($V$8-$S$8,S21,V21) -> 0.076469956
B22: =Schedules!B39 -> Other SG&A Expenses | D22: =Schedules!D41 -> 71.2 | E22: =Schedules!E41 -> 64.8 | F22: =Schedules!F41 -> 80.6 | G22: =Schedules!G41 -> 79.3 | H22: =Schedules!H41 -> 113.6 | I22: =Schedules!I41 -> 121.278 | J22: =Schedules!J41 -> 147.95916 | K22: =Schedules!K41 -> 184.94895 | ... V22: =Schedules!V41 -> 896.00219 | X22: =_xlfn.RRI($V$8-$N$8,N22,V22) -> 0.12621938 | Y22: =_xlfn.RRI($V$8-$Q$8,Q22,V22) -> 0.09755356 | Z22: =_xlfn.RRI($V$8-$S$8,S22,V22) -> 0.076469956
B23: Total SG&A Expenses | D23: =SUM(D19:D22) -> 182.2 | E23: =SUM(E19:E22) -> 279.8 | F23: =SUM(F19:F22) -> 383.6 | G23: =SUM(G19:G22) -> 387.3 | H23: =SUM(H19:H22) -> 485.6 | I23: =SUM(I19:I22) -> 562.02 | J23: =SUM(J19:J22) -> 685.6644 | K23: =SUM(K19:K22) -> 857.0805 | ... V23: =SUM(V19:V22) -> 4152.2053
B24: EBITDA | D24: =D14-D23 -> 261.8 | E24: =E14-E23 -> 510.2 | F24: =F14-F23 -> 689.4 | G24: =G14-G23 -> 480.7 | H24: =H14-H23 -> 711.4 | I24: =I14-I23 -> 769.08 | J24: =J14-J23 -> 959.93016 | K24: =K14-K23 -> 1199.9127 | ... V24: =V14-V23 -> 7211.725 | X24: =_xlfn.RRI($V$8-$N$8,N24,V24) -> 0.14938358 | Y24: =_xlfn.RRI($V$8-$Q$8,Q24,V24) -> 0.1043291 | Z24: =_xlfn.RRI($V$8-$S$8,S24,V24) -> 0.087568367
B26: Ebitda Margin | D26: =D24/D12 -> 0.31580217 | E26: =E24/E12 -> 0.32894907 | F26: =F24/F12 -> 0.31508227 | G26: =G24/G12 -> 0.24919647 | H26: =H24/H12 -> 0.27898039 | I26: =I24/I12 -> 0.26 | J26: =J24/J12 -> 0.266 | K26: =K24/K12 -> 0.266 | ... V26: =V24/V12 -> 0.33
B28: Less: Depreciation & Amortization
B29: Depreciation | D29: =' Income Statement'!D26*-1 -> 70.77 | E29: =' Income Statement'!E26*-1 -> 82.67 | F29: =' Income Statement'!F26*-1 -> 105.72 | G29: =' Income Statement'!G26*-1 -> 120.33 | H29: =' Income Statement'!H26*-1 -> 129.33 | I29: =Schedules!I72 -> 161.47286 | J29: =Schedules!J72 -> 204.33 | K29: =Schedules!K72 -> 257.90143 | L29: =Schedules!L72 -> 322.18714 | M29: =Schedules!M72 -> 397.18714 | N29: =Schedules!N72 -> 482.90143 | O29: =Schedules!O72 -> 579.33 | P29: =Schedules!P72 -> 686.47286 | ... V29: =Schedules!V72 -> 1425.5758 | X29: =_xlfn.RRI($V$8-$N$8,N29,V29) -> 0.14489716 | Y29: =_xlfn.RRI($V$8-$Q$8,Q29,V29) -> 0.1230736 | Z29: =_xlfn.RRI($V$8-$S$8,S29,V29) -> 0.11287599
B30: Amortization | D30: =' Income Statement'!D27*-1 -> 3.23 | E30: =' Income Statement'!E27*-1 -> 3.23 | F30: =' Income Statement'!F27*-1 -> 3.23 | G30: =' Income Statement'!G27*-1 -> 3.23 | H30: =' Income Statement'!H27*-1 -> 3.23 | I30: =Schedules!I77 -> 3.23 | J30: =Schedules!J77 -> 3.23 | K30: =Schedules!K77 -> 3.23 | L30: =Schedules!L77 -> 3.23 | M30: =Schedules!M77 -> 3.23 | N30: =Schedules!N77 -> 3.23 | O30: =Schedules!O77 -> 0 | P30: =Schedules!P77 -> 0 | ... V30: =Schedules!V77 -> 0
B31: EBIT | D31: =D24-(SUM(D29:D30)) -> 187.8 | E31: =E24-(SUM(E29:E30)) -> 424.3 | F31: =F24-(SUM(F29:F30)) -> 580.45 | G31: =G24-(SUM(G29:G30)) -> 357.14 | H31: =H24-(SUM(H29:H30)) -> 578.84 | I31: =I24-(SUM(I29:I30)) -> 604.37714 | J31: =J24-(SUM(J29:J30)) -> 752.37016 | K31: =K24-(SUM(K29:K30)) -> 938.78127 | ... V31: =V24-(SUM(V29:V30)) -> 5786.1491 | X31: =_xlfn.RRI($V$8-$N$8,N31,V31) -> 0.15076029 | Y31: =_xlfn.RRI($V$8-$Q$8,Q31,V31) -> 0.099988686 | Z31: =_xlfn.RRI($V$8-$S$8,S31,V31) -> 0.081676865
B33: Ebit Margin | D33: =D31/D12 -> 0.226538 | E33: =E31/E12 -> 0.27356544 | F33: =F31/F12 -> 0.26528793 | G33: =G31/G12 -> 0.18514256 | H33: =H31/H12 -> 0.22699608 | I33: =I31/I12 -> 0.20431952 | J33: =J31/J12 -> 0.2084844 | K33: =K31/K12 -> 0.20811166 | ... V33: =V31/V12 -> 0.26476734
B35: Less : Interest Expense | D35: =' Income Statement'!D29*-1 -> 34 | E35: =' Income Statement'!E29*-1 -> 48 | F35: =' Income Statement'!F29*-1 -> 67 | G35: =' Income Statement'!G29*-1 -> 73 | H35: =' Income Statement'!H29*-1 -> 53 | I35: =Schedules!I191 -> 40.433085 | J35: =Schedules!J191 -> 43.907002 | K35: =Schedules!K191 -> 47.153555 | L35: =Schedules!L191 -> 51.009132 | M35: =Schedules!M191 -> 54.059506 | N35: =Schedules!N191 -> 53.640875 | O35: =Schedules!O191 -> 51.473793 | P35: =Schedules!P191 -> 50.917445 | ... V35: =Schedules!V191 -> 51.13203 | X35: =_xlfn.RRI($V$8-$N$8,N35,V35) -> -0.005969644 | Y35: =_xlfn.RRI($V$8-$Q$8,Q35,V35) -> 0 | Z35: =_xlfn.RRI($V$8-$S$8,S35,V35) -> 0
B36: Add : Other Income | D36: =' Income Statement'!D30 -> 7.5 | E36: =' Income Statement'!E30 -> 8.3 | F36: =' Income Statement'!F30 -> 9.3 | G36: =' Income Statement'!G30 -> 6.6 | H36: =' Income Statement'!H30 -> 15 | I36: =Schedules!I197 -> 14.79 | J36: =Schedules!J197 -> 18.0438 | K36: =Schedules!K197 -> 22.55475 | L36: =Schedules!L197 -> 28.193438 | M36: =Schedules!M197 -> 34.748412 | N36: =Schedules!N197 -> 42.21932 | O36: =Schedules!O197 -> 50.557636 | P36: =Schedules!P197 -> 59.65801 | ... V36: =Schedules!V197 -> 109.26856 | X36: =_xlfn.RRI($V$8-$N$8,N36,V36) -> 0.12621938 | Y36: =_xlfn.RRI($V$8-$Q$8,Q36,V36) -> 0.09755356 | Z36: =_xlfn.RRI($V$8-$S$8,S36,V36) -> 0.076469956
B37: Earning Before Taxes | D37: =D31-D35+D36 -> 161.3 | E37: =E31-E35+E36 -> 384.6 | F37: =F31-F35+F36 -> 522.75 | G37: =G31-G35+G36 -> 290.74 | H37: =H31-H35+H36 -> 540.84 | I37: =I31-I35+I36 -> 578.73406 | J37: =J31-J35+J36 -> 726.50696 | K37: =K31-K35+K36 -> 914.18247 | ... V37: =V31-V35+V36 -> 5844.2857
B38: Less: Taxes | D38: =' Income Statement'!D32*-1 -> 60 | E38: =' Income Statement'!E32*-1 -> 131 | F38: =' Income Statement'!F32*-1 -> 169 | G38: =' Income Statement'!G32*-1 -> 95 | H38: =' Income Statement'!H32*-1 -> 183 | I38: =Schedules!I111*-1 -> 145.66736 | J38: =Schedules!J111*-1 -> 182.8618 | K38: =Schedules!K111*-1 -> 230.09973 | L38: =Schedules!L111*-1 -> 296.68476 | M38: =Schedules!M111*-1 -> 376.44358 | N38: =Schedules!N111*-1 -> 470.7058 | O38: =Schedules!O111*-1 -> 579.8064 | P38: =Schedules!P111*-1 -> 700.33821 | ... V38: =Schedules!V111*-1 -> 1471.0067 | X38: =_xlfn.RRI($V$8-$N$8,N38,V38) -> 0.15307654 | Y38: =_xlfn.RRI($V$8-$Q$8,Q38,V38) -> 0.10112128 | Z38: =_xlfn.RRI($V$8-$S$8,S38,V38) -> 0.082417396
B39: Net Income | D39: =D37-D38 -> 101.3 | E39: =E37-E38 -> 253.6 | F39: =F37-F38 -> 353.75 | G39: =G37-G38 -> 195.74 | H39: =H37-H38 -> 357.84 | I39: =I37-I38 -> 433.0667 | J39: =J37-J38 -> 543.64516 | K39: =K37-K38 -> 684.08274 | ... V39: =V37-V38 -> 4373.279 | X39: =_xlfn.RRI($V$8-$N$8,N39,V39) -> 0.15307654 | Y39: =_xlfn.RRI($V$8-$Q$8,Q39,V39) -> 0.10112128 | Z39: =_xlfn.RRI($V$8-$S$8,S39,V39) -> 0.082417396
B41: Sales Growth % | D41: =IFERROR(D12/C12-1,"NM") -> NM | E41: =IFERROR(E12/D12,"NM")-1 -> 0.87092883 | F41: =IFERROR(F12/E12,"NM")-1 -> 0.41070277 | G41: =IFERROR(G12/F12,"NM")-1 -> -0.11837294 | H41: =IFERROR(H12/G12,"NM")-1 -> 0.32192846 | I41: =IFERROR(I12/H12,"NM")-1 -> 0.16 | J41: =IFERROR(J12/I12,"NM")-1 -> 0.22 | K41: =IFERROR(K12/J12,"NM")-1 -> 0.25 | L41: =IFERROR(L12/K12,"NM")-1 -> 0.25 | ... V41: =IFERROR(V12/U12,"NM")-1 -> 0.05
B42: Gross Profit Margin % | D42: =IFERROR(D14/D12, "NM") -> 0.53558504 | E42: =IFERROR(E14/E12, "NM") -> 0.50934881 | F42: =IFERROR(F14/F12, "NM") -> 0.49040219 | G42: =IFERROR(G14/G12, "NM") -> 0.44997408 | H42: =IFERROR(H14/H12, "NM") -> 0.46941176 | I42: =IFERROR(I14/I12, "NM") -> 0.45 | J42: =IFERROR(J14/J12, "NM") -> 0.456 | K42: =IFERROR(K14/K12, "NM") -> 0.456 | ... V42: =IFERROR(V14/V12, "NM") -> 0.52
B43: EBITDA Margin % | D43: =IFERROR(D24/D12, "NM") -> 0.31580217 | E43: =IFERROR(E24/E12, "NM") -> 0.32894907 | F43: =IFERROR(F24/F12, "NM") -> 0.31508227 | G43: =IFERROR(G24/G12, "NM") -> 0.24919647 | H43: =IFERROR(H24/H12, "NM") -> 0.27898039 | I43: =IFERROR(I24/I12, "NM") -> 0.26 | J43: =IFERROR(J24/J12, "NM") -> 0.266 | K43: =IFERROR(K24/K12, "NM") -> 0.266 | ... V43: =IFERROR(V24/V12, "NM") -> 0.33
B44: EBIT Margin % | D44: =IFERROR(D31/D12, "NM") -> 0.226538 | E44: =IFERROR(E31/E12, "NM") -> 0.27356544 | F44: =IFERROR(F31/F12, "NM") -> 0.26528793 | G44: =IFERROR(G31/G12, "NM") -> 0.18514256 | H44: =IFERROR(H31/H12, "NM") -> 0.22699608 | I44: =IFERROR(I31/I12, "NM") -> 0.20431952 | J44: =IFERROR(J31/J12, "NM") -> 0.2084844 | K44: =IFERROR(K31/K12, "NM") -> 0.20811166 | ... V44: =IFERROR(V31/V12, "NM") -> 0.26476734
B45: Actual Tax Rate % | D45: =IFERROR(D38/D37,"NM") -> 0.37197768 | E45: =IFERROR(E38/E37,"NM") -> 0.34061362 | F45: =IFERROR(F38/F37,"NM") -> 0.32329029 | G45: =IFERROR(G38/G37,"NM") -> 0.32675242 | H45: =IFERROR(H38/H37,"NM") -> 0.33836255 | I45: =IFERROR(I38/I37,"NM") -> 0.2517 | J45: =IFERROR(J38/J37,"NM") -> 0.2517 | K45: =IFERROR(K38/K37,"NM") -> 0.2517 | ... V45: =IFERROR(V38/V37,"NM") -> 0.2517
B46: Net Profit Margin % | D46: =IFERROR(D39/D12,"NM") -> 0.12219542 | E46: =IFERROR(E39/E12,"NM") -> 0.16350741 | F46: =IFERROR(F39/F12,"NM") -> 0.16167733 | G46: =IFERROR(G39/G12,"NM") -> 0.10147227 | H46: =IFERROR(H39/H12,"NM") -> 0.14032941 | I46: =IFERROR(I39/I12,"NM") -> 0.14640524 | J46: =IFERROR(J39/J12,"NM") -> 0.15064597 | K46: =IFERROR(K39/K12,"NM") -> 0.15164937 | ... V46: =IFERROR(V39/V12,"NM") -> 0.20011607
A48: # | B48: Balance Sheet
B50: Assets
B51: Cash | D51: =D125 -> 0.676 | E51: =E125 -> 25.026 | F51: =F125 -> 14.201 | G51: =G125 -> 3.141 | H51: =H125 -> 18.601 | I51: =I125 -> 148.02369 | J51: =J125 -> 157.45065 | K51: =K125 -> 120.26837 | ... V51: =V125 -> 1522.9582
B52: Cash at Bank | D52: =' Balance Sheet'!D13 -> 0 | E52: =' Balance Sheet'!E13 -> 0 | F52: =' Balance Sheet'!F13 -> 1 | G52: =' Balance Sheet'!G13 -> 3.62 | H52: =' Balance Sheet'!H13 -> 3.36 | I52: =H52 -> 3.36 | J52: =I52 -> 3.36 | K52: =J52 -> 3.36 | L52: =K52 -> 3.36 | M52: =L52 -> 3.36 | N52: =M52 -> 3.36 | O52: =N52 -> 3.36 | P52: =O52 -> 3.36 | ... V52: =U52 -> 3.36
B53: Inventory | D53: =Schedules!D134 -> 54 | E53: =Schedules!E134 -> 154 | F53: =Schedules!F134 -> 212 | G53: =Schedules!G134 -> 263 | H53: =Schedules!H134 -> 388 | I53: =Schedules!I134 -> 397.10137 | J53: =Schedules!J134 -> 484.46367 | K53: =Schedules!K134 -> 630.29712 | ... V53: =Schedules!V134 -> 2933.786
B54: Trade Receivable | D54: =Schedules!D129 -> 119 | E54: =Schedules!E129 -> 256 | F54: =Schedules!F129 -> 166 | G54: =Schedules!G129 -> 179 | H54: =Schedules!H129 -> 232 | I54: =Schedules!I129 -> 283.64384 | J54: =Schedules!J129 -> 346.04548 | K54: =Schedules!K129 -> 432.55685 | ... V54: =Schedules!V129 -> 2095.5614
B55: Other Current Assets | D55: =Schedules!D140 -> 8.1 | E55: =Schedules!E140 -> 12.2 | F55: =Schedules!F140 -> 26 | G55: =Schedules!G140 -> 52 | H55: =Schedules!H140 -> 131.61 | I55: =Schedules!I140 -> 147.9 | J55: =Schedules!J140 -> 180.438 | K55: =Schedules!K140 -> 225.5475 | ... V55: =Schedules!V140 -> 1092.6856
B56: Total Current Assets | D56: =SUM(D51:D55) -> 181.776 | E56: =SUM(E51:E55) -> 447.226 | F56: =SUM(F51:F55) -> 419.201 | G56: =SUM(G51:G55) -> 500.761 | H56: =SUM(H51:H55) -> 773.571 | I56: =SUM(I51:I55) -> 980.0289 | J56: =SUM(J51:J55) -> 1171.7578 | K56: =SUM(K51:K55) -> 1412.0298 | ... V56: =SUM(V51:V55) -> 7648.3512
B58: Property, Plant and Equipment | D58: =Schedules!D53 -> 1070.65 | E58: =Schedules!E53 -> 1039.4 | F58: =Schedules!F53 -> 1778.85 | G58: =Schedules!G53 -> 1744.68 | H58: =Schedules!H53 -> 2219.39 | I58: =Schedules!I73 -> 2507.5271 | J58: =Schedules!J73 -> 2903.1971 | K58: =Schedules!K73 -> 3395.2957 | L58: =Schedules!L73 -> 3973.1086 | M58: =Schedules!M73 -> 4625.9214 | N58: =Schedules!N73 -> 5343.02 | O58: =Schedules!O73 -> 6113.69 | P58: =Schedules!P73 -> 6927.2171 | ... V58: =Schedules!V73 -> 10653.43
B59: Other Intangible Assets | D59: =Schedules!D65 -> 31.35 | E59: =Schedules!E65 -> 28.6 | F59: =Schedules!F65 -> 25.15 | G59: =Schedules!G65 -> 22.32 | H59: =Schedules!H65 -> 19 | I59: =Schedules!I75 -> 16 | J59: =Schedules!J75 -> 13 | K59: =Schedules!K75 -> 10 | L59: =Schedules!L75 -> 7 | M59: =Schedules!M75 -> 4 | N59: =Schedules!N75 -> 0.77 | P59: =Schedules!P75 -> 0 | Q59: =Schedules!Q75 -> 0 | R59: =Schedules!R75 -> 0 | S59: =Schedules!S75 -> 0 | T59: =Schedules!T75 -> 0 | U59: =Schedules!U75 -> 0 | V59: =Schedules!V75 -> 0
B60: Capital Work in Progress | D60: =Schedules!D61 -> 126 | E60: =Schedules!E61 -> 589 | F60: =Schedules!F61 -> 158 | G60: =Schedules!G61 -> 483 | H60: =Schedules!H61 -> 64 | I60: =Schedules!I61 -> 64 | J60: =Schedules!J61 -> 64 | K60: =Schedules!K61 -> 64 | ... V60: =Schedules!V61 -> 64
B61: Other Non-Current Assets | D61: =Schedules!D57 -> 39.2 | E61: =Schedules!E57 -> 19.8 | F61: =Schedules!F57 -> 51 | G61: =Schedules!G57 -> 43.2 | H61: =Schedules!H57 -> 76 | I61: =Schedules!I57 -> 76 | J61: =Schedules!J57 -> 76 | K61: =Schedules!K57 -> 76 | ... V61: =Schedules!V57 -> 76
B62: Total Non-Current Assets | D62: =SUM(D58:D61) -> 1267.2 | E62: =SUM(E58:E61) -> 1676.8 | F62: =SUM(F58:F61) -> 2013 | G62: =SUM(G58:G61) -> 2293.2 | H62: =SUM(H58:H61) -> 2378.39 | I62: =SUM(I58:I61) -> 2663.5271 | J62: =SUM(J58:J61) -> 3056.1971 | K62: =SUM(K58:K61) -> 3545.2957 | ... V62: =SUM(V58:V61) -> 10793.43
B64: Total Assets | D64: =SUM(D62,D56) -> 1448.976 | E64: =SUM(E62,E56) -> 2124.026 | F64: =SUM(F62,F56) -> 2432.201 | G64: =SUM(G62,G56) -> 2793.961 | H64: =SUM(H62,H56) -> 3151.961 | I64: =SUM(I62,I56) -> 3643.556 | J64: =SUM(J62,J56) -> 4227.9549 | K64: =SUM(K62,K56) -> 4957.3256 | ... V64: =SUM(V62,V56) -> 18441.781
B66: Equity & Liablities
B68: Liabilities and Shareholders' Equity
B69: Creditors | D69: =' Balance Sheet'!D30 -> 73 | E69: =' Balance Sheet'!E30 -> 88 | F69: =' Balance Sheet'!F30 -> 110 | G69: =' Balance Sheet'!G30 -> 184 | H69: =' Balance Sheet'!H30 -> 186 | I69: =Schedules!I145 -> 222.86301 | J69: =Schedules!J145 -> 268.92677 | K69: =Schedules!K145 -> 336.15847 | L69: =Schedules!L145 -> 416.49045 | M69: =Schedules!M145 -> 508.75483 | N69: =Schedules!N145 -> 612.58499 | O69: =Schedules!O145 -> 726.92185 | P69: =Schedules!P145 -> 849.92234 | ... V69: =Schedules!V145 -> 1436.9564
B70: Other Payables | D70: =SUM(' Balance Sheet'!D31,' Balance Sheet'!D33:D34,' Balance Sheet'!D35) -> 4.9 | E70: =SUM(' Balance Sheet'!E31,' Balance Sheet'!E33:E34,' Balance Sheet'!E35) -> 28.4 | F70: =SUM(' Balance Sheet'!F31,' Balance Sheet'!F33:F34,' Balance Sheet'!F35) -> 21.8 | G70: =SUM(' Balance Sheet'!G31,' Balance Sheet'!G33:G34,' Balance Sheet'!G35) -> 28 | H70: =SUM(' Balance Sheet'!H31,' Balance Sheet'!H33:H34,' Balance Sheet'!H35) -> 12.1 | I70: =Schedules!I154 -> 12.1 | J70: =Schedules!J154 -> 12.1 | K70: =Schedules!K154 -> 12.1 | L70: =Schedules!L154 -> 12.1 | M70: =Schedules!M154 -> 12.1 | N70: =Schedules!N154 -> 12.1 | O70: =Schedules!O154 -> 12.1 | P70: =Schedules!P154 -> 12.1 | ... V70: =Schedules!V154 -> 12.1
B71: Other Current Liabilities | D71: =' Balance Sheet'!D37 -> 236.4 | E71: =' Balance Sheet'!E37 -> 336.1 | F71: =' Balance Sheet'!F37 -> 422.2 | G71: =' Balance Sheet'!G37 -> 345 | H71: =' Balance Sheet'!H37 -> 244.3 | I71: =Schedules!I158 -> 244.3 | J71: =Schedules!J158 -> 244.3 | K71: =Schedules!K158 -> 244.3 | L71: =Schedules!L158 -> 244.3 | M71: =Schedules!M158 -> 244.3 | N71: =Schedules!N158 -> 244.3 | O71: =Schedules!O158 -> 244.3 | P71: =Schedules!P158 -> 244.3 | ... V71: =Schedules!V158 -> 244.3
B72: Short Term Borrowing | D72: =' Balance Sheet'!D36 -> 75 | E72: =' Balance Sheet'!E36 -> 80 | F72: =' Balance Sheet'!F36 -> 92 | G72: =' Balance Sheet'!G36 -> 221 | H72: =' Balance Sheet'!H36 -> 50 | I72: =Schedules!I182 -> 88.74 | J72: =Schedules!J182 -> 108.2628 | K72: =Schedules!K182 -> 135.3285 | L72: =Schedules!L182 -> 169.16062 | M72: =Schedules!M182 -> 173.74206 | N72: =Schedules!N182 -> 126.65796 | O72: =Schedules!O182 -> 101.11527 | P72: =Schedules!P182 -> 101.11527 | ... V72: =Schedules!V182 -> 101.11527
B73: Total Current Liabilities | D73: =SUM(D69:D72) -> 389.3 | E73: =SUM(E69:E72) -> 532.5 | F73: =SUM(F69:F72) -> 646 | G73: =SUM(G69:G72) -> 778 | H73: =SUM(H69:H72) -> 492.4 | I73: =SUM(I69:I72) -> 568.00301 | J73: =SUM(J69:J72) -> 633.58957 | K73: =SUM(K69:K72) -> 727.88697 | ... V73: =SUM(V69:V72) -> 1794.4717
B75: Long Term Borrowing | D75: =' Balance Sheet'!D40 -> 340 | E75: =' Balance Sheet'!E40 -> 768 | F75: =' Balance Sheet'!F40 -> 545 | G75: =' Balance Sheet'!G40 -> 547 | H75: =' Balance Sheet'!H40 -> 449 | I75: =Schedules!I179 -> 462.47 | J75: =Schedules!J179 -> 480.9688 | K75: =Schedules!K179 -> 500.20755 | L75: =Schedules!L179 -> 520.21585 | M75: =Schedules!M179 -> 541.02449 | N75: =Schedules!N179 -> 551.84498 | O75: =Schedules!O179 -> 557.36343 | P75: =Schedules!P179 -> 562.93706 | ... V75: =Schedules!V179 -> 562.93706
B76: Other Non-Current Liabilities | D76: =' Balance Sheet'!D41 -> 35.7 | E76: =' Balance Sheet'!E41 -> 97.5 | F76: =' Balance Sheet'!F41 -> 171 | G76: =' Balance Sheet'!G41 -> 214 | H76: =' Balance Sheet'!H41 -> 306.6 | I76: =H76 -> 306.6 | J76: =I76 -> 306.6 | K76: =J76 -> 306.6 | L76: =K76 -> 306.6 | M76: =L76 -> 306.6 | N76: =M76 -> 306.6 | O76: =N76 -> 306.6 | P76: =O76 -> 306.6 | ... V76: =U76 -> 306.6
B77: Total Non-Current Liabilities | D77: =SUM(D75:D76) -> 375.7 | E77: =SUM(E75:E76) -> 865.5 | F77: =SUM(F75:F76) -> 716 | G77: =SUM(G75:G76) -> 761 | H77: =SUM(H75:H76) -> 755.6 | I77: =SUM(I75:I76) -> 769.07 | J77: =SUM(J75:J76) -> 787.5688 | K77: =SUM(K75:K76) -> 806.80755 | ... V77: =SUM(V75:V76) -> 869.53706
B79: Equity Shares | D79: =' Balance Sheet'!D48 -> 252 | E79: =' Balance Sheet'!E48 -> 42 | F79: =' Balance Sheet'!F48 -> 42 | G79: =' Balance Sheet'!G48 -> 42 | H79: =' Balance Sheet'!H48 -> 43 | I79: =H79 -> 43 | J79: =I79 -> 43 | K79: =J79 -> 43 | L79: =K79 -> 43 | M79: =L79 -> 43 | N79: =M79 -> 43 | O79: =N79 -> 43 | P79: 43 | Q79: =P79 -> 43 | R79: =Q79 -> 43 | S79: =R79 -> 43 | T79: =S79 -> 43 | U79: =T79 -> 43 | V79: =U79 -> 43
B80: Retained Earnings | D80: =' Balance Sheet'!D49 -> 432 | E80: =' Balance Sheet'!E49 -> 684 | F80: =' Balance Sheet'!F49 -> 1028 | G80: =' Balance Sheet'!G49 -> 1213 | H80: =' Balance Sheet'!H49 -> 1861 | I80: =Schedules!I121 -> 2263.752 | J80: =Schedules!J121 -> 2763.9056 | K80: =Schedules!K121 -> 3379.58 | L80: =Schedules!L121 -> 4155.7743 | M80: =Schedules!M121 -> 5073.4861 | N80: =Schedules!N121 -> 6165.0186 | O80: =Schedules!O121 -> 7371.6471 | P80: =Schedules!P121 -> 8620.9035 | ... V80: =Schedules!V121 -> 15735.801 | X80: =_xlfn.RRI($V$8-$N$8,N80,V80) -> 0.1242666 | Y80: =_xlfn.RRI($V$8-$Q$8,Q80,V80) -> 0.095528351 | Z80: =_xlfn.RRI($V$8-$S$8,S80,V80) -> 0.082316767
B81: Total Shareholders' Equity | D81: =SUM(D79:D80) -> 684 | E81: =SUM(E79:E80) -> 726 | F81: =SUM(F79:F80) -> 1070 | G81: =SUM(G79:G80) -> 1255 | H81: =SUM(H79:H80) -> 1904 | I81: =SUM(I79:I80) -> 2306.752 | J81: =SUM(J79:J80) -> 2806.9056 | K81: =SUM(K79:K80) -> 3422.58 | ... V81: =SUM(V79:V80) -> 15778.801
B83: Total Liabilities and Shareholders' Equity | D83: =SUM(D81,D77,D73) -> 1449 | E83: =SUM(E81,E77,E73) -> 2124 | F83: =SUM(F81,F77,F73) -> 2432 | G83: =SUM(G81,G77,G73) -> 2794 | H83: =SUM(H81,H77,H73) -> 3152 | I83: =SUM(I81,I77,I73) -> 3643.825 | J83: =SUM(J81,J77,J73) -> 4228.0639 | K83: =SUM(K81,K77,K73) -> 4957.2746 | ... V83: =SUM(V81,V77,V73) -> 18442.81
D86: 365
B87: Net Working Capital | D87: =D56-D73 -> -207.524 | E87: =E56-E73 -> -85.274 | F87: =F56-F73 -> -226.799 | G87: =G56-G73 -> -277.239 | H87: =H56-H73 -> 281.171 | I87: =I56-I73 -> 412.02588 | J87: =J56-J73 -> 538.16823 | K87: =K56-K73 -> 684.14287 | ... V87: =V56-V73 -> 5853.8795
B88: Debtor Days | D88: =D54/D12*$D$86 -> 52.394451 | E88: =E54/E12*$D$86 -> 60.245003 | F88: =F54/F12*$D$86 -> 27.691956 | G88: =G54/G12*$D$86 -> 33.869881 | H88: =H54/H12*$D$86 -> 33.207843 | I88: =I54/I12*$D$86 -> 35 | J88: =J54/J12*$D$86 -> 35 | K88: =K54/K12*$D$86 -> 35 | ... V88: =V54/V12*$D$86 -> 35
B89: Inventory Days | D89: =D53/D13*$D$86 -> 51.194805 | E89: =E53/E13*$D$86 -> 73.863338 | F89: =F53/F13*$D$86 -> 69.399103 | G89: =G53/G13*$D$86 -> 90.475966 | H89: =H53/H13*$D$86 -> 104.6711 | I89: =I53/I13*$D$86 -> 89.090909 | J89: =J53/J13*$D$86 -> 90.073529 | K89: =K53/K13*$D$86 -> 93.75 | ... V89: =V53/V13*$D$86 -> 102.08333
B90: Creditors Days | D90: =D69/D13*$D$86 -> 69.207792 | E90: =E69/E13*$D$86 -> 42.207622 | F90: =F69/F13*$D$86 -> 36.008969 | G90: =G69/G13*$D$86 -> 63.298775 | H90: =H69/H13*$D$86 -> 50.177384 | I90: =I69/I13*$D$86 -> 50 | J90: =J69/J13*$D$86 -> 50 | K90: =K69/K13*$D$86 -> 50 | ... V90: =V69/V13*$D$86 -> 50
B91: Other Current Assets % Sales | D91: =D55/D12 -> 0.0097708082 | E91: =E55/E12 -> 0.007865893 | F91: =F55/F12 -> 0.011882998 | G91: =G55/G12 -> 0.026956973 | H91: =H55/H12 -> 0.051611765 | I91: =I55/I12 -> 0.05 | J91: =J55/J12 -> 0.05 | K91: =K55/K12 -> 0.05 | ... V91: =V55/V12 -> 0.05
B92: Other Current Liabilites % Sales | D92: =D71/D12 -> 0.28516285 | E92: =E71/E12 -> 0.2166989 | F92: =F71/F12 -> 0.19296161 | G92: =G71/G12 -> 0.17884914 | H92: =H71/H12 -> 0.095803922 | I92: =I71/I12 -> 0.082589588 | J92: =J71/J12 -> 0.067696383 | K92: =K71/K12 -> 0.054157107 | ... V92: =V71/V12 -> 0.011178879
B93: Other Payables % Sales | D93: =D70/D12 -> 0.0059107358 | E93: =E70/E12 -> 0.018310767 | F93: =F70/F12 -> 0.0099634369 | G93: =G70/G12 -> 0.014515293 | H93: =H70/H12 -> 0.004745098 | I93: =I70/I12 -> 0.0040906018 | J93: =J70/J12 -> 0.0033529523 | K93: =K70/K12 -> 0.0026823618 | ... V93: =V70/V12 -> 0.00055368168
A95: # | B95: Cash Flow
B97: Profit Before Tax | D97: ='Cash Flow'!D9 -> 160.86 | E97: ='Cash Flow'!E9 -> 383.42 | F97: ='Cash Flow'!F9 -> 522.48 | G97: ='Cash Flow'!G9 -> 290.72 | H97: ='Cash Flow'!H9 -> 540.1 | I97: =I37 -> 578.73406 | J97: =J37 -> 726.50696 | K97: =K37 -> 914.18247 | L97: =L37 -> 1178.7237 | M97: =M37 -> 1495.6042 | N97: =N37 -> 1870.1065 | O97: =O37 -> 2303.5614 | P97: =P37 -> 2782.4323 | ... V97: =V37 -> 5844.2857
B98: Less: Interest Income | D98: ='Cash Flow'!D13 -> -0.15 | E98: ='Cash Flow'!E13 -> -0.16 | F98: ='Cash Flow'!F13 -> -0.84 | G98: ='Cash Flow'!G13 -> -0.1 | H98: ='Cash Flow'!H13 -> -0.33 | I98: =H98 -> -0.33 | J98: =I98 -> -0.33 | K98: =J98 -> -0.33 | L98: =K98 -> -0.33 | M98: =L98 -> -0.33 | N98: =M98 -> -0.33 | O98: =N98 -> -0.33 | P98: =O98 -> -0.33 | ... V98: =U98 -> -0.33
B99: Add: Interest Expenses | D99: ='Cash Flow'!D14 -> 29.11 | E99: ='Cash Flow'!E14 -> 44.27 | F99: ='Cash Flow'!F14 -> 65.5 | G99: ='Cash Flow'!G14 -> 73.49 | H99: ='Cash Flow'!H14 -> 53.27 | I99: =I35 -> 40.433085 | J99: =J35 -> 43.907002 | K99: =K35 -> 47.153555 | L99: =L35 -> 51.009132 | M99: =M35 -> 54.059506 | N99: =N35 -> 53.640875 | O99: =O35 -> 51.473793 | P99: =P35 -> 50.917445 | ... V99: =V35 -> 51.13203
B100: Add: Depreciation | D100: ='Cash Flow'!D11 -> 70.31 | E100: ='Cash Flow'!E11 -> 82.68 | F100: ='Cash Flow'!F11 -> 105.72 | G100: ='Cash Flow'!G11 -> 120.33 | H100: ='Cash Flow'!H11 -> 129.33 | I100: =I29 -> 161.47286 | J100: =J29 -> 204.33 | K100: =K29 -> 257.90143 | L100: =L29 -> 322.18714 | M100: =M29 -> 397.18714 | N100: =N29 -> 482.90143 | O100: =O29 -> 579.33 | P100: =P29 -> 686.47286 | ... V100: =V29 -> 1425.5758
B101: Add: Amortization | D101: ='Cash Flow'!D12 -> 3.23 | E101: ='Cash Flow'!E12 -> 3.23 | F101: ='Cash Flow'!F12 -> 3.23 | G101: ='Cash Flow'!G12 -> 3.23 | H101: ='Cash Flow'!H12 -> 3.23 | I101: =I30 -> 3.23 | J101: =J30 -> 3.23 | K101: =K30 -> 3.23 | L101: =L30 -> 3.23 | M101: =M30 -> 3.23 | N101: =N30 -> 3.23 | O101: =O30 -> 0 | P101: =P30 -> 0 | ... V101: =V30 -> 0
B102: Add: Other Items | D102: =SUM('Cash Flow'!D15:D21) -> 0.116 | E102: =SUM('Cash Flow'!E15:E21) -> 0.24 | F102: =SUM('Cash Flow'!F15:F21) -> -3.265 | G102: =SUM('Cash Flow'!G15:G21) -> -1.1 | H102: =SUM('Cash Flow'!H15:H21) -> -7.91 | I102: 0 | J102: =I102 -> 0 | K102: =J102 -> 0 | L102: =K102 -> 0 | M102: =L102 -> 0 | N102: =M102 -> 0 | O102: =N102 -> 0 | P102: =O102 -> 0 | Q102: =P102 -> 0 | ... V102: =U102 -> 0
B103: Less: Change in Working Capital | D103: ='Cash Flow'!D23 -> -5.65 | E103: ='Cash Flow'!E23 -> -169.41 | F103: ='Cash Flow'!F23 -> 40.82 | G103: ='Cash Flow'!G23 -> -38.4 | H103: ='Cash Flow'!H23 -> -166.68 | I103: =Schedules!I174*-1 -> -40.172192 | J103: =Schedules!J174*-1 -> -136.23819 | K103: =Schedules!K174*-1 -> -210.22263 | L103: =Schedules!L174*-1 -> -272.6653 | M103: =Schedules!M174*-1 -> -270.32061 | N103: =Schedules!N174*-1 -> -303.89247 | O103: =Schedules!O174*-1 -> -306.56952 | P103: =Schedules!P174*-1 -> -386.8698 | ... V103: =Schedules!V174*-1 -> -223.09889
B104: Less: Tax Paid | D104: ='Cash Flow'!D25 -> -28.62 | E104: ='Cash Flow'!E25 -> -60.45 | F104: ='Cash Flow'!F25 -> -107.48 | G104: ='Cash Flow'!G25 -> -50.53 | H104: ='Cash Flow'!H25 -> -110.45 | I104: =I38*-1 -> -145.66736 | J104: =J38*-1 -> -182.8618 | K104: =K38*-1 -> -230.09973 | L104: =L38*-1 -> -296.68476 | M104: =M38*-1 -> -376.44358 | N104: =N38*-1 -> -470.7058 | O104: =O38*-1 -> -579.8064 | P104: =P38*-1 -> -700.33821 | ... V104: =V38*-1 -> -1471.0067
B105: Cash Flow from Operations Activities | D105: =SUM(D97:D104) -> 229.206 | E105: =SUM(E97:E104) -> 283.82 | F105: =SUM(F97:F104) -> 626.165 | G105: =SUM(G97:G104) -> 397.64 | H105: =SUM(H97:H104) -> 440.56 | I105: =SUM(I97:I104) -> 597.70045 | J105: =SUM(J97:J104) -> 658.54397 | K105: =SUM(K97:K104) -> 781.81509 | ... V105: =SUM(V97:V104) -> 5626.5579
B107: Net Purchase of Fixed Assets | D107: =SUM('Cash Flow'!D29:D30) -> -196.75 | E107: =SUM('Cash Flow'!E29:E30) -> -456.3 | F107: =SUM('Cash Flow'!F29:F30) -> -416.45 | G107: =SUM('Cash Flow'!G29:G30) -> -398.44 | H107: =SUM('Cash Flow'!H29:H30) -> -186.35 | I107: =Schedules!I71*-1 -> -450 | J107: =Schedules!J71*-1 -> -600 | K107: =Schedules!K71*-1 -> -750 | L107: =Schedules!L71*-1 -> -900 | M107: =Schedules!M71*-1 -> -1050 | N107: =Schedules!N71*-1 -> -1200 | O107: =Schedules!O71*-1 -> -1350 | P107: =Schedules!P71*-1 -> -1500 | ... V107: =Schedules!V71*-1 -> -1897.9785
B108: Net Purchase of Investments | D108: =SUM('Cash Flow'!D31,'Cash Flow'!D36:D37) -> 0 | E108: =SUM('Cash Flow'!E31,'Cash Flow'!E36:E37) -> -0.05 | F108: =SUM('Cash Flow'!F31,'Cash Flow'!F36:F37) -> -20.54 | G108: =SUM('Cash Flow'!G31,'Cash Flow'!G36:G37) -> 0 | H108: =SUM('Cash Flow'!H31,'Cash Flow'!H36:H37) -> -74.71 | I108: 0 | J108: =I108 -> 0 | K108: =J108 -> 0 | L108: =K108 -> 0 | M108: =L108 -> 0 | N108: =M108 -> 0 | O108: =N108 -> 0 | P108: =O108 -> 0 | Q108: =P108 -> 0 | ... V108: =U108 -> 0
B109: Interest Received | D109: ='Cash Flow'!D35 -> 0.08 | E109: ='Cash Flow'!E35 -> 0.29 | F109: ='Cash Flow'!F35 -> 0.85 | G109: ='Cash Flow'!G35 -> 0.08 | H109: ='Cash Flow'!H35 -> 0.26 | I109: =H109 -> 0.26 | J109: =I109 -> 0.26 | K109: =J109 -> 0.26 | L109: =K109 -> 0.26 | M109: =L109 -> 0.26 | N109: =M109 -> 0.26 | O109: =N109 -> 0.26 | P109: =O109 -> 0.26 | ... V109: =U109 -> 0.26
B110: Other Investments | D110: =SUM('Cash Flow'!D32:D34) -> -0.06 | E110: =SUM('Cash Flow'!E32:E34) -> 1.38 | F110: =SUM('Cash Flow'!F32:F34) -> -1.07 | G110: =SUM('Cash Flow'!G32:G34) -> -2.74 | H110: =SUM('Cash Flow'!H32:H34) -> -0.76 | I110: 0 | J110: =I110 -> 0 | K110: =J110 -> 0 | L110: =K110 -> 0 | M110: =L110 -> 0 | N110: =M110 -> 0 | O110: =N110 -> 0 | P110: =O110 -> 0 | Q110: =P110 -> 0 | ... V110: =U110 -> 0
B111: Cash Flow from Investments Activities | D111: =SUM(D107:D110) -> -196.73 | E111: =SUM(E107:E110) -> -454.68 | F111: =SUM(F107:F110) -> -437.21 | G111: =SUM(G107:G110) -> -401.1 | H111: =SUM(H107:H110) -> -261.56 | I111: =SUM(I107:I110) -> -449.74 | J111: =SUM(J107:J110) -> -599.74 | K111: =SUM(K107:K110) -> -749.74 | ... V111: =SUM(V107:V110) -> -1897.7185
B113: Net Proceeds from Long Term Borrowing | D113: =SUM('Cash Flow'!D42:D43) -> -46.51 | E113: =SUM('Cash Flow'!E42:E43) -> 239.25 | F113: =SUM('Cash Flow'!F42:F43) -> -64.35 | G113: =SUM('Cash Flow'!G42:G43) -> 16.74 | H113: =SUM('Cash Flow'!H42:H43) -> -111.55 | I113: =I75-H75 -> 13.47 | J113: =J75-I75 -> 18.4988 | K113: =K75-J75 -> 19.238752 | L113: =L75-K75 -> 20.008302 | M113: =M75-L75 -> 20.808634 | N113: =N75-M75 -> 10.82049 | O113: =O75-N75 -> 5.5184498 | P113: =P75-O75 -> 5.5736343 | ... V113: =V75-U75 -> 0
B114: Net Proceeds from Short Term Borrowing | D114: ='Cash Flow'!D44 -> 55.32 | E114: ='Cash Flow'!E44 -> 5.11 | F114: ='Cash Flow'!F44 -> 11.57 | G114: ='Cash Flow'!G44 -> 129.24 | H114: ='Cash Flow'!H44 -> -171.55 | I114: =I72-H72 -> 38.74 | J114: =J72-I72 -> 19.5228 | K114: =K72-J72 -> 27.0657 | L114: =L72-K72 -> 33.832125 | M114: =M72-L72 -> 4.5814336 | N114: =N72-M72 -> -47.084098 | O114: =O72-N72 -> -25.542689 | P114: =P72-O72 -> 0 | ... V114: =V72-U72 -> 0
B115: Net Issue of Share Capital | D115: =SUM('Cash Flow'!D48:D49) -> 0 | E115: =SUM('Cash Flow'!E48:E49) -> 0 | F115: =SUM('Cash Flow'!F48:F49) -> 0 | G115: =SUM('Cash Flow'!G48:G49) -> 0 | H115: =SUM('Cash Flow'!H48:H49) -> 324.72 | I115: 0 | J115: =I115 -> 0 | K115: =J115 -> 0 | L115: =K115 -> 0 | M115: =L115 -> 0 | N115: =M115 -> 0 | O115: =N115 -> 0 | P115: =O115 -> 0 | Q115: =P115 -> 0 | ... V115: =U115 -> 0
B116: Interest Expense | D116: ='Cash Flow'!D41 -> -39.72 | E116: ='Cash Flow'!E41 -> -48.04 | F116: ='Cash Flow'!F41 -> -60.45 | G116: ='Cash Flow'!G41 -> -72.02 | H116: ='Cash Flow'!H41 -> -65.94 | I116: =I99*-1 -> -40.433085 | J116: =J99*-1 -> -43.907002 | K116: =K99*-1 -> -47.153555 | L116: =L99*-1 -> -51.009132 | M116: =M99*-1 -> -54.059506 | N116: =N99*-1 -> -53.640875 | O116: =O99*-1 -> -51.473793 | P116: =P99*-1 -> -50.917445 | ... V116: =V99*-1 -> -51.13203
B117: Dividend paid on Redeemable Preference Shares | D117: ='Cash Flow'!D46 -> 0 | E117: ='Cash Flow'!E46 -> 0 | F117: ='Cash Flow'!F46 -> -13.85 | G117: ='Cash Flow'!G46 -> -14.75 | H117: ='Cash Flow'!H46 -> -10.32 | I117: 0 | J117: =I117 -> 0 | K117: =J117 -> 0 | L117: =K117 -> 0 | M117: =L117 -> 0 | N117: =M117 -> 0 | O117: =N117 -> 0 | P117: =O117 -> 0 | Q117: =P117 -> 0 | ... V117: =U117 -> 0
B118: Dividend paid on Equity Shares | D118: ='Cash Flow'!D47 -> 0 | E118: ='Cash Flow'!E47 -> 0 | F118: ='Cash Flow'!F47 -> -10.37 | G118: ='Cash Flow'!G47 -> -10.37 | H118: ='Cash Flow'!H47 -> -31.54 | I118: =Schedules!I120*-1 -> -30.314669 | J118: =Schedules!J120*-1 -> -43.491613 | K118: =Schedules!K120*-1 -> -68.408274 | L118: =Schedules!L120*-1 -> -105.84468 | M118: =Schedules!M120*-1 -> -201.44891 | N118: =Schedules!N120*-1 -> -307.86815 | O118: =Schedules!O120*-1 -> -517.1265 | P118: =Schedules!P120*-1 -> -832.83764 | ... V118: =Schedules!V120*-1 -> -3279.9592
B119: Payment of Lease Liability | D119: ='Cash Flow'!D45 -> -0.99 | E119: ='Cash Flow'!E45 -> -1.11 | F119: ='Cash Flow'!F45 -> -1.41 | G119: ='Cash Flow'!G45 -> -1.44 | H119: ='Cash Flow'!H45 -> -2.36 | I119: 0 | J119: =I119 -> 0 | K119: =J119 -> 0 | L119: =K119 -> 0 | M119: =L119 -> 0 | N119: =M119 -> 0 | O119: =N119 -> 0 | P119: =O119 -> 0 | Q119: =P119 -> 0 | ... V119: =U119 -> 0
B120: Redemption of Redeemable Preference Shares | D120: ='Cash Flow'!D50 -> 0 | E120: ='Cash Flow'!E50 -> 0 | F120: ='Cash Flow'!F50 -> -60.92 | G120: ='Cash Flow'!G50 -> -55 | H120: ='Cash Flow'!H50 -> -95 | I120: 0 | J120: =I120 -> 0 | K120: =J120 -> 0 | L120: =K120 -> 0 | M120: =L120 -> 0 | N120: =M120 -> 0 | O120: =N120 -> 0 | P120: =O120 -> 0 | Q120: =P120 -> 0 | ... V120: =U120 -> 0
B121: Cash Flow from Financing Activities | D121: =SUM(D113:D120) -> -31.9 | E121: =SUM(E113:E120) -> 195.21 | F121: =SUM(F113:F120) -> -199.78 | G121: =SUM(G113:G120) -> -7.6 | H121: =SUM(H113:H120) -> -163.54 | I121: =SUM(I113:I120) -> -18.537754 | J121: =SUM(J113:J120) -> -49.377014 | K121: =SUM(K113:K120) -> -69.257377 | ... V121: =SUM(V113:V120) -> -3331.0912
B123: Net Change in Cash | D123: ='3 Statement Model'!D121+'3 Statement Model'!D111+'3 Statement Model'!D105 -> 0.576 | E123: ='3 Statement Model'!E121+'3 Statement Model'!E111+'3 Statement Model'!E105 -> 24.35 | F123: ='3 Statement Model'!F121+'3 Statement Model'!F111+'3 Statement Model'!F105 -> -10.825 | G123: ='3 Statement Model'!G121+'3 Statement Model'!G111+'3 Statement Model'!G105 -> -11.06 | H123: ='3 Statement Model'!H121+'3 Statement Model'!H111+'3 Statement Model'!H105 -> 15.46 | I123: ='3 Statement Model'!I121+'3 Statement Model'!I111+'3 Statement Model'!I105 -> 129.42269 | J123: ='3 Statement Model'!J121+'3 Statement Model'!J111+'3 Statement Model'!J105 -> 9.4269581 | K123: ='3 Statement Model'!K121+'3 Statement Model'!K111+'3 Statement Model'!K105 -> -37.182282 | ... V123: ='3 Statement Model'!V121+'3 Statement Model'!V111+'3 Statement Model'!V105 -> 397.74816
B124: Opening Cash Balance | D124: ='Cash Flow'!D53 -> 0.1 | E124: =D125 -> 0.676 | F124: =E125 -> 25.026 | G124: =F125 -> 14.201 | H124: =G125 -> 3.141 | I124: =H125 -> 18.601 | J124: =I125 -> 148.02369 | K124: =J125 -> 157.45065 | L124: =K125 -> 120.26837 | ... V124: =U125 -> 1125.21
B125: Closing Cash Balance | D125: =SUM(D123:D124) -> 0.676 | E125: =SUM(E123:E124) -> 25.026 | F125: =SUM(F123:F124) -> 14.201 | G125: =SUM(G123:G124) -> 3.141 | H125: =SUM(H123:H124) -> 18.601 | I125: =SUM(I123:I124) -> 148.02369 | J125: =SUM(J123:J124) -> 157.45065 | K125: =SUM(K123:K124) -> 120.26837 | ... V125: =SUM(V123:V124) -> 1522.9582

Sheet CommonSizeStatement
B2: ='Input Sheet'!C5 -> Epigral Ltd.
B3: Common Size Statement | H3: Current Case | I3: 2
D7: Actual | I7: Explicit Forecast Period | Q7: Terminal Value
B8: In INR Crores Other wise Stated | D8: =Schedules!D8 -> 2021 | E8: =Schedules!E8 -> 2022 | F8: =Schedules!F8 -> 2023 | G8: =Schedules!G8 -> 2024 | H8: =Schedules!H8 -> 2025 | I8: =H8+1 -> 2026 | J8: =I8+1 -> 2027 | K8: =J8+1 -> 2028 | L8: =K8+1 -> 2029 | M8: =L8+1 -> 2030 | N8: =M8+1 -> 2031 | O8: =N8+1 -> 2032 | P8: =O8+1 -> 2033 | Q8: ='3 Statement Model'!Q8 -> 2034 | R8: ='3 Statement Model'!R8 -> 2035 | S8: ='3 Statement Model'!S8 -> 2036 | T8: ='3 Statement Model'!T8 -> 2037 | U8: ='3 Statement Model'!U8 -> 2038 | V8: ='3 Statement Model'!V8 -> 2039
A10: # | B10: Common Size Statement Income Statement
B12: Revenue | D12: ='3 Statement Model'!D12/'3 Statement Model'!D$12 -> 1 | E12: ='3 Statement Model'!E12/'3 Statement Model'!E$12 -> 1 | F12: ='3 Statement Model'!F12/'3 Statement Model'!F$12 -> 1 | G12: ='3 Statement Model'!G12/'3 Statement Model'!G$12 -> 1 | H12: ='3 Statement Model'!H12/'3 Statement Model'!H$12 -> 1 | I12: ='3 Statement Model'!I12/'3 Statement Model'!I$12 -> 1 | J12: ='3 Statement Model'!J12/'3 Statement Model'!J$12 -> 1 | K12: ='3 Statement Model'!K12/'3 Statement Model'!K$12 -> 1 | ... V12: ='3 Statement Model'!V12/'3 Statement Model'!V$12 -> 1
B13: Less: Cost of Goods Sold | D13: ='3 Statement Model'!D13/'3 Statement Model'!D$12 -> 0.46441496 | E13: ='3 Statement Model'!E13/'3 Statement Model'!E$12 -> 0.49065119 | F13: ='3 Statement Model'!F13/'3 Statement Model'!F$12 -> 0.50959781 | G13: ='3 Statement Model'!G13/'3 Statement Model'!G$12 -> 0.55002592 | H13: ='3 Statement Model'!H13/'3 Statement Model'!H$12 -> 0.53058824 | I13: ='3 Statement Model'!I13/'3 Statement Model'!I$12 -> 0.55 | J13: ='3 Statement Model'!J13/'3 Statement Model'!J$12 -> 0.544 | K13: ='3 Statement Model'!K13/'3 Statement Model'!K$12 -> 0.544 | ... V13: ='3 Statement Model'!V13/'3 Statement Model'!V$12 -> 0.48
B14: Gross Profit | D14: =D12-D13 -> 0.53558504 | E14: =E12-E13 -> 0.50934881 | F14: =F12-F13 -> 0.49040219 | G14: =G12-G13 -> 0.44997408 | H14: =H12-H13 -> 0.46941176 | I14: =I12-I13 -> 0.45 | J14: =J12-J13 -> 0.456 | K14: =K12-K13 -> 0.456 | ... V14: =V12-V13 -> 0.52
B16: Less: SG&A Expense (Excluding Depreciation & Interest)
B17: =Schedules!B24 -> Salaries, Wages & Bonus | D17: ='3 Statement Model'!D19/'3 Statement Model'!D$12 -> 0.049457177 | E17: ='3 Statement Model'!E19/'3 Statement Model'!E$12 -> 0.033526757 | F17: ='3 Statement Model'!F19/'3 Statement Model'!F$12 -> 0.031535649 | G17: ='3 Statement Model'!G19/'3 Statement Model'!G$12 -> 0.041990669 | H17: ='3 Statement Model'!H19/'3 Statement Model'!H$12 -> 0.038431373 | I17: ='3 Statement Model'!I19/'3 Statement Model'!I$12 -> 0.038 | J17: ='3 Statement Model'!J19/'3 Statement Model'!J$12 -> 0.038 | K17: ='3 Statement Model'!K19/'3 Statement Model'!K$12 -> 0.038 | ... V17: ='3 Statement Model'!V19/'3 Statement Model'!V$12 -> 0.038
B18: =Schedules!B29 -> Power & Fuel Cost | D18: ='3 Statement Model'!D20/'3 Statement Model'!D$12 -> 0.031363088 | E18: ='3 Statement Model'!E20/'3 Statement Model'!E$12 -> 0.064474533 | F18: ='3 Statement Model'!F20/'3 Statement Model'!F$12 -> 0.070383912 | G18: ='3 Statement Model'!G20/'3 Statement Model'!G$12 -> 0.073094868 | H18: ='3 Statement Model'!H20/'3 Statement Model'!H$12 -> 0.070588235 | I18: ='3 Statement Model'!I20/'3 Statement Model'!I$12 -> 0.07 | J18: ='3 Statement Model'!J20/'3 Statement Model'!J$12 -> 0.07 | K18: ='3 Statement Model'!K20/'3 Statement Model'!K$12 -> 0.07 | ... V18: ='3 Statement Model'!V20/'3 Statement Model'!V$12 -> 0.07
B19: =Schedules!B34 -> Other Operating Expenses | D19: ='3 Statement Model'!D21/'3 Statement Model'!D$12 -> 0.053075995 | E19: ='3 Statement Model'!E21/'3 Statement Model'!E$12 -> 0.040618956 | F19: ='3 Statement Model'!F21/'3 Statement Model'!F$12 -> 0.036563071 | G19: ='3 Statement Model'!G21/'3 Statement Model'!G$12 -> 0.044582685 | H19: ='3 Statement Model'!H21/'3 Statement Model'!H$12 -> 0.036862745 | I19: ='3 Statement Model'!I21/'3 Statement Model'!I$12 -> 0.041 | J19: ='3 Statement Model'!J21/'3 Statement Model'!J$12 -> 0.041 | K19: ='3 Statement Model'!K21/'3 Statement Model'!K$12 -> 0.041 | ... V19: ='3 Statement Model'!V21/'3 Statement Model'!V$12 -> 0.041
B20: =Schedules!B39 -> Other SG&A Expenses | D20: ='3 Statement Model'!D22/'3 Statement Model'!D$12 -> 0.08588661 | E20: ='3 Statement Model'!E22/'3 Statement Model'!E$12 -> 0.041779497 | F20: ='3 Statement Model'!F22/'3 Statement Model'!F$12 -> 0.036837294 | G20: ='3 Statement Model'!G22/'3 Statement Model'!G$12 -> 0.041109383 | H20: ='3 Statement Model'!H22/'3 Statement Model'!H$12 -> 0.04454902 | I20: ='3 Statement Model'!I22/'3 Statement Model'!I$12 -> 0.041 | J20: ='3 Statement Model'!J22/'3 Statement Model'!J$12 -> 0.041 | K20: ='3 Statement Model'!K22/'3 Statement Model'!K$12 -> 0.041 | ... V20: ='3 Statement Model'!V22/'3 Statement Model'!V$12 -> 0.041
B21: EBITDA | D21: ='3 Statement Model'!D24/'3 Statement Model'!D$12 -> 0.31580217 | E21: ='3 Statement Model'!E24/'3 Statement Model'!E$12 -> 0.32894907 | F21: ='3 Statement Model'!F24/'3 Statement Model'!F$12 -> 0.31508227 | G21: ='3 Statement Model'!G24/'3 Statement Model'!G$12 -> 0.24919647 | H21: ='3 Statement Model'!H24/'3 Statement Model'!H$12 -> 0.27898039 | I21: ='3 Statement Model'!I24/'3 Statement Model'!I$12 -> 0.26 | J21: ='3 Statement Model'!J24/'3 Statement Model'!J$12 -> 0.266 | K21: ='3 Statement Model'!K24/'3 Statement Model'!K$12 -> 0.266 | ... V21: ='3 Statement Model'!V24/'3 Statement Model'!V$12 -> 0.33
B23: Less: Depreciation & Amortization
B24: Depreciation | D24: ='3 Statement Model'!D29/'3 Statement Model'!D$12 -> 0.085367913 | E24: ='3 Statement Model'!E29/'3 Statement Model'!E$12 -> 0.053301096 | F24: ='3 Statement Model'!F29/'3 Statement Model'!F$12 -> 0.048318099 | G24: ='3 Statement Model'!G29/'3 Statement Model'!G$12 -> 0.062379471 | H24: ='3 Statement Model'!H29/'3 Statement Model'!H$12 -> 0.050717647 | I24: ='3 Statement Model'!I29/'3 Statement Model'!I$12 -> 0.054588525 | J24: ='3 Statement Model'!J29/'3 Statement Model'!J$12 -> 0.056620557 | K24: ='3 Statement Model'!K29/'3 Statement Model'!K$12 -> 0.057172309 | ... V24: ='3 Statement Model'!V29/'3 Statement Model'!V$12 -> 0.065232663
B25: Amortization | D25: ='3 Statement Model'!D30/'3 Statement Model'!D$12 -> 0.0038962606 | E25: ='3 Statement Model'!E30/'3 Statement Model'!E$12 -> 0.0020825274 | F25: ='3 Statement Model'!F30/'3 Statement Model'!F$12 -> 0.001476234 | G25: ='3 Statement Model'!G30/'3 Statement Model'!G$12 -> 0.0016744427 | H25: ='3 Statement Model'!H30/'3 Statement Model'!H$12 -> 0.0012666667 | I25: ='3 Statement Model'!I30/'3 Statement Model'!I$12 -> 0.001091954 | J25: ='3 Statement Model'!J30/'3 Statement Model'!J$12 -> 0.00089504428 | K25: ='3 Statement Model'!K30/'3 Statement Model'!K$12 -> 0.00071603542 | ... V25: ='3 Statement Model'!V30/'3 Statement Model'!V$12 -> 0
B26: EBIT | D26: ='3 Statement Model'!D31/'3 Statement Model'!D$12 -> 0.226538 | E26: ='3 Statement Model'!E31/'3 Statement Model'!E$12 -> 0.27356544 | F26: ='3 Statement Model'!F31/'3 Statement Model'!F$12 -> 0.26528793 | G26: ='3 Statement Model'!G31/'3 Statement Model'!G$12 -> 0.18514256 | H26: ='3 Statement Model'!H31/'3 Statement Model'!H$12 -> 0.22699608 | I26: ='3 Statement Model'!I31/'3 Statement Model'!I$12 -> 0.20431952 | J26: ='3 Statement Model'!J31/'3 Statement Model'!J$12 -> 0.2084844 | K26: ='3 Statement Model'!K31/'3 Statement Model'!K$12 -> 0.20811166 | ... V26: ='3 Statement Model'!V31/'3 Statement Model'!V$12 -> 0.26476734
B28: Less : Interest Expense | D28: ='3 Statement Model'!D35/'3 Statement Model'!D$12 -> 0.041013269 | E28: ='3 Statement Model'!E35/'3 Statement Model'!E$12 -> 0.030947776 | F28: ='3 Statement Model'!F35/'3 Statement Model'!F$12 -> 0.030621572 | G28: ='3 Statement Model'!G35/'3 Statement Model'!G$12 -> 0.037843442 | H28: ='3 Statement Model'!H35/'3 Statement Model'!H$12 -> 0.020784314 | I28: ='3 Statement Model'!I35/'3 Statement Model'!I$12 -> 0.013669062 | J28: ='3 Statement Model'!J35/'3 Statement Model'!J$12 -> 0.012166783 | K28: ='3 Statement Model'!K35/'3 Statement Model'!K$12 -> 0.010453132 | ... V28: ='3 Statement Model'!V35/'3 Statement Model'!V$12 -> 0.0023397412
B29: Add : Other Income | D29: ='3 Statement Model'!D36/'3 Statement Model'!D$12 -> 0.0090470446 | E29: ='3 Statement Model'!E36/'3 Statement Model'!E$12 -> 0.0053513862 | F29: ='3 Statement Model'!F36/'3 Statement Model'!F$12 -> 0.004250457 | G29: ='3 Statement Model'!G36/'3 Statement Model'!G$12 -> 0.0034214619 | H29: ='3 Statement Model'!H36/'3 Statement Model'!H$12 -> 0.0058823529 | I29: ='3 Statement Model'!I36/'3 Statement Model'!I$12 -> 0.005 | J29: ='3 Statement Model'!J36/'3 Statement Model'!J$12 -> 0.005 | K29: ='3 Statement Model'!K36/'3 Statement Model'!K$12 -> 0.005 | ... V29: ='3 Statement Model'!V36/'3 Statement Model'!V$12 -> 0.005
B30: Earning Before Taxes | D30: ='3 Statement Model'!D37/'3 Statement Model'!D$12 -> 0.19457177 | E30: ='3 Statement Model'!E37/'3 Statement Model'!E$12 -> 0.24796905 | F30: ='3 Statement Model'!F37/'3 Statement Model'!F$12 -> 0.23891682 | G30: ='3 Statement Model'!G37/'3 Statement Model'!G$12 -> 0.15072058 | H30: ='3 Statement Model'!H37/'3 Statement Model'!H$12 -> 0.21209412 | I30: ='3 Statement Model'!I37/'3 Statement Model'!I$12 -> 0.19565046 | J30: ='3 Statement Model'!J37/'3 Statement Model'!J$12 -> 0.20131762 | K30: ='3 Statement Model'!K37/'3 Statement Model'!K$12 -> 0.20265852 | ... V30: ='3 Statement Model'!V37/'3 Statement Model'!V$12 -> 0.2674276
B31: Less: Taxes | D31: ='3 Statement Model'!D38/'3 Statement Model'!D$12 -> 0.072376357 | E31: ='3 Statement Model'!E38/'3 Statement Model'!E$12 -> 0.084461638 | F31: ='3 Statement Model'!F38/'3 Statement Model'!F$12 -> 0.077239488 | G31: ='3 Statement Model'!G38/'3 Statement Model'!G$12 -> 0.049248315 | H31: ='3 Statement Model'!H38/'3 Statement Model'!H$12 -> 0.071764706 | I31: ='3 Statement Model'!I38/'3 Statement Model'!I$12 -> 0.049245221 | J31: ='3 Statement Model'!J38/'3 Statement Model'!J$12 -> 0.050671644 | K31: ='3 Statement Model'!K38/'3 Statement Model'!K$12 -> 0.05100915 | ... V31: ='3 Statement Model'!V38/'3 Statement Model'!V$12 -> 0.067311526
B32: Net Income | D32: ='3 Statement Model'!D39/'3 Statement Model'!D$12 -> 0.12219542 | E32: ='3 Statement Model'!E39/'3 Statement Model'!E$12 -> 0.16350741 | F32: ='3 Statement Model'!F39/'3 Statement Model'!F$12 -> 0.16167733 | G32: ='3 Statement Model'!G39/'3 Statement Model'!G$12 -> 0.10147227 | H32: ='3 Statement Model'!H39/'3 Statement Model'!H$12 -> 0.14032941 | I32: ='3 Statement Model'!I39/'3 Statement Model'!I$12 -> 0.14640524 | J32: ='3 Statement Model'!J39/'3 Statement Model'!J$12 -> 0.15064597 | K32: ='3 Statement Model'!K39/'3 Statement Model'!K$12 -> 0.15164937 | ... V32: ='3 Statement Model'!V39/'3 Statement Model'!V$12 -> 0.20011607
A34: # | B34: Common Size Statement Balance Sheet
B36: Assets
B37: Cash | D37: ='3 Statement Model'!D51/'3 Statement Model'!D$64 -> 0.00046653637 | E37: ='3 Statement Model'!E51/'3 Statement Model'!E$64 -> 0.011782342 | F37: ='3 Statement Model'!F51/'3 Statement Model'!F$64 -> 0.0058387444 | G37: ='3 Statement Model'!G51/'3 Statement Model'!G$64 -> 0.0011242104 | H37: ='3 Statement Model'!H51/'3 Statement Model'!H$64 -> 0.0059014055 | I37: ='3 Statement Model'!I51/'3 Statement Model'!I$64 -> 0.04062616 | J37: ='3 Statement Model'!J51/'3 Statement Model'!J$64 -> 0.03724038 | K37: ='3 Statement Model'!K51/'3 Statement Model'!K$64 -> 0.024260736 | ... V37: ='3 Statement Model'!V51/'3 Statement Model'!V$64 -> 0.082581947
B38: Cash at Bank | D38: ='3 Statement Model'!D52/'3 Statement Model'!D$64 -> 0 | E38: ='3 Statement Model'!E52/'3 Statement Model'!E$64 -> 0 | F38: ='3 Statement Model'!F52/'3 Statement Model'!F$64 -> 0.00041115023 | G38: ='3 Statement Model'!G52/'3 Statement Model'!G$64 -> 0.0012956516 | H38: ='3 Statement Model'!H52/'3 Statement Model'!H$64 -> 0.001066003 | I38: ='3 Statement Model'!I52/'3 Statement Model'!I$64 -> 0.00092217602 | J38: ='3 Statement Model'!J52/'3 Statement Model'!J$64 -> 0.00079471046 | K38: ='3 Statement Model'!K52/'3 Statement Model'!K$64 -> 0.00067778482 | ... V38: ='3 Statement Model'!V52/'3 Statement Model'!V$64 -> 0.00018219498
B39: Inventory | D39: ='3 Statement Model'!D53/'3 Statement Model'!D$64 -> 0.037267698 | E39: ='3 Statement Model'!E53/'3 Statement Model'!E$64 -> 0.072503821 | F39: ='3 Statement Model'!F53/'3 Statement Model'!F$64 -> 0.087163849 | G39: ='3 Statement Model'!G53/'3 Statement Model'!G$64 -> 0.094131593 | H39: ='3 Statement Model'!H53/'3 Statement Model'!H$64 -> 0.12309797 | I39: ='3 Statement Model'!I53/'3 Statement Model'!I$64 -> 0.10898731 | J39: ='3 Statement Model'!J53/'3 Statement Model'!J$64 -> 0.11458582 | K39: ='3 Statement Model'!K53/'3 Statement Model'!K$64 -> 0.12714459 | ... V39: ='3 Statement Model'!V53/'3 Statement Model'!V$64 -> 0.15908366
B40: Trade Receivable | D40: ='3 Statement Model'!D54/'3 Statement Model'!D$64 -> 0.082126964 | E40: ='3 Statement Model'!E54/'3 Statement Model'!E$64 -> 0.12052583 | F40: ='3 Statement Model'!F54/'3 Statement Model'!F$64 -> 0.068250938 | G40: ='3 Statement Model'!G54/'3 Statement Model'!G$64 -> 0.06406675 | H40: ='3 Statement Model'!H54/'3 Statement Model'!H$64 -> 0.073604972 | I40: ='3 Statement Model'!I54/'3 Statement Model'!I$64 -> 0.077848078 | J40: ='3 Statement Model'!J54/'3 Statement Model'!J$64 -> 0.081847012 | K40: ='3 Statement Model'!K54/'3 Statement Model'!K$64 -> 0.087256091 | ... V40: ='3 Statement Model'!V54/'3 Statement Model'!V$64 -> 0.11363118
B41: Other Current Assets | D41: ='3 Statement Model'!D55/'3 Statement Model'!D$64 -> 0.0055901547 | E41: ='3 Statement Model'!E55/'3 Statement Model'!E$64 -> 0.0057438092 | F41: ='3 Statement Model'!F55/'3 Statement Model'!F$64 -> 0.010689906 | G41: ='3 Statement Model'!G55/'3 Statement Model'!G$64 -> 0.01861157 | H41: ='3 Statement Model'!H55/'3 Statement Model'!H$64 -> 0.041754958 | I41: ='3 Statement Model'!I55/'3 Statement Model'!I$64 -> 0.040592212 | J41: ='3 Statement Model'!J55/'3 Statement Model'!J$64 -> 0.042677371 | K41: ='3 Statement Model'!K55/'3 Statement Model'!K$64 -> 0.045497819 | ... V41: ='3 Statement Model'!V55/'3 Statement Model'!V$64 -> 0.059250546
B42: Total Current Assets | D42: ='3 Statement Model'!D56/'3 Statement Model'!D$64 -> 0.12545135 | E42: ='3 Statement Model'!E56/'3 Statement Model'!E$64 -> 0.2105558 | F42: ='3 Statement Model'!F56/'3 Statement Model'!F$64 -> 0.17235459 | G42: ='3 Statement Model'!G56/'3 Statement Model'!G$64 -> 0.17922977 | H42: ='3 Statement Model'!H56/'3 Statement Model'!H$64 -> 0.24542531 | I42: ='3 Statement Model'!I56/'3 Statement Model'!I$64 -> 0.26897594 | J42: ='3 Statement Model'!J56/'3 Statement Model'!J$64 -> 0.27714529 | K42: ='3 Statement Model'!K56/'3 Statement Model'!K$64 -> 0.28483702 | ... V42: ='3 Statement Model'!V56/'3 Statement Model'!V$64 -> 0.41472953
B44: Property, Plant and Equipment | D44: ='3 Statement Model'!D58/'3 Statement Model'!D$64 -> 0.73890113 | E44: ='3 Statement Model'!E58/'3 Statement Model'!E$64 -> 0.48935371 | F44: ='3 Statement Model'!F58/'3 Statement Model'!F$64 -> 0.73137459 | G44: ='3 Statement Model'!G58/'3 Statement Model'!G$64 -> 0.6244468 | H44: ='3 Statement Model'!H58/'3 Statement Model'!H$64 -> 0.70412991 | I44: ='3 Statement Model'!I58/'3 Statement Model'!I$64 -> 0.68820875 | J44: ='3 Statement Model'!J58/'3 Statement Model'!J$64 -> 0.686667 | K44: ='3 Statement Model'!K58/'3 Statement Model'!K$64 -> 0.68490473 | ... V44: ='3 Statement Model'!V58/'3 Statement Model'!V$64 -> 0.57767901
B45: Other Intangible Assets | D45: ='3 Statement Model'!D59/'3 Statement Model'!D$64 -> 0.021635969 | E45: ='3 Statement Model'!E59/'3 Statement Model'!E$64 -> 0.013464995 | F45: ='3 Statement Model'!F59/'3 Statement Model'!F$64 -> 0.010340428 | G45: ='3 Statement Model'!G59/'3 Statement Model'!G$64 -> 0.0079886584 | H45: ='3 Statement Model'!H59/'3 Statement Model'!H$64 -> 0.0060279934 | I45: ='3 Statement Model'!I59/'3 Statement Model'!I$64 -> 0.0043913144 | J45: ='3 Statement Model'!J59/'3 Statement Model'!J$64 -> 0.0030747726 | K45: ='3 Statement Model'!K59/'3 Statement Model'!K$64 -> 0.0020172167 | ... V45: ='3 Statement Model'!V59/'3 Statement Model'!V$64 -> 0
B46: Capital Work in Progress | D46: ='3 Statement Model'!D60/'3 Statement Model'!D$64 -> 0.086957962 | E46: ='3 Statement Model'!E60/'3 Statement Model'!E$64 -> 0.27730357 | F46: ='3 Statement Model'!F60/'3 Statement Model'!F$64 -> 0.064961736 | G46: ='3 Statement Model'!G60/'3 Statement Model'!G$64 -> 0.17287285 | H46: ='3 Statement Model'!H60/'3 Statement Model'!H$64 -> 0.02030482 | I46: ='3 Statement Model'!I60/'3 Statement Model'!I$64 -> 0.017565257 | J46: ='3 Statement Model'!J60/'3 Statement Model'!J$64 -> 0.015137342 | K46: ='3 Statement Model'!K60/'3 Statement Model'!K$64 -> 0.012910187 | ... V46: ='3 Statement Model'!V60/'3 Statement Model'!V$64 -> 0.0034703806
B47: Other Non-Current Assets | D47: ='3 Statement Model'!D61/'3 Statement Model'!D$64 -> 0.027053588 | E47: ='3 Statement Model'!E61/'3 Statement Model'!E$64 -> 0.0093219198 | F47: ='3 Statement Model'!F61/'3 Statement Model'!F$64 -> 0.020968662 | G47: ='3 Statement Model'!G61/'3 Statement Model'!G$64 -> 0.015461919 | H47: ='3 Statement Model'!H61/'3 Statement Model'!H$64 -> 0.024111973 | I47: ='3 Statement Model'!I61/'3 Statement Model'!I$64 -> 0.020858743 | J47: ='3 Statement Model'!J61/'3 Statement Model'!J$64 -> 0.017975594 | K47: ='3 Statement Model'!K61/'3 Statement Model'!K$64 -> 0.015330847 | ... V47: ='3 Statement Model'!V61/'3 Statement Model'!V$64 -> 0.004121077
B48: Total Non-Current Assets | D48: ='3 Statement Model'!D62/'3 Statement Model'!D$64 -> 0.87454865 | E48: ='3 Statement Model'!E62/'3 Statement Model'!E$64 -> 0.7894442 | F48: ='3 Statement Model'!F62/'3 Statement Model'!F$64 -> 0.82764541 | G48: ='3 Statement Model'!G62/'3 Statement Model'!G$64 -> 0.82077023 | H48: ='3 Statement Model'!H62/'3 Statement Model'!H$64 -> 0.75457469 | I48: ='3 Statement Model'!I62/'3 Statement Model'!I$64 -> 0.73102406 | J48: ='3 Statement Model'!J62/'3 Statement Model'!J$64 -> 0.72285471 | K48: ='3 Statement Model'!K62/'3 Statement Model'!K$64 -> 0.71516298 | ... V48: ='3 Statement Model'!V62/'3 Statement Model'!V$64 -> 0.58527047
B50: Total Assets | D50: ='3 Statement Model'!D64/'3 Statement Model'!D$64 -> 1 | E50: ='3 Statement Model'!E64/'3 Statement Model'!E$64 -> 1 | F50: ='3 Statement Model'!F64/'3 Statement Model'!F$64 -> 1 | G50: ='3 Statement Model'!G64/'3 Statement Model'!G$64 -> 1 | H50: ='3 Statement Model'!H64/'3 Statement Model'!H$64 -> 1 | I50: ='3 Statement Model'!I64/'3 Statement Model'!I$64 -> 1 | J50: ='3 Statement Model'!J64/'3 Statement Model'!J$64 -> 1 | K50: ='3 Statement Model'!K64/'3 Statement Model'!K$64 -> 1 | ... V50: ='3 Statement Model'!V64/'3 Statement Model'!V$64 -> 1
B52: Equity & Liablities
B54: Liabilities and Shareholders' Equity
B55: Creditors | D55: ='3 Statement Model'!D69/'3 Statement Model'!D$83 -> 0.050379572 | E55: ='3 Statement Model'!E69/'3 Statement Model'!E$83 -> 0.041431262 | F55: ='3 Statement Model'!F69/'3 Statement Model'!F$83 -> 0.045230263 | G55: ='3 Statement Model'!G69/'3 Statement Model'!G$83 -> 0.065855404 | H55: ='3 Statement Model'!H69/'3 Statement Model'!H$83 -> 0.059010152 | I55: ='3 Statement Model'!I69/'3 Statement Model'!I$83 -> 0.061161832 | J55: ='3 Statement Model'!J69/'3 Statement Model'!J$83 -> 0.063605181 | K55: ='3 Statement Model'!K69/'3 Statement Model'!K$83 -> 0.067811145 | ... V55: ='3 Statement Model'!V69/'3 Statement Model'!V$83 -> 0.077914179
B56: Other Payables | D56: ='3 Statement Model'!D70/'3 Statement Model'!D$83 -> 0.0033816425 | E56: ='3 Statement Model'!E70/'3 Statement Model'!E$83 -> 0.013370998 | F56: ='3 Statement Model'!F70/'3 Statement Model'!F$83 -> 0.0089638158 | G56: ='3 Statement Model'!G70/'3 Statement Model'!G$83 -> 0.010021475 | H56: ='3 Statement Model'!H70/'3 Statement Model'!H$83 -> 0.0038388325 | I56: ='3 Statement Model'!I70/'3 Statement Model'!I$83 -> 0.0033206863 | J56: ='3 Statement Model'!J70/'3 Statement Model'!J$83 -> 0.0028618299 | K56: ='3 Statement Model'!K70/'3 Statement Model'!K$83 -> 0.0024408573 | ... V56: ='3 Statement Model'!V70/'3 Statement Model'!V$83 -> 0.00065608223
B57: Other Current Liabilities | D57: ='3 Statement Model'!D71/'3 Statement Model'!D$83 -> 0.163147 | E57: ='3 Statement Model'!E71/'3 Statement Model'!E$83 -> 0.15823917 | F57: ='3 Statement Model'!F71/'3 Statement Model'!F$83 -> 0.17360197 | G57: ='3 Statement Model'!G71/'3 Statement Model'!G$83 -> 0.12347888 | H57: ='3 Statement Model'!H71/'3 Statement Model'!H$83 -> 0.077506345 | I57: ='3 Statement Model'!I71/'3 Statement Model'!I$83 -> 0.067044931 | J57: ='3 Statement Model'!J71/'3 Statement Model'!J$83 -> 0.057780583 | K57: ='3 Statement Model'!K71/'3 Statement Model'!K$83 -> 0.049281111 | ... V57: ='3 Statement Model'!V71/'3 Statement Model'!V$83 -> 0.013246354
B58: Short Term Borrowing | D58: ='3 Statement Model'!D72/'3 Statement Model'!D$83 -> 0.051759834 | E58: ='3 Statement Model'!E72/'3 Statement Model'!E$83 -> 0.037664783 | F58: ='3 Statement Model'!F72/'3 Statement Model'!F$83 -> 0.037828947 | G58: ='3 Statement Model'!G72/'3 Statement Model'!G$83 -> 0.079098067 | H58: ='3 Statement Model'!H72/'3 Statement Model'!H$83 -> 0.015862944 | I58: ='3 Statement Model'!I72/'3 Statement Model'!I$83 -> 0.024353529 | J58: ='3 Statement Model'!J72/'3 Statement Model'!J$83 -> 0.025605762 | K58: ='3 Statement Model'!K72/'3 Statement Model'!K$83 -> 0.027298972 | ... V58: ='3 Statement Model'!V72/'3 Statement Model'!V$83 -> 0.0054826391
B59: Total Current Liabilities | D59: ='3 Statement Model'!D73/'3 Statement Model'!D$83 -> 0.26866805 | E59: ='3 Statement Model'!E73/'3 Statement Model'!E$83 -> 0.25070621 | F59: ='3 Statement Model'!F73/'3 Statement Model'!F$83 -> 0.265625 | G59: ='3 Statement Model'!G73/'3 Statement Model'!G$83 -> 0.27845383 | H59: ='3 Statement Model'!H73/'3 Statement Model'!H$83 -> 0.15621827 | I59: ='3 Statement Model'!I73/'3 Statement Model'!I$83 -> 0.15588098 | J59: ='3 Statement Model'!J73/'3 Statement Model'!J$83 -> 0.14985336 | K59: ='3 Statement Model'!K73/'3 Statement Model'!K$83 -> 0.14683209 | ... V59: ='3 Statement Model'!V73/'3 Statement Model'!V$83 -> 0.097299254
B61: Long Term Borrowing | D61: ='3 Statement Model'!D75/'3 Statement Model'!D$83 -> 0.23464458 | E61: ='3 Statement Model'!E75/'3 Statement Model'!E$83 -> 0.36158192 | F61: ='3 Statement Model'!F75/'3 Statement Model'!F$83 -> 0.22409539 | G61: ='3 Statement Model'!G75/'3 Statement Model'!G$83 -> 0.19577666 | H61: ='3 Statement Model'!H75/'3 Statement Model'!H$83 -> 0.14244924 | I61: ='3 Statement Model'!I75/'3 Statement Model'!I$83 -> 0.12691883 | J61: ='3 Statement Model'!J75/'3 Statement Model'!J$83 -> 0.11375627 | K61: ='3 Statement Model'!K75/'3 Statement Model'!K$83 -> 0.10090374 | ... V61: ='3 Statement Model'!V75/'3 Statement Model'!V$83 -> 0.030523389
B62: Other Non-Current Liabilities | D62: ='3 Statement Model'!D76/'3 Statement Model'!D$83 -> 0.024637681 | E62: ='3 Statement Model'!E76/'3 Statement Model'!E$83 -> 0.045903955 | F62: ='3 Statement Model'!F76/'3 Statement Model'!F$83 -> 0.0703125 | G62: ='3 Statement Model'!G76/'3 Statement Model'!G$83 -> 0.076592699 | H62: ='3 Statement Model'!H76/'3 Statement Model'!H$83 -> 0.097271574 | I62: ='3 Statement Model'!I76/'3 Statement Model'!I$83 -> 0.084142349 | J62: ='3 Statement Model'!J76/'3 Statement Model'!J$83 -> 0.07251546 | K62: ='3 Statement Model'!K76/'3 Statement Model'!K$83 -> 0.061848501 | ... V62: ='3 Statement Model'!V76/'3 Statement Model'!V$83 -> 0.016624365
B63: Total Non-Current Liabilities | D63: ='3 Statement Model'!D77/'3 Statement Model'!D$83 -> 0.25928226 | E63: ='3 Statement Model'!E77/'3 Statement Model'!E$83 -> 0.40748588 | F63: ='3 Statement Model'!F77/'3 Statement Model'!F$83 -> 0.29440789 | G63: ='3 Statement Model'!G77/'3 Statement Model'!G$83 -> 0.27236936 | H63: ='3 Statement Model'!H77/'3 Statement Model'!H$83 -> 0.23972081 | I63: ='3 Statement Model'!I77/'3 Statement Model'!I$83 -> 0.21106118 | J63: ='3 Statement Model'!J77/'3 Statement Model'!J$83 -> 0.18627173 | K63: ='3 Statement Model'!K77/'3 Statement Model'!K$83 -> 0.16275224 | ... V63: ='3 Statement Model'!V77/'3 Statement Model'!V$83 -> 0.047147753
B65: Equity Shares | D65: ='3 Statement Model'!D79/'3 Statement Model'!D$83 -> 0.17391304 | E65: ='3 Statement Model'!E79/'3 Statement Model'!E$83 -> 0.019774011 | F65: ='3 Statement Model'!F79/'3 Statement Model'!F$83 -> 0.017269737 | G65: ='3 Statement Model'!G79/'3 Statement Model'!G$83 -> 0.015032212 | H65: ='3 Statement Model'!H79/'3 Statement Model'!H$83 -> 0.013642132 | I65: ='3 Statement Model'!I79/'3 Statement Model'!I$83 -> 0.011800786 | J65: ='3 Statement Model'!J79/'3 Statement Model'!J$83 -> 0.010170139 | K65: ='3 Statement Model'!K79/'3 Statement Model'!K$83 -> 0.0086741211 | ... V65: ='3 Statement Model'!V79/'3 Statement Model'!V$83 -> 0.0023315319
B66: Retained Earnings | D66: ='3 Statement Model'!D80/'3 Statement Model'!D$83 -> 0.29813665 | E66: ='3 Statement Model'!E80/'3 Statement Model'!E$83 -> 0.3220339 | F66: ='3 Statement Model'!F80/'3 Statement Model'!F$83 -> 0.42269737 | G66: ='3 Statement Model'!G80/'3 Statement Model'!G$83 -> 0.4341446 | H66: ='3 Statement Model'!H80/'3 Statement Model'!H$83 -> 0.59041878 | I66: ='3 Statement Model'!I80/'3 Statement Model'!I$83 -> 0.62125706 | J66: ='3 Statement Model'!J80/'3 Statement Model'!J$83 -> 0.65370477 | K66: ='3 Statement Model'!K80/'3 Statement Model'!K$83 -> 0.68174155 | ... V66: ='3 Statement Model'!V80/'3 Statement Model'!V$83 -> 0.85322146
B67: Total Shareholders' Equity | D67: ='3 Statement Model'!D81/'3 Statement Model'!D$83 -> 0.47204969 | E67: ='3 Statement Model'!E81/'3 Statement Model'!E$83 -> 0.34180791 | F67: ='3 Statement Model'!F81/'3 Statement Model'!F$83 -> 0.43996711 | G67: ='3 Statement Model'!G81/'3 Statement Model'!G$83 -> 0.44917681 | H67: ='3 Statement Model'!H81/'3 Statement Model'!H$83 -> 0.60406091 | I67: ='3 Statement Model'!I81/'3 Statement Model'!I$83 -> 0.63305784 | J67: ='3 Statement Model'!J81/'3 Statement Model'!J$83 -> 0.66387491 | K67: ='3 Statement Model'!K81/'3 Statement Model'!K$83 -> 0.69041567 | ... V67: ='3 Statement Model'!V81/'3 Statement Model'!V$83 -> 0.85555299
B69: Total Liabilities and Shareholders' Equity | D69: ='3 Statement Model'!D83/'3 Statement Model'!D$83 -> 1 | E69: ='3 Statement Model'!E83/'3 Statement Model'!E$83 -> 1 | F69: ='3 Statement Model'!F83/'3 Statement Model'!F$83 -> 1 | G69: ='3 Statement Model'!G83/'3 Statement Model'!G$83 -> 1 | H69: ='3 Statement Model'!H83/'3 Statement Model'!H$83 -> 1 | I69: ='3 Statement Model'!I83/'3 Statement Model'!I$83 -> 1 | J69: ='3 Statement Model'!J83/'3 Statement Model'!J$83 -> 1 | K69: ='3 Statement Model'!K83/'3 Statement Model'!K$83 -> 1 | ... V69: ='3 Statement Model'!V83/'3 Statement Model'!V$83 -> 1

Sheet Ratio Analysis
B2: ='Input Sheet'!C5 -> Epigral Ltd.
B3: Ratio Analysis | F3: Current Case | G3: 2
D7: Actual | I7: Explicit Forecast Period | Q7: =Schedules!Q7 -> Terminal Value
B8: In INR Crores Other wise Stated | D8: =Schedules!D8 -> 2021 | E8: =Schedules!E8 -> 2022 | F8: =Schedules!F8 -> 2023 | G8: =Schedules!G8 -> 2024 | H8: =Schedules!H8 -> 2025 | I8: =Schedules!I8 -> 2026 | J8: =Schedules!J8 -> 2027 | K8: =Schedules!K8 -> 2028 | ... V8: =Schedules!V8 -> 2039
A10: # | B10: Liquidity Ratios | D10: 2021 | E10: 2022 | F10: 2023 | G10: 2024 | H10: 2025 | I10: 2026 | J10: 2027 | K10: 2028 | L10: 2029 | M10: 2030 | N10: 2031 | O10: 2032 | P10: 2033 | Q10: 2034 | R10: 2035 | S10: 2036 | T10: 2037 | U10: 2038 | V10: 2039
B12: Current Assets | D12: ='3 Statement Model'!D56 -> 181.776 | E12: ='3 Statement Model'!E56 -> 447.226 | F12: ='3 Statement Model'!F56 -> 419.201 | G12: ='3 Statement Model'!G56 -> 500.761 | H12: ='3 Statement Model'!H56 -> 773.571 | I12: ='3 Statement Model'!I56 -> 980.0289 | J12: ='3 Statement Model'!J56 -> 1171.7578 | K12: ='3 Statement Model'!K56 -> 1412.0298 | ... V12: ='3 Statement Model'!V56 -> 7648.3512
B13: Current Liabilities | D13: ='3 Statement Model'!D73 -> 389.3 | E13: ='3 Statement Model'!E73 -> 532.5 | F13: ='3 Statement Model'!F73 -> 646 | G13: ='3 Statement Model'!G73 -> 778 | H13: ='3 Statement Model'!H73 -> 492.4 | I13: ='3 Statement Model'!I73 -> 568.00301 | J13: ='3 Statement Model'!J73 -> 633.58957 | K13: ='3 Statement Model'!K73 -> 727.88697 | ... V13: ='3 Statement Model'!V73 -> 1794.4717
B14: Current Ratio | D14: =D12/D13 -> 0.46693039 | E14: =E12/E13 -> 0.83986103 | F14: =F12/F13 -> 0.64891796 | G14: =G12/G13 -> 0.64365167 | H14: =H12/H13 -> 1.5710215 | I14: =I12/I13 -> 1.7253938 | J14: =J12/J13 -> 1.8493957 | K14: =K12/K13 -> 1.9399026 | ... V14: =V12/V13 -> 4.2621744
B16: Current Assets | D16: =D12 -> 181.776 | E16: =E12 -> 447.226 | F16: =F12 -> 419.201 | G16: =G12 -> 500.761 | H16: =H12 -> 773.571 | I16: =I12 -> 980.0289 | J16: =J12 -> 1171.7578 | K16: =K12 -> 1412.0298 | ... V16: =V12 -> 7648.3512
B17: Inventory | D17: ='3 Statement Model'!D53 -> 54 | E17: ='3 Statement Model'!E53 -> 154 | F17: ='3 Statement Model'!F53 -> 212 | G17: ='3 Statement Model'!G53 -> 263 | H17: ='3 Statement Model'!H53 -> 388 | I17: ='3 Statement Model'!I53 -> 397.10137 | J17: ='3 Statement Model'!J53 -> 484.46367 | K17: ='3 Statement Model'!K53 -> 630.29712 | ... V17: ='3 Statement Model'!V53 -> 2933.786
B18: Current Liabilities | D18: =D13 -> 389.3 | E18: =E13 -> 532.5 | F18: =F13 -> 646 | G18: =G13 -> 778 | H18: =H13 -> 492.4 | I18: =I13 -> 568.00301 | J18: =J13 -> 633.58957 | K18: =K13 -> 727.88697 | ... V18: =V13 -> 1794.4717
B19: Quick Ratio / Acid Test Ratio | D19: =(D16-D17)/D18 -> 0.32821988 | E19: =(E16-E17)/E18 -> 0.55065915 | F19: =(F16-F17)/F18 -> 0.32074458 | G19: =(G16-G17)/G18 -> 0.3056054 | H19: =(H16-H17)/H18 -> 0.78304427 | I19: =(I16-I17)/I18 -> 1.0262754 | J19: =(J16-J17)/J18 -> 1.0847624 | K19: =(K16-K17)/K18 -> 1.0739754 | ... V19: =(V16-V17)/V18 -> 2.627272
B21: Inventory Days | D21: ='3 Statement Model'!D89 -> 51.194805 | E21: ='3 Statement Model'!E89 -> 73.863338 | F21: ='3 Statement Model'!F89 -> 69.399103 | G21: ='3 Statement Model'!G89 -> 90.475966 | H21: ='3 Statement Model'!H89 -> 104.6711 | I21: ='3 Statement Model'!I89 -> 89.090909 | J21: ='3 Statement Model'!J89 -> 90.073529 | K21: ='3 Statement Model'!K89 -> 93.75 | ... V21: ='3 Statement Model'!V89 -> 102.08333
B22: Debtors Days | D22: ='3 Statement Model'!D88 -> 52.394451 | E22: ='3 Statement Model'!E88 -> 60.245003 | F22: ='3 Statement Model'!F88 -> 27.691956 | G22: ='3 Statement Model'!G88 -> 33.869881 | H22: ='3 Statement Model'!H88 -> 33.207843 | I22: ='3 Statement Model'!I88 -> 35 | J22: ='3 Statement Model'!J88 -> 35 | K22: ='3 Statement Model'!K88 -> 35 | ... V22: ='3 Statement Model'!V88 -> 35
B23: Creditors Days | D23: ='3 Statement Model'!D90 -> 69.207792 | E23: ='3 Statement Model'!E90 -> 42.207622 | F23: ='3 Statement Model'!F90 -> 36.008969 | G23: ='3 Statement Model'!G90 -> 63.298775 | H23: ='3 Statement Model'!H90 -> 50.177384 | I23: ='3 Statement Model'!I90 -> 50 | J23: ='3 Statement Model'!J90 -> 50 | K23: ='3 Statement Model'!K90 -> 50 | ... V23: ='3 Statement Model'!V90 -> 50
B24: Cash Conversion Days | D24: =D21+D22-D23 -> 34.381464 | E24: =E21+E22-E23 -> 91.900719 | F24: =F21+F22-F23 -> 61.082091 | G24: =G21+G22-G23 -> 61.047072 | H24: =H21+H22-H23 -> 87.701561 | I24: =I21+I22-I23 -> 74.090909 | J24: =J21+J22-J23 -> 75.073529 | K24: =K21+K22-K23 -> 78.75 | ... V24: =V21+V22-V23 -> 87.083333
A26: # | B26: Leverage Ratio / Solvency Ratio
B28: Total Debt | D28: =SUM('3 Statement Model'!D75,'3 Statement Model'!D72) -> 415 | E28: =SUM('3 Statement Model'!E75,'3 Statement Model'!E72) -> 848 | F28: =SUM('3 Statement Model'!F75,'3 Statement Model'!F72) -> 637 | G28: =SUM('3 Statement Model'!G75,'3 Statement Model'!G72) -> 768 | H28: =SUM('3 Statement Model'!H75,'3 Statement Model'!H72) -> 499 | I28: =SUM('3 Statement Model'!I75,'3 Statement Model'!I72) -> 551.21 | J28: =SUM('3 Statement Model'!J75,'3 Statement Model'!J72) -> 589.2316 | K28: =SUM('3 Statement Model'!K75,'3 Statement Model'!K72) -> 635.53605 | ... V28: =SUM('3 Statement Model'!V75,'3 Statement Model'!V72) -> 664.05233
B29: Total Equity | D29: ='3 Statement Model'!D81 -> 684 | E29: ='3 Statement Model'!E81 -> 726 | F29: ='3 Statement Model'!F81 -> 1070 | G29: ='3 Statement Model'!G81 -> 1255 | H29: ='3 Statement Model'!H81 -> 1904 | I29: ='3 Statement Model'!I81 -> 2306.752 | J29: ='3 Statement Model'!J81 -> 2806.9056 | K29: ='3 Statement Model'!K81 -> 3422.58 | ... V29: ='3 Statement Model'!V81 -> 15778.801
B30: Debt to Equity Ratio | D30: =D28/D29 -> 0.60672515 | E30: =E28/E29 -> 1.1680441 | F30: =F28/F29 -> 0.5953271 | G30: =G28/G29 -> 0.61195219 | H30: =H28/H29 -> 0.26207983 | I30: =I28/I29 -> 0.23895503 | J30: =J28/J29 -> 0.20992213 | K30: =K28/K29 -> 0.18568917 | ... V30: =V28/V29 -> 0.042085094
B32: Total Debt | D32: =D28 -> 415 | E32: =E28 -> 848 | F32: =F28 -> 637 | G32: =G28 -> 768 | H32: =H28 -> 499 | I32: =I28 -> 551.21 | J32: =J28 -> 589.2316 | K32: =K28 -> 635.53605 | ... V32: =V28 -> 664.05233
B33: Total Assets | D33: ='3 Statement Model'!D64 -> 1448.976 | E33: ='3 Statement Model'!E64 -> 2124.026 | F33: ='3 Statement Model'!F64 -> 2432.201 | G33: ='3 Statement Model'!G64 -> 2793.961 | H33: ='3 Statement Model'!H64 -> 3151.961 | I33: ='3 Statement Model'!I64 -> 3643.556 | J33: ='3 Statement Model'!J64 -> 4227.9549 | K33: ='3 Statement Model'!K64 -> 4957.3256 | ... V33: ='3 Statement Model'!V64 -> 18441.781
B34: Debt to Assets Ratio | D34: =D32/D33 -> 0.28640916 | E34: =E32/E33 -> 0.39924182 | F34: =F32/F33 -> 0.2619027 | G34: =G32/G33 -> 0.27487857 | H34: =H32/H33 -> 0.15831414 | I34: =I32/I33 -> 0.15128352 | J34: =J32/J33 -> 0.13936563 | K34: =K32/K33 -> 0.1282014 | ... V34: =V32/V33 -> 0.036008037
B36: Total Equity | D36: =D29 -> 684 | E36: =E29 -> 726 | F36: =F29 -> 1070 | G36: =G29 -> 1255 | H36: =H29 -> 1904 | I36: =I29 -> 2306.752 | J36: =J29 -> 2806.9056 | K36: =K29 -> 3422.58 | ... V36: =V29 -> 15778.801
B37: Total Assets | D37: =D33 -> 1448.976 | E37: =E33 -> 2124.026 | F37: =F33 -> 2432.201 | G37: =G33 -> 2793.961 | H37: =H33 -> 3151.961 | I37: =I33 -> 3643.556 | J37: =J33 -> 4227.9549 | K37: =K33 -> 4957.3256 | ... V37: =V33 -> 18441.781
B38: Equity Ratio | D38: =D36/D37 -> 0.47205751 | E38: =E36/E37 -> 0.34180373 | F38: =F36/F37 -> 0.43993075 | G38: =G36/G37 -> 0.44918308 | H38: =H36/H37 -> 0.60406839 | I38: =I36/I37 -> 0.63310458 | J38: =J36/J37 -> 0.66389203 | K38: =K36/K37 -> 0.69040857 | ... V38: =V36/V37 -> 0.85560073
A40: # | B40: Profitability / Margin Ratio
B42: Gross Profit | D42: ='3 Statement Model'!D14 -> 444 | E42: ='3 Statement Model'!E14 -> 790 | F42: ='3 Statement Model'!F14 -> 1073 | G42: ='3 Statement Model'!G14 -> 868 | H42: ='3 Statement Model'!H14 -> 1197 | I42: ='3 Statement Model'!I14 -> 1331.1 | J42: ='3 Statement Model'!J14 -> 1645.5946 | K42: ='3 Statement Model'!K14 -> 2056.9932 | ... V42: ='3 Statement Model'!V14 -> 11363.93
B43: Total Sales | D43: ='3 Statement Model'!D12 -> 829 | E43: ='3 Statement Model'!E12 -> 1551 | F43: ='3 Statement Model'!F12 -> 2188 | G43: ='3 Statement Model'!G12 -> 1929 | H43: ='3 Statement Model'!H12 -> 2550 | I43: ='3 Statement Model'!I12 -> 2958 | J43: ='3 Statement Model'!J12 -> 3608.76 | K43: ='3 Statement Model'!K12 -> 4510.95 | ... V43: ='3 Statement Model'!V12 -> 21853.712
B44: Gross Margin | D44: =D42/D43 -> 0.53558504 | E44: =E42/E43 -> 0.50934881 | F44: =F42/F43 -> 0.49040219 | G44: =G42/G43 -> 0.44997408 | H44: =H42/H43 -> 0.46941176 | I44: =I42/I43 -> 0.45 | J44: =J42/J43 -> 0.456 | K44: =K42/K43 -> 0.456 | ... V44: =V42/V43 -> 0.52
B46: EBITDA | D46: ='3 Statement Model'!D24 -> 261.8 | E46: ='3 Statement Model'!E24 -> 510.2 | F46: ='3 Statement Model'!F24 -> 689.4 | G46: ='3 Statement Model'!G24 -> 480.7 | H46: ='3 Statement Model'!H24 -> 711.4 | I46: ='3 Statement Model'!I24 -> 769.08 | J46: ='3 Statement Model'!J24 -> 959.93016 | K46: ='3 Statement Model'!K24 -> 1199.9127 | ... V46: ='3 Statement Model'!V24 -> 7211.725
B47: Total Sales | D47: =D43 -> 829 | E47: =E43 -> 1551 | F47: =F43 -> 2188 | G47: =G43 -> 1929 | H47: =H43 -> 2550 | I47: =I43 -> 2958 | J47: =J43 -> 3608.76 | K47: =K43 -> 4510.95 | ... V47: =V43 -> 21853.712
B48: EBITDA Margin | D48: =D46/D47 -> 0.31580217 | E48: =E46/E47 -> 0.32894907 | F48: =F46/F47 -> 0.31508227 | G48: =G46/G47 -> 0.24919647 | H48: =H46/H47 -> 0.27898039 | I48: =I46/I47 -> 0.26 | J48: =J46/J47 -> 0.266 | K48: =K46/K47 -> 0.266 | ... V48: =V46/V47 -> 0.33
B50: EBIT | D50: ='3 Statement Model'!D31 -> 187.8 | E50: ='3 Statement Model'!E31 -> 424.3 | F50: ='3 Statement Model'!F31 -> 580.45 | G50: ='3 Statement Model'!G31 -> 357.14 | H50: ='3 Statement Model'!H31 -> 578.84 | I50: ='3 Statement Model'!I31 -> 604.37714 | J50: ='3 Statement Model'!J31 -> 752.37016 | K50: ='3 Statement Model'!K31 -> 938.78127 | ... V50: ='3 Statement Model'!V31 -> 5786.1491
B51: Total Sales | D51: =D47 -> 829 | E51: =E47 -> 1551 | F51: =F47 -> 2188 | G51: =G47 -> 1929 | H51: =H47 -> 2550 | I51: =I47 -> 2958 | J51: =J47 -> 3608.76 | K51: =K47 -> 4510.95 | ... V51: =V47 -> 21853.712
B52: EBIT Margin | D52: =D50/D51 -> 0.226538 | E52: =E50/E51 -> 0.27356544 | F52: =F50/F51 -> 0.26528793 | G52: =G50/G51 -> 0.18514256 | H52: =H50/H51 -> 0.22699608 | I52: =I50/I51 -> 0.20431952 | J52: =J50/J51 -> 0.2084844 | K52: =K50/K51 -> 0.20811166 | ... V52: =V50/V51 -> 0.26476734
B54: Net Profit | D54: ='3 Statement Model'!D39 -> 101.3 | E54: ='3 Statement Model'!E39 -> 253.6 | F54: ='3 Statement Model'!F39 -> 353.75 | G54: ='3 Statement Model'!G39 -> 195.74 | H54: ='3 Statement Model'!H39 -> 357.84 | I54: ='3 Statement Model'!I39 -> 433.0667 | J54: ='3 Statement Model'!J39 -> 543.64516 | K54: ='3 Statement Model'!K39 -> 684.08274 | ... V54: ='3 Statement Model'!V39 -> 4373.279
B55: Total Sales | D55: =D51 -> 829 | E55: =E51 -> 1551 | F55: =F51 -> 2188 | G55: =G51 -> 1929 | H55: =H51 -> 2550 | I55: =I51 -> 2958 | J55: =J51 -> 3608.76 | K55: =K51 -> 4510.95 | ... V55: =V51 -> 21853.712
B56: Net Profit Margin | D56: =D54/D55 -> 0.12219542 | E56: =E54/E55 -> 0.16350741 | F56: =F54/F55 -> 0.16167733 | G56: =G54/G55 -> 0.10147227 | H56: =H54/H55 -> 0.14032941 | I56: =I54/I55 -> 0.14640524 | J56: =J54/J55 -> 0.15064597 | K56: =K54/K55 -> 0.15164937 | ... V56: =V54/V55 -> 0.20011607
B58: Net Income | D58: =D54 -> 101.3 | E58: =E54 -> 253.6 | F58: =F54 -> 353.75 | G58: =G54 -> 195.74 | H58: =H54 -> 357.84 | I58: =I54 -> 433.0667 | J58: =J54 -> 543.64516 | K58: =K54 -> 684.08274 | ... V58: =V54 -> 4373.279
B59: Total Assets | D59: =D37 -> 1448.976 | E59: =E37 -> 2124.026 | F59: =F37 -> 2432.201 | G59: =G37 -> 2793.961 | H59: =H37 -> 3151.961 | I59: =I37 -> 3643.556 | J59: =J37 -> 4227.9549 | K59: =K37 -> 4957.3256 | ... V59: =V37 -> 18441.781
B60: Retur on Assets | D60: =D58/D59 -> 0.069911441 | E60: =E58/E59 -> 0.1193959 | F60: =F58/F59 -> 0.14544439 | G60: =G58/G59 -> 0.070058243 | H60: =H58/H59 -> 0.11352932 | I60: =I58/I59 -> 0.11885825 | J60: =J58/J59 -> 0.12858348 | K60: =K58/K59 -> 0.13799431 | ... V60: =V58/V59 -> 0.23713973
B62: Net Income | D62: =D58 -> 101.3 | E62: =E58 -> 253.6 | F62: =F58 -> 353.75 | G62: =G58 -> 195.74 | H62: =H58 -> 357.84 | I62: =I58 -> 433.0667 | J62: =J58 -> 543.64516 | K62: =K58 -> 684.08274 | ... V62: =V58 -> 4373.279
B63: Total Equity | D63: =D36 -> 684 | E63: =E36 -> 726 | F63: =F36 -> 1070 | G63: =G36 -> 1255 | H63: =H36 -> 1904 | I63: =I36 -> 2306.752 | J63: =J36 -> 2806.9056 | K63: =K36 -> 3422.58 | ... V63: =V36 -> 15778.801
B64: Return on Equity | D64: =D62/D63 -> 0.14809942 | E64: =E62/E63 -> 0.34931129 | F64: =F62/F63 -> 0.33060748 | G64: =G62/G63 -> 0.15596813 | H64: =H62/H63 -> 0.18794118 | I64: =I62/I63 -> 0.18773873 | J64: =J62/J63 -> 0.19368131 | K64: =K62/K63 -> 0.19987341 | ... V64: =V62/V63 -> 0.27716167
A66: # | B66: Efficiency Ratio
B68: Sales | D68: =D47 -> 829 | E68: =E47 -> 1551 | F68: =F47 -> 2188 | G68: =G47 -> 1929 | H68: =H47 -> 2550 | I68: =I47 -> 2958 | J68: =J47 -> 3608.76 | K68: =K47 -> 4510.95 | ... V68: =V47 -> 21853.712
B69: Total Assets | D69: =D59 -> 1448.976 | E69: =E59 -> 2124.026 | F69: =F59 -> 2432.201 | G69: =G59 -> 2793.961 | H69: =H59 -> 3151.961 | I69: =I59 -> 3643.556 | J69: =J59 -> 4227.9549 | K69: =K59 -> 4957.3256 | ... V69: =V59 -> 18441.781
B70: Asset Turnover Ratio | D70: =D68/D69 -> 0.57212818 | E70: =E68/E69 -> 0.73021705 | F70: =F68/F69 -> 0.8995967 | G70: =G68/G69 -> 0.69041765 | H70: =H68/H69 -> 0.80902016 | I70: =I68/I69 -> 0.81184424 | J70: =J68/J69 -> 0.85354741 | K70: =K68/K69 -> 0.90995638 | ... V70: =V68/V69 -> 1.1850109
B72: Change in Revenue | D72: 0 | E72: =E68-D68 -> 722 | F72: =F68-E68 -> 637 | G72: =G68-F68 -> -259 | H72: =H68-G68 -> 621 | I72: =I68-H68 -> 408 | J72: =J68-I68 -> 650.76 | K72: =K68-J68 -> 902.19 | L72: =L68-K68 -> 1127.7375 | ... V72: =V68-U68 -> 1040.653
B73: Change in Total Assets | D73: 0 | E73: =E69-D69 -> 675.05 | F73: =F69-E69 -> 308.175 | G73: =G69-F69 -> 361.76 | H73: =H69-G69 -> 358 | I73: =I69-H69 -> 491.59504 | J73: =J69-I69 -> 584.3989 | K73: =K69-J69 -> 729.37061 | L73: =L69-K69 -> 910.52671 | ... V73: =V69-U69 -> 1161.6762
B74: Reinvestment Ratio | E74: =E72/E73 -> 1.0695504 | F74: =F72/F73 -> 2.0670074 | G74: =G72/G73 -> -0.71594427 | H74: =H72/H73 -> 1.7346369 | I74: =I72/I73 -> 0.82995142 | J74: =J72/J73 -> 1.1135545 | K74: =K72/K73 -> 1.2369432 | L74: =L72/L73 -> 1.2385551 | ... V74: =V72/V73 -> 0.89582013
B76: COGS | D76: ='3 Statement Model'!D13 -> 385 | E76: ='3 Statement Model'!E13 -> 761 | F76: ='3 Statement Model'!F13 -> 1115 | G76: ='3 Statement Model'!G13 -> 1061 | H76: ='3 Statement Model'!H13 -> 1353 | I76: ='3 Statement Model'!I13 -> 1626.9 | J76: ='3 Statement Model'!J13 -> 1963.1654 | K76: ='3 Statement Model'!K13 -> 2453.9568 | ... V76: ='3 Statement Model'!V13 -> 10489.782
B77: Inventory | D77: ='3 Statement Model'!D53 -> 54 | E77: ='3 Statement Model'!E53 -> 154 | F77: ='3 Statement Model'!F53 -> 212 | G77: ='3 Statement Model'!G53 -> 263 | H77: ='3 Statement Model'!H53 -> 388 | I77: ='3 Statement Model'!I53 -> 397.10137 | J77: ='3 Statement Model'!J53 -> 484.46367 | K77: ='3 Statement Model'!K53 -> 630.29712 | ... V77: ='3 Statement Model'!V53 -> 2933.786
B78: Inventory Turnover Ratio | D78: =D76/D77 -> 7.1296296 | E78: =E76/E77 -> 4.9415584 | F78: =F76/F77 -> 5.259434 | G78: =G76/G77 -> 4.0342205 | H78: =H76/H77 -> 3.4871134 | I78: =I76/I77 -> 4.0969388 | J78: =J76/J77 -> 4.0522449 | K78: =K76/K77 -> 3.8933333 | ... V78: =V76/V77 -> 3.5755102
A80: # | B80: Coverage Ratio
B82: Total Debt | D82: =D32 -> 415 | E82: =E32 -> 848 | F82: =F32 -> 637 | G82: =G32 -> 768 | H82: =H32 -> 499 | I82: =I32 -> 551.21 | J82: =J32 -> 589.2316 | K82: =K32 -> 635.53605 | ... V82: =V32 -> 664.05233
B83: EBITDA | D83: =D46 -> 261.8 | E83: =E46 -> 510.2 | F83: =F46 -> 689.4 | G83: =G46 -> 480.7 | H83: =H46 -> 711.4 | I83: =I46 -> 769.08 | J83: =J46 -> 959.93016 | K83: =K46 -> 1199.9127 | ... V83: =V46 -> 7211.725
B84: Debt to EBITDA Ratio | D84: =D82/D83 -> 1.5851795 | E84: =E82/E83 -> 1.6620933 | F84: =F82/F83 -> 0.92399188 | G84: =G82/G83 -> 1.5976701 | H84: =H82/H83 -> 0.70143379 | I84: =I82/I83 -> 0.71671348 | J84: =J82/J83 -> 0.61382757 | K84: =K82/K83 -> 0.52965191 | ... V84: =V82/V83 -> 0.092079542
B87: EBIT | D87: ='Ratio Analysis'!D50 -> 187.8 | E87: ='Ratio Analysis'!E50 -> 424.3 | F87: ='Ratio Analysis'!F50 -> 580.45 | G87: ='Ratio Analysis'!G50 -> 357.14 | H87: ='Ratio Analysis'!H50 -> 578.84 | I87: ='Ratio Analysis'!I50 -> 604.37714 | J87: ='Ratio Analysis'!J50 -> 752.37016 | K87: ='Ratio Analysis'!K50 -> 938.78127 | ... V87: ='Ratio Analysis'!V50 -> 5786.1491
B88: Dep | D88: ='3 Statement Model'!D29 -> 70.77 | E88: ='3 Statement Model'!E29 -> 82.67 | F88: ='3 Statement Model'!F29 -> 105.72 | G88: ='3 Statement Model'!G29 -> 120.33 | H88: ='3 Statement Model'!H29 -> 129.33 | I88: ='3 Statement Model'!I29 -> 161.47286 | J88: ='3 Statement Model'!J29 -> 204.33 | K88: ='3 Statement Model'!K29 -> 257.90143 | ... V88: ='3 Statement Model'!V29 -> 1425.5758
B89: Interest | D89: ='3 Statement Model'!D35 -> 34 | E89: ='3 Statement Model'!E35 -> 48 | F89: ='3 Statement Model'!F35 -> 67 | G89: ='3 Statement Model'!G35 -> 73 | H89: ='3 Statement Model'!H35 -> 53 | I89: ='3 Statement Model'!I35 -> 40.433085 | J89: ='3 Statement Model'!J35 -> 43.907002 | K89: ='3 Statement Model'!K35 -> 47.153555 | ... V89: ='3 Statement Model'!V35 -> 51.13203
B90: Debt Repayment | D90: =D91-C91 -> 415 | E90: =E91-D91 -> 433 | F90: =F91-E91 -> -211 | G90: =G91-F91 -> 131 | H90: =H91-G91 -> -269 | I90: =I91-H91 -> 52.21 | J90: =J91-I91 -> 38.0216 | K90: =K91-J91 -> 46.304452 | ... V90: =V91-U91 -> 0
B91: Total Debt | D91: =D32 -> 415 | E91: =E32 -> 848 | F91: =F32 -> 637 | G91: =G32 -> 768 | H91: =H32 -> 499 | I91: =I32 -> 551.21 | J91: =J32 -> 589.2316 | K91: =K32 -> 635.53605 | ... V91: =V32 -> 664.05233
B92: Debt Service Coverage Ratio | E92: {=SUM(E87:E88/SUM(IF(E90>0,E89+E90,E89)))} -> 1.0539917 | F92: {=SUM(F87:F88/SUM(IF(F90>0,F89+F90,F89)))} -> 10.241343 | G92: {=SUM(G87:G88/SUM(IF(G90>0,G89+G90,G89)))} -> 2.3405392 | H92: {=SUM(H87:H88/SUM(IF(H90>0,H89+H90,H89)))} -> 13.361698 | I92: {=SUM(I87:I88/SUM(IF(I90>0,I89+I90,I89)))} -> 8.266672 | J92: {=SUM(J87:J88/SUM(IF(J90>0,J89+J90,J89)))} -> 11.677243 | K92: {=SUM(K87:K88/SUM(IF(K90>0,K89+K90,K89)))} -> 12.804496 | L92: {=SUM(L87:L88/SUM(IF(L90>0,L89+L90,L89)))} -> 14.532503 | ... V92: {=SUM(V87:V88/SUM(IF(V90>0,V89+V90,V89)))} -> 141.04124
B95: EBIT | D95: =D50 -> 187.8 | E95: =E50 -> 424.3 | F95: =F50 -> 580.45 | G95: =G50 -> 357.14 | H95: =H50 -> 578.84 | I95: =I50 -> 604.37714 | J95: =J50 -> 752.37016 | K95: =K50 -> 938.78127 | ... V95: =V50 -> 5786.1491
B96: Interest Expense | D96: =D89 -> 34 | E96: =E89 -> 48 | F96: =F89 -> 67 | G96: =G89 -> 73 | H96: =H89 -> 53 | I96: =I89 -> 40.433085 | J96: =J89 -> 43.907002 | K96: =K89 -> 47.153555 | ... V96: =V89 -> 51.13203
B97: Interest Coverage Ratio | D97: =D95/D96 -> 5.5235294 | E97: =E95/E96 -> 8.8395833 | F97: =F95/F96 -> 8.6634328 | G97: =G95/G96 -> 4.8923288 | H97: =H95/H96 -> 10.921509 | I97: =I95/I96 -> 14.947589 | J97: =J95/J96 -> 17.135539 | K97: =K95/K96 -> 19.909024 | ... V97: =V95/V96 -> 113.16095

Sheet DCF>

Sheet Wacc
A1: # | B1: Epigral Ltd. | J1: Epigral Mark Cap | K1: 4442
B2: Weighted Average Cost of Capital
B4: Particulars | D4: Low | E4: Mid | F4: High | H4: Risk Free Rate
B6: Risk Free Rate | D6: ='Input Sheet'!C10-'Input Sheet'!C12 -> 0.045390142 | E6: =D6 -> 0.045390142 | F6: =E6 -> 0.045390142 | H6: ="We have considered "&TEXT(E6,"0.00%")&" as the risk free rate in estimation of cost of equity of "&TEXT(E11,"0.00%")&".The risk free rate of india is calculated by considering local currency 10 years government bond yield adjusted for default spread of India." -> We have considered 4.54% as the risk free rate in estimation of cost of equity of 12.58%.The risk free rate of india is calculated by considering local currency 10 years government bond yield adjusted for default spread of India.
B7: Equity Risk Premium | D7: ='Input Sheet'!C13+'Input Sheet'!C12 -> 0.063409858 | E7: =D7 -> 0.063409858 | F7: =E7 -> 0.063409858
B8: Asset Beta | D8: =E8-'Input Sheet'!C15 -> 0.87 | E8: ='Input Sheet'!C14 -> 1.02 | F8: =E8+'Input Sheet'!C15 -> 1.17
B9: D/E Ratio | D9: ='Input Sheet'!C16 -> 0.26207983 | E9: =D9 -> 0.26207983 | F9: =E9 -> 0.26207983
B10: Equity Beta | D10: =D8*(1+(1-Wacc!C17)*Wacc!D9) -> 1.0980095 | E10: =E8*(1+(1-Wacc!D17)*Wacc!E9) -> 1.2683416 | F10: =F8*(1+(1-Wacc!E17)*Wacc!F9) -> 1.4548624
B11: CAPM Cost of Equity | D11: =D6+D7*D10 -> 0.11501477 | E11: =E6+E7*E10 -> 0.1258155 | F11: =F6+F7*F10 -> 0.13764276 | H11: Asset Beta
B13: Small Size Premium | D13: ='Input Sheet'!C24 -> 0.1222 | E13: =D13 -> 0.1222 | F13: =E13 -> 0.1222 | H13: ="We have estimated an asset beta range of "&TEXT(D8,"0.00")&" to "&TEXT(F8,"0.00")&" with the mid point of "&TEXT(E8,"0.00")&" based on observed median of 5 year monthly asset beta of benchmark listed companies for Blume effect ." -> We have estimated an asset beta range of 0.87 to 1.17 with the mid point of 1.02 based on observed median of 5 year monthly asset beta of benchmark listed companies for Blume effect .
B14: Asset Specific Premium | D14: ='Input Sheet'!C25 -> 0 | E14: =D14 -> 0 | F14: =E14 -> 0
B15: Modified Cost of Equity | D15: =D11+D13+D14 -> 0.23721477 | E15: =E11+E13+E14 -> 0.2480155 | F15: =F11+F13+F14 -> 0.25984276
B17: Pre Tax Cost of Debt | D17: ='Input Sheet'!C10+(IF('Input Sheet'!C19="No",'Input Sheet'!C23,VLOOKUP('Input Sheet'!C21,'Damodaran Data'!I7:J21,2,FALSE))) -> 0.071 | E17: =D17 -> 0.071 | F17: =E17 -> 0.071 | H17: Equity Risk Premium
B18: Marginal Tax Rate | D18: ='Input Sheet'!C18 -> 0.2517 | E18: =D18 -> 0.2517 | F18: =E18 -> 0.2517
B19: Post Tax Cost of Debt | D19: =D17*(1-D18) -> 0.0531293 | E19: =E17*(1-E18) -> 0.0531293 | F19: =F17*(1-F18) -> 0.0531293 | H19: ="An ERP of "&TEXT(E7,"0.00%")&" has been adopted as on US implierd Erp, relative equity volatilly of ICE BoFA Public Sector Issues Emerging Mkts Index, S&P emerging BMI Index and country risk premium of India." -> An ERP of 6.34% has been adopted as on US implierd Erp, relative equity volatilly of ICE BoFA Public Sector Issues Emerging Mkts Index, S&P emerging BMI Index and country risk premium of India.
B21: Capital Gearing (D/D+E) | D21: ='Input Sheet'!C17 -> 0.2076571 | E21: =D21 -> 0.2076571 | F21: =E21 -> 0.2076571
B22: Weighted Average Cost of Capital | D22: =(D21*D19)+(D15*(1-D21)) -> 0.19898811 | E22: =(E21*E19)+(E15*(1-E21)) -> 0.207546 | F22: =(F21*F19)+(F15*(1-F21)) -> 0.21691725
B23: Weighted Average Cost of Capital (Rounded) | D23: =ROUNDUP(D22,2) -> 0.2 | E23: =ROUNDUP(E22,2) -> 0.21 | F23: =ROUNDUP(F22,2) -> 0.22 | H23: Cost of Debt
B25: 1. Tax Rate considered as Marginal Tax Rate of india | H25: For the purpose of assessing the cost of debt, we have used country's risk free rate, country default rate and corporate default spread rate based on company's debt rating and interest coverage ration.
B26: 2. Asset Beta is considered as Median of 5 Years beta of comps adjusted for blume effect.
B27: 3. Equity Beta = Asset Beta * (1+(1-Tax Rate )* Debt / Equity
H29: Small Size Premium
H31: Empirically small size assets premium have expected the return as compared to large sized assets. We have used the study on size premium conducted by incwert which is based on difference between actual return and CAPM expected returns arranged in decile basis market capitalization of indian Companies.
H35: Asset Specific Premium
B42: Epigral Ltd.
B43: Beta Analysis - 2 Years Weekly
A45: # | B45: Comparables Company | D45: Ticker | E45: No. of Weekly Observations | F45: Market Cap | G45: Asset Beta | H45: 2 Years Avg D/E | I45: Equity Beta | J45: 2 Years avg D/(D+E) | L45: Considered? | M45: Narrow set
B46: Gujarat Alkalies & Chemicals Ltd (GAKL) | D46: GAKL | E46: 105 | F46: 3259 | G46: ='Beta Calculation'!F3 -> 1.1194237 | H46: ='Beta Calculation'!D3 -> 0.049479626 | I46: ='Beta Calculation'!C3 -> 1.160871 | J46: ='Beta Calculation'!E3 -> 0.045024077 | L46: Yes | M46: =IF(L46="Yes","True","False") -> True
B47: Gujarat Narmada Valley Fertilizers & Chemicals Ltd (GNFC) | D47: GNFC | E47: 105 | F47: 6955 | G47: ='Beta Calculation'!F4 -> 1.3051965 | H47: ='Beta Calculation'!D4 -> 0.0063605645 | I47: ='Beta Calculation'!C4 -> 1.3114087 | J47: ='Beta Calculation'!E4 -> 0.0062850462 | L47: Yes | M47: =IF(L47="Yes","True","False") -> True | O47: Yes
B48: Grasim Industries Ltd | D48: GRASIM | E48: 105 | F48: 189015 | G48: ='Beta Calculation'!F5 -> 0.52701761 | H48: ='Beta Calculation'!D5 -> 1.7289794 | I48: ='Beta Calculation'!C5 -> 1.2088705 | J48: ='Beta Calculation'!E5 -> 0.6319277 | L48: No | M48: =IF(L48="Yes","True","False") -> False | O48: No
B49: Chemplast Sanmar Ltd | D49: CHEMPLASTS | E49: 105 | F49: 4032 | G49: ='Beta Calculation'!F6 -> 0.71824921 | H49: ='Beta Calculation'!D6 -> 0.90038429 | I49: ='Beta Calculation'!C6 -> 1.202175 | J49: ='Beta Calculation'!E6 -> 0.47377702 | L49: Yes | M49: =IF(L49="Yes","True","False") -> True
B50: SRF | D50: SRF | E50: 105 | F50: 83021 | G50: ='Beta Calculation'!F7 -> 0.61356018 | H50: ='Beta Calculation'!D7 -> 0.40629279 | I50: ='Beta Calculation'!C7 -> 0.80010021 | J50: ='Beta Calculation'!E7 -> 0.28854247 | L50: No | M50: =IF(L50="Yes","True","False") -> False
B51: TGV SRACC LTD | D51: TGV SRACC | E51: 105 | F51: 921 | G51: ='Beta Calculation'!F8 -> 1.0953081 | H51: ='Beta Calculation'!D8 -> 0.29796962 | I51: ='Beta Calculation'!C8 -> 1.3395297 | J51: ='Beta Calculation'!E8 -> 0.22955411 | L51: No | M51: =IF(L51="Yes","True","False") -> False
B52: Primo Chemicals | D52: PRIMO | E52: 105 | F52: 476 | G52: ='Beta Calculation'!F9 -> 0.53716896 | H52: ='Beta Calculation'!D9 -> 0.44664083 | I52: ='Beta Calculation'!C9 -> 0.71670229 | J52: ='Beta Calculation'!E9 -> 0.30868491 | L52: No | M52: =IF(L52="Yes","True","False") -> False
B53: Deepak Nitrite | D53: DEEPAKNITRITE | E53: 105 | F53: 22162 | G53: ='Beta Calculation'!F10 -> 0.93561856 | H53: ='Beta Calculation'!D10 -> 0.14739261 | I53: ='Beta Calculation'!C10 -> 1.0388116 | J53: ='Beta Calculation'!E10 -> 0.12333011 | L53: No | M53: =IF(L53="Yes","True","False") -> False
B55: Median - Broad Set | G55: =MEDIAN(G46:G53) -> 0.82693389 | H55: =MEDIAN(H46:H53) -> 0.35213121 | I55: =MEDIAN(I46:I53) -> 1.181523 | J55: =MEDIAN(J46:J53) -> 0.25904829
B56: Average - Broad Set | G56: =AVERAGE(G46:G53) -> 0.85644285 | H56: =AVERAGE(H46:H53) -> 0.49793747 | I56: =AVERAGE(I46:I53) -> 1.0973086 | J56: =AVERAGE(J46:J53) -> 0.26339068
B58: Median - Considered Set | G58: {=MEDIAN(IF($M$46:$M$53,G46:G53))} -> 1.1194237 | H58: {=MEDIAN(IF($M$46:$M$53,H46:H53))} -> 0.049479626 | I58: {=MEDIAN(IF($M$46:$M$53,I46:I53))} -> 1.202175 | J58: {=MEDIAN(IF($M$46:$M$53,J46:J53))} -> 0.045024077
B59: Average - Considered Set | G59: {=AVERAGE(IF($M$46:$M$53,G46:G53))} -> 1.0476231 | H59: {=AVERAGE(IF($M$46:$M$53,H46:H53))} -> 0.31874149 | I59: {=AVERAGE(IF($M$46:$M$53,I46:I53))} -> 1.2248183 | J59: {=AVERAGE(IF($M$46:$M$53,J46:J53))} -> 0.17502871
B61: Epigral Ltd.
B62: Beta Analysis - 5 Years Monthly
A64: # | B64: Comparables Company | D64: Ticker | E64: No. of Weekly Observations | F64: Market Cap | G64: Asset Beta | H64: 5 Years Avg D/E | I64: Equity Beta | J64: 5 Years avg D/(D+E) | L64: Considered? | M64: Narrow set
B65: Gujarat Alkalies & Chemicals Ltd (GAKL) | D65: GAKL | E65: 60 | F65: 3259 | G65: ='Beta Calculation'!K3 -> 1.4366831 | H65: ='Beta Calculation'!I3 -> 0.077913959 | I65: ='Beta Calculation'!H3 -> 1.5204461 | J65: ='Beta Calculation'!J3 -> 0.070993764 | L65: Yes | M65: =IF(L65="Yes","True","False") -> True
B66: Gujarat Narmada Valley Fertilizers & Chemicals Ltd (GNFC) | D66: GNFC | E66: 60 | F66: 6955 | G66: ='Beta Calculation'!K4 -> 1.2912424 | H66: ='Beta Calculation'!I4 -> 0.0027700594 | I66: ='Beta Calculation'!H4 -> 1.2939189 | J66: ='Beta Calculation'!J4 -> 0.0027397431 | L66: Yes | M66: =IF(L66="Yes","True","False") -> True
B67: Grasim Industries Ltd | D67: GRASIM | E67: 60 | F67: 189015 | G67: ='Beta Calculation'!K5 -> 0.56923278 | H67: ='Beta Calculation'!I5 -> 1.3922632 | I67: ='Beta Calculation'!H5 -> 1.1622769 | J67: ='Beta Calculation'!J5 -> 0.57489838 | L67: No | M67: =IF(L67="Yes","True","False") -> False
B68: Chemplast Sanmar Ltd | D68: CHEMPLASTS | E68: 60 | F68: 4032 | G68: ='Beta Calculation'!K6 -> 0.74193691 | H68: ='Beta Calculation'!I6 -> 0.57330196 | I68: ='Beta Calculation'!H6 -> 1.0602292 | J68: ='Beta Calculation'!J6 -> 0.56792781 | L68: Yes | M68: =IF(L68="Yes","True","False") -> True
B69: SRF | D69: SRF | E69: 60 | F69: 83021 | G69: ='Beta Calculation'!K7 -> 0.72171996 | H69: ='Beta Calculation'!I7 -> 0.43578461 | I69: ='Beta Calculation'!H7 -> 0.95707112 | J69: ='Beta Calculation'!J7 -> 0.30292616 | L69: No | M69: =IF(L69="Yes","True","False") -> False
B70: TGV SRACC LTD | D70: TGV SRACC | E70: 60 | F70: 921 | G70: ='Beta Calculation'!K8 -> 0.53523655 | H70: ='Beta Calculation'!I8 -> 0.4516278 | I70: ='Beta Calculation'!H8 -> 0.71612139 | J70: ='Beta Calculation'!J8 -> 0.2949532 | L70: No | M70: =IF(L70="Yes","True","False") -> False
B71: Primo Chemicals | D71: PRIMO | E71: 60 | F71: 476 | G71: ='Beta Calculation'!K9 -> 0.27993502 | H71: ='Beta Calculation'!I9 -> 0.29530943 | I71: ='Beta Calculation'!H9 -> 0.34179507 | J71: ='Beta Calculation'!J9 -> 0.21378119 | L71: No | M71: =IF(L71="Yes","True","False") -> False
B72: Deepak Nitrite | D72: DEEPAKNITRITE | E72: 60 | F72: 22162 | G72: ='Beta Calculation'!K10 -> 1.4056224 | H72: ='Beta Calculation'!I10 -> 0.13169868 | I72: ='Beta Calculation'!H10 -> 1.5441467 | J72: ='Beta Calculation'!J10 -> 0.11027597 | L72: No | M72: =IF(L72="Yes","True","False") -> False
B75: Median - Broad Set | G75: =MEDIAN(G65:G72) -> 0.73182844 | H75: =MEDIAN(H65:H72) -> 0.36554702 | I75: =MEDIAN(I65:I72) -> 1.1112531 | J75: =MEDIAN(J65:J72) -> 0.2543672
B76: Average - Broad Set | G76: =AVERAGE(G65:G72) -> 0.87270114 | H76: =AVERAGE(H65:H72) -> 0.42008372 | I76: =AVERAGE(I65:I72) -> 1.0745007 | J76: =AVERAGE(J65:J72) -> 0.26731203
B78: Median - Considered Set | G78: {=MEDIAN(IF($M$65:$M$72,G65:G72))} -> 1.2912424 | H78: {=MEDIAN(IF($M$65:$M$72,H65:H72))} -> 0.077913959 | I78: {=MEDIAN(IF($M$65:$M$72,I65:I72))} -> 1.2939189 | J78: {=MEDIAN(IF($M$65:$M$72,J65:J72))} -> 0.070993764
B79: Average - Considered Set | G79: {=AVERAGE(IF($M$65:$M$72,G65:G72))} -> 1.1566208 | H79: {=AVERAGE(IF($M$65:$M$72,H65:H72))} -> 0.21799533 | I79: {=AVERAGE(IF($M$65:$M$72,I65:I72))} -> 1.2915314 | J79: {=AVERAGE(IF($M$65:$M$72,J65:J72))} -> 0.21388711
B82: Epigral Ltd.
B83: Blume Beta Analysis - 5 Years Monthly | D83: `2/3 - Beta *1/3* Market Beta | H83: 0.2517
A85: # | B85: Comparables Company | D85: Ticker | E85: No. of Weekly Observations | F85: Market Cap | G85: Asset Beta | H85: 5 Years Avg D/E | I85: Equity Beta | J85: 5 Years avg D/(D+E) | K85: Considered? | L85: Narrow set
B86: Gujarat Alkalies & Chemicals Ltd (GAKL) | D86: GAKL | E86: 60 | F86: 3259 | G86: =I86/(1+(1-$H$83)*H86) -> 1.2212404 | H86: =H65 -> 0.077913959 | I86: =0.33+0.633*I65 -> 1.2924424 | J86: =J65 -> 0.070993764 | K86: Yes | L86: =IF(K86="Yes","True","False") -> True
B87: Gujarat Narmada Valley Fertilizers & Chemicals Ltd (GNFC) | D87: GNFC | E87: 60 | F87: 6955 | G87: =I87/(1+(1-$H$83)*H87) -> 1.1466738 | H87: =H66 -> 0.0027700594 | I87: =0.33+0.633*I66 -> 1.1490507 | J87: =J66 -> 0.0027397431 | K87: Yes | L87: =IF(K87="Yes","True","False") -> True
B88: Grasim Industries Ltd | D88: GRASIM | E88: 60 | F88: 189015 | G88: =I88/(1+(1-$H$83)*H88) -> 0.52194403 | H88: =H67 -> 1.3922632 | I88: =0.33+0.633*I67 -> 1.0657213 | J88: =J67 -> 0.57489838 | K88: No | L88: =IF(K88="Yes","True","False") -> False
B89: Chemplast Sanmar Ltd | D89: CHEMPLASTS | E89: 60 | F89: 4032 | G89: =I89/(1+(1-$H$83)*H89) -> 0.70057649 | H89: =H68 -> 0.57330196 | I89: =0.33+0.633*I68 -> 1.0011251 | J89: =J68 -> 0.56792781 | K89: Yes | L89: =IF(K89="Yes","True","False") -> True
B90: SRF | D90: SRF | E90: 60 | F90: 83021 | G90: =I90/(1+(1-$H$83)*H90) -> 0.70569919 | H90: =H69 -> 0.43578461 | I90: =0.33+0.633*I69 -> 0.93582602 | J90: =J69 -> 0.30292616 | K90: No | L90: =IF(K90="Yes","True","False") -> False
B91: TGV SRACC LTD | D91: TGV SRACC | E91: 60 | F91: 921 | G91: =I91/(1+(1-$H$83)*H91) -> 0.58545016 | H91: =H70 -> 0.4516278 | I91: =0.33+0.633*I70 -> 0.78330484 | J91: =J70 -> 0.2949532 | K91: No | L91: =IF(K91="Yes","True","False") -> False
B92: Primo Chemicals | D92: PRIMO | E92: 60 | F92: 476 | G92: =I92/(1+(1-$H$83)*H92) -> 0.44747355 | H92: =H71 -> 0.29530943 | I92: =0.33+0.633*I71 -> 0.54635628 | J92: =J71 -> 0.21378119 | K92: No | L92: =IF(K92="Yes","True","False") -> False
B93: Deepak Nitrite | D93: DEEPAKNITRITE | E93: 60 | F93: 22162 | G93: =I93/(1+(1-$H$83)*H93) -> 1.1901549 | H93: =H72 -> 0.13169868 | I93: =0.33+0.633*I72 -> 1.3074448 | J93: =J72 -> 0.11027597 | K93: No | L93: =IF(K93="Yes","True","False") -> False
B96: Median - Broad Set | G96: =MEDIAN(G86:G93) -> 0.70313784 | H96: =MEDIAN(H86:H93) -> 0.36554702 | I96: =MEDIAN(I86:I93) -> 1.0334232 | J96: =MEDIAN(J86:J93) -> 0.2543672
B97: Average - Broad Set | G97: =AVERAGE(G86:G93) -> 0.81490156 | H97: =AVERAGE(H86:H93) -> 0.42008372 | I97: =AVERAGE(I86:I93) -> 1.0101589 | J97: =AVERAGE(J86:J93) -> 0.26731203
B99: Median - Considered Set | G99: {=MEDIAN(IF($L$86:$L$93,G86:G93))} -> 1.1466738 | H99: {=MEDIAN(IF($L$86:$L$93,H86:H93))} -> 0.077913959 | I99: {=MEDIAN(IF($L$86:$L$93,I86:I93))} -> 1.1490507 | J99: {=MEDIAN(IF($L$86:$L$93,J86:J93))} -> 0.070993764
B100: Average - Considered Set | G100: {=AVERAGE(IF($L$86:$L$93,G86:G93))} -> 1.0228302 | H100: {=AVERAGE(IF($L$86:$L$93,H86:H93))} -> 0.21799533 | I100: {=AVERAGE(IF($L$86:$L$93,I86:I93))} -> 1.1475394 | J100: {=AVERAGE(IF($L$86:$L$93,J86:J93))} -> 0.21388711
B102: We are taking 1.02 as Asset beta of Chemicals Units

Sheet DCF Value
B2: ='Input Sheet'!C5 -> Epigral Ltd. | U2: Yes | X2: Mid Year Convenstion
B3: DCF MODEL | J3: Current Case | K3: 2 | U3: No | X3: Yes
X4: No
E7: Actual | J7: Explicit Forecast Period | R7: Terminal Value
B8: In INR Crores Other wise Stated | E8: ='Ratio Analysis'!D8 -> 2021 | F8: ='Ratio Analysis'!E8 -> 2022 | G8: ='Ratio Analysis'!F8 -> 2023 | H8: ='Ratio Analysis'!G8 -> 2024 | I8: ='Ratio Analysis'!H8 -> 2025 | J8: ='Ratio Analysis'!I8 -> 2026 | K8: ='Ratio Analysis'!J8 -> 2027 | L8: ='Ratio Analysis'!K8 -> 2028 | ... W8: ='Ratio Analysis'!V8 -> 2039
A10: # | B10: Free Cash Flow to Firm
B11: EBITDA | E11: ='3 Statement Model'!D24 -> 261.8 | F11: ='3 Statement Model'!E24 -> 510.2 | G11: ='3 Statement Model'!F24 -> 689.4 | H11: ='3 Statement Model'!G24 -> 480.7 | I11: ='3 Statement Model'!H24 -> 711.4 | J11: ='3 Statement Model'!I24 -> 769.08 | K11: ='3 Statement Model'!J24 -> 959.93016 | L11: ='3 Statement Model'!K24 -> 1199.9127 | ... W11: ='3 Statement Model'!V24 -> 7211.725
B12: Less: Depreciation | E12: ='3 Statement Model'!D29*-1 -> -70.77 | F12: ='3 Statement Model'!E29*-1 -> -82.67 | G12: ='3 Statement Model'!F29*-1 -> -105.72 | H12: ='3 Statement Model'!G29*-1 -> -120.33 | I12: ='3 Statement Model'!H29*-1 -> -129.33 | J12: ='3 Statement Model'!I29*-1 -> -161.47286 | K12: ='3 Statement Model'!J29*-1 -> -204.33 | L12: ='3 Statement Model'!K29*-1 -> -257.90143 | ... W12: ='3 Statement Model'!V29*-1 -> -1425.5758
